Workbook
Name PtsPerWin: SETTINGS!$B$39
Name RatingRange: SETTINGS!$B$36
Name CLOppP0c: CLEAN!$AM$3:$AM$722
Name AsOfDate: SETTINGS!$B$7
Name CalcGP: CALC!$B$2:$B$33
Name MinGamesTrust: SETTINGS!$B$19
Name RatEff: 'TEAM RATINGS'!$J$5:$J$36
Name FavList: LISTS!$B$2:$B$34
Name MktGameID: 'MARKET LINES'!$B$5:$B$304
Name CLGameID: CLEAN!$D$3:$D$722
Name AdjGameID: ADJUSTMENTS!$A$5:$A$104
Name QBSpreadEff: 'QB VALUES'!$G$5:$G$36
Name DQStatus: 'DATA QUALITY'!$P$12:$P$311
Name WinTotalsMode: SETTINGS!$B$40
Name CLPerf: CLEAN!$AE$3:$AE$722
Name BetTot: SETTINGS!$B$29
Name CLOppP1cPv: CLEAN!$AQ$3:$AQ$722
Name CalcOffPl: CALC!$AG$2:$AG$33
Name AdjTeam: ADJUSTMENTS!$B$5:$B$104
Name CLPlays: CLEAN!$Q$3:$Q$722
Name HFAexcTeam: SETTINGS!$A$65:$A$70
Name MktCheck: 'MARKET LINES'!$R$5:$R$304
Name CalcGoverned: CALC!$AD$2:$AD$33
Name PriorEff: PRESEASON!$S$5:$S$36
Name QBStaleDays: SETTINGS!$B$68
Name DQGameID: 'DATA QUALITY'!$B$12:$B$311
Name CLOpp: CLEAN!$K$3:$K$722
Name QBActive: 'QB VALUES'!$D$5:$D$36
Name BlendWts: SETTINGS!$B$44:$B$61
Name WEpa: SETTINGS!$B$12
Name MktHomeSpread: 'MARKET LINES'!$Q$5:$Q$304
Name LeaguePlays: CALC!$B$37
Name TotRegress: SETTINGS!$B$21
Name QBTotEff: 'QB VALUES'!$H$5:$H$36
Name CLOppP2c: CLEAN!$AO$3:$AO$722
Name AdjSpread: ADJUSTMENTS!$E$5:$E$104
Name AdjCap: SETTINGS!$B$34
Name CLOppP1c: CLEAN!$AN$3:$AN$722
Name CLTeam: CLEAN!$I$3:$I$722
Name NeutralHFA: SETTINGS!$B$10
Name MoveCap: SETTINGS!$B$17
Name MktTotal: 'MARKET LINES'!$I$5:$I$304
Name CalcDefAdj: CALC!$AN$2:$AN$33
Name RestCapPts: SETTINGS!$B$16
Name CLUseCur: CLEAN!$AF$3:$AF$722
Name StatsZone: 'IMPORT STATS'!$A$6:$EC$625
Name TotRecency: SETTINGS!$B$22
Name DstPts: CALC!$B$38
Name CLWeek: CLEAN!$G$3:$G$722
Name CLOffPts: CLEAN!$V$3:$V$722
Name MinGamesEnh: SETTINGS!$B$18
Name DQWeek: 'DATA QUALITY'!$C$12:$C$311
Name AdjTot: ADJUSTMENTS!$F$5:$F$104
Name MktStale: 'MARKET LINES'!$S$5:$S$304
Name Teams: LISTS!$A$2:$A$33
Name StatsKey: 'IMPORT STATS'!$EE$6:$EE$625
Name BlendWeeks: SETTINGS!$A$44:$A$61
Name QBTotFactor: SETTINGS!$B$24
Name EngWeek: ENGINE!$C$5:$C$304
Name CLWgtPrev: CLEAN!$AI$3:$AI$722

Sheet START HERE
A1: TO THE WINDOW — NFL POWER RATINGS 2026 (v1.1)
A2: Google Sheets-first · nflverse data in, opponent-adjusted ratings out, Novig lines for edges · no picks sold here, just process
A4: WEEKLY ROUTINE (25-40 min). Status lights update live.
A5: Step | B5: What to do | C5: Status
A6: 1 | B6: Set SETTINGS → Current week + As-of date | C6: =IF(AND(CurrentWeek>=1,CurrentWeek<=22),"OK — week "&CurrentWeek,"⚠ SET WEEK") -> OK — week 1
A7: 2 | B7: Download the two nflverse files (links in DICTIONARY tab) | C7: —
A8: 3 | B8: Paste stats_team_week CSV into IMPORT STATS at A6 (whole file, replaces old) | C8: =IF(CurrentWeek=1,"— (preseason: priors drive ratings)",IF(COUNTIFS(CLWeek,CurrentWeek-1,CLUseCur,1)>=20,"OK — week "&(CurrentWeek-1)&" stats loaded","⚠ WEEK "&(CurrentWeek-1)&" STATS NOT FOUND — REPASTE IMPORT STATS")) -> — (preseason: priors drive ratings)
A9: 4 | B9: Paste games.csv rows for your season(s) into IMPORT SCHEDULE at A6 | C9: =IF(COUNT(SchedSeq)>0,"OK — "&COUNT(SchedSeq)&" games loaded for season "&CurrentSeason,"⚠ NO CURRENT-SEASON GAMES FOUND") -> OK — 272 games loaded for season 2026
A10: 5 | B10: Confirm QB VALUES — active starter, delta, confidence, "Reviewed for season" = current season, fresh update date | C10: =IF(SUMPRODUCT((QBActive="")*1)=0,"OK","⚠ "&SUMPRODUCT((QBActive="")*1)&" TEAMS BLANK") -> OK
A11: 6 | B11: Enter Novig lines in MARKET LINES (favorite + positive spread + total + line date) | C11: ="Missing: "&(SUMPRODUCT((EngWeek=CurrentWeek)*(EngGameID<>"")*1)-SUMPRODUCT((MktHomeSpread<>"")*(EngWeek=CurrentWeek)*1))&" spreads · "&(SUMPRODUCT((EngWeek=CurrentWeek)*(EngGameID<>"")*1)-SUMPRODUCT((MktTotal<>"")*(EngWeek=CurrentWeek)*1))&" totals" -> Missing: 16 spreads · 16 totals
A12: 7 | B12: Log injuries/situational spots in ADJUSTMENTS (explanation required) | C12: —
A13: 8 | B13: Clear DATA QUALITY, then work the DASHBOARD by Review Priority | C13: =IF(SUMPRODUCT((DQStatus="BLOCKED")*(DQWeek=CurrentWeek))=0,"OK — nothing blocked","⚠ "&SUMPRODUCT((DQStatus="BLOCKED")*(DQWeek=CurrentWeek))&" GAME(S) BLOCKED") -> OK — nothing blocked
A15: SIGN CONVENTION — worked example (this trips everyone once)
A16: • Market: Home team favored by 3 → you enter Favorite=HOME, Spread=3 → sheet stores market home spread = -3.0
A17: • Model: FinalMargin = +5.0 (model says home wins by 5) → model spread displays HOME -5.0
A18: • SpreadEdge = FinalMargin + market home spread = 5.0 + (-3.0) = +2.0 → positive = value on HOME at -3.0
A19: • If FinalMargin were +1.0: edge = 1.0 + (-3.0) = -2.0 → negative = value on AWAY at +3.0
A21: TAB MAP
A22: DASHBOARD | B22: This week at a glance, sorted by your attention priority
A23: ENGINE | B23: Every game, every bridge step from ratings to final number
A24: MARKET LINES | B24: Novig entry (favorite + positive spread), OddsLogic reference columns
A25: ADJUSTMENTS | B25: Every subjective point you add, documented and reversible
A26: QB VALUES | B26: Baseline-delta QB system — only deltas move projections
A27: TEAM RATINGS | B27: Final effective ratings + mode + override column
A28: DATA QUALITY | B28: What is blocked and why
A29: SETTINGS | B29: Every weight and threshold, backtest defaults noted
A30: IMPORT tabs | B30: Paste zones for the two nflverse files
A31: Hidden: MAP/CLEAN/CALC | B31: The pipeline — unhide to audit, never edit
A32: Hidden: PRESEASON | B32: Prior blend for season start (2026 priors pre-loaded)
A33: Hidden: HISTORY 2025/BACKTEST/AUDIT/DICTIONARY/CHANGELOG | B33: Receipts: methodology, tests, definitions

Sheet DASHBOARD
A1: WEEKLY DASHBOARD
A2: =CONCATENATE("Season ",CurrentSeason," · Week ",CurrentWeek," · ",TEXT(R3,"0")," games · set week in SETTINGS") -> Season 2026 · Week 1 · 16 games · set week in SETTINGS
A3: ⚠ Labels mark model-vs-market DIVERGENCE thresholds, not proven betting profitability. 2025 was both calibration and evaluation; 2026 is the first out-of-sample test. BET labels are OFF by default (SETTINGS → Enable BET labels). | R3: =SUMPRODUCT((EngWeek=CurrentWeek)*(EngGameID<>"")) -> 16
A4: Game | B4: Date | C4: Market spread | D4: Model spread | E4: Edge (side @ market) | F4: ATS REC | G4: Market total | H4: Model total | I4: O/U edge | J4: TOTAL REC | K4: Total trigger | L4: Status | M4: DQ | N4: Priority | O4: Rank | P4: Mode (A/H) | Q4: Notes
A5: {=IF(IFERROR(MATCH(1,EngDash,0),"")="","",INDEX(ENGINE!$E$5:$E$304,MATCH(1,EngDash,0))&" @ "&INDEX(ENGINE!$F$5:$F$304,MATCH(1,EngDash,0))&IF(INDEX(ENGINE!$G$5:$G$304,MATCH(1,EngDash,0))="Y"," (N)",""))} -> NE @ SEA | B5: {=IF($A5="","",INDEX(ENGINE!$D$5:$D$304,MATCH(1,EngDash,0)))} -> 46274 | C5: {=IF($A5="","",IF(INDEX(ENGINE!$U$5:$U$304,MATCH(1,EngDash,0))="","PENDING",INDEX(ENGINE!$F$5:$F$304,MATCH(1,EngDash,0))&" "&TEXT(INDEX(ENGINE!$U$5:$U$304,MATCH(1,EngDash,0)),"+0.0;-0.0;""PK""")))} -> PENDING | D5: {=IF($A5="","",INDEX(ENGINE!$T$5:$T$304,MATCH(1,EngDash,0)))} -> SEA -3.6 | E5: {=IF($A5="","",IF(INDEX(ENGINE!$V$5:$V$304,MATCH(1,EngDash,0))="","",TEXT(INDEX(ENGINE!$W$5:$W$304,MATCH(1,EngDash,0)),"0.0")&" — "&INDEX(ENGINE!$X$5:$X$304,MATCH(1,EngDash,0))))} | F5: {=IF($A5="","",INDEX(ENGINE!$Z$5:$Z$304,MATCH(1,EngDash,0)))} | G5: {=IF($A5="","",INDEX(ENGINE!$AH$5:$AH$304,MATCH(1,EngDash,0)))} | H5: {=IF($A5="","",INDEX(ENGINE!$AG$5:$AG$304,MATCH(1,EngDash,0)))} -> 0 | I5: {=IF($A5="","",IF(INDEX(ENGINE!$AI$5:$AI$304,MATCH(1,EngDash,0))="","",INDEX(ENGINE!$AK$5:$AK$304,MATCH(1,EngDash,0))&" "&TEXT(INDEX(ENGINE!$AJ$5:$AJ$304,MATCH(1,EngDash,0)),"0.0")))} | J5: {=IF($A5="","",INDEX(ENGINE!$AM$5:$AM$304,MATCH(1,EngDash,0)))} | K5: {=IF($A5="","",INDEX(ENGINE!$AN$5:$AN$304,MATCH(1,EngDash,0)))} -> BET OVER at ≤ -3.0 | BET UNDER at ≥ 3.0 | L5: {=IF($A5="","",INDEX(ENGINE!$AQ$5:$AQ$304,MATCH(1,EngDash,0)))} -> PENDING BOTH | M5: {=IF($A5="","",INDEX(ENGINE!$AP$5:$AP$304,MATCH(1,EngDash,0)))} -> READY | N5: {=IF($A5="","",INDEX(ENGINE!$AS$5:$AS$304,MATCH(1,EngDash,0)))} -> 50 | O5: {=IF($A5="","",INDEX(ENGINE!$AT$5:$AT$304,MATCH(1,EngDash,0)))} -> 1 | P5: {=IF($A5="","",INDEX(RatMode,MATCH(INDEX(ENGINE!$E$5:$E$304,MATCH(1,EngDash,0)),RatTeams,0))&"/"&INDEX(RatMode,MATCH(INDEX(ENGINE!$F$5:$F$304,MATCH(1,EngDash,0)),RatTeams,0)))} -> BASIC/BASIC | Q5: {=IF($A5="","",INDEX(ENGINE!$AU$5:$AU$304,MATCH(1,EngDash,0)))}
A6: {=IF(IFERROR(MATCH(2,EngDash,0),"")="","",INDEX(ENGINE!$E$5:$E$304,MATCH(2,EngDash,0))&" @ "&INDEX(ENGINE!$F$5:$F$304,MATCH(2,EngDash,0))&IF(INDEX(ENGINE!$G$5:$G$304,MATCH(2,EngDash,0))="Y"," (N)",""))} -> SF @ LA (N) | B6: {=IF($A6="","",INDEX(ENGINE!$D$5:$D$304,MATCH(2,EngDash,0)))} -> 46275 | C6: {=IF($A6="","",IF(INDEX(ENGINE!$U$5:$U$304,MATCH(2,EngDash,0))="","PENDING",INDEX(ENGINE!$F$5:$F$304,MATCH(2,EngDash,0))&" "&TEXT(INDEX(ENGINE!$U$5:$U$304,MATCH(2,EngDash,0)),"+0.0;-0.0;""PK""")))} -> PENDING | D6: {=IF($A6="","",INDEX(ENGINE!$T$5:$T$304,MATCH(2,EngDash,0)))} -> LA -2.3 | E6: {=IF($A6="","",IF(INDEX(ENGINE!$V$5:$V$304,MATCH(2,EngDash,0))="","",TEXT(INDEX(ENGINE!$W$5:$W$304,MATCH(2,EngDash,0)),"0.0")&" — "&INDEX(ENGINE!$X$5:$X$304,MATCH(2,EngDash,0))))} | F6: {=IF($A6="","",INDEX(ENGINE!$Z$5:$Z$304,MATCH(2,EngDash,0)))} | G6: {=IF($A6="","",INDEX(ENGINE!$AH$5:$AH$304,MATCH(2,EngDash,0)))} | H6: {=IF($A6="","",INDEX(ENGINE!$AG$5:$AG$304,MATCH(2,EngDash,0)))} -> 0 | I6: {=IF($A6="","",IF(INDEX(ENGINE!$AI$5:$AI$304,MATCH(2,EngDash,0))="","",INDEX(ENGINE!$AK$5:$AK$304,MATCH(2,EngDash,0))&" "&TEXT(INDEX(ENGINE!$AJ$5:$AJ$304,MATCH(2,EngDash,0)),"0.0")))} | J6: {=IF($A6="","",INDEX(ENGINE!$AM$5:$AM$304,MATCH(2,EngDash,0)))} | K6: {=IF($A6="","",INDEX(ENGINE!$AN$5:$AN$304,MATCH(2,EngDash,0)))} -> BET OVER at ≤ -3.0 | BET UNDER at ≥ 3.0 | L6: {=IF($A6="","",INDEX(ENGINE!$AQ$5:$AQ$304,MATCH(2,EngDash,0)))} -> PENDING BOTH | M6: {=IF($A6="","",INDEX(ENGINE!$AP$5:$AP$304,MATCH(2,EngDash,0)))} -> READY | N6: {=IF($A6="","",INDEX(ENGINE!$AS$5:$AS$304,MATCH(2,EngDash,0)))} -> 50 | O6: {=IF($A6="","",INDEX(ENGINE!$AT$5:$AT$304,MATCH(2,EngDash,0)))} -> 1 | P6: {=IF($A6="","",INDEX(RatMode,MATCH(INDEX(ENGINE!$E$5:$E$304,MATCH(2,EngDash,0)),RatTeams,0))&"/"&INDEX(RatMode,MATCH(INDEX(ENGINE!$F$5:$F$304,MATCH(2,EngDash,0)),RatTeams,0)))} -> BASIC/BASIC | Q6: {=IF($A6="","",INDEX(ENGINE!$AU$5:$AU$304,MATCH(2,EngDash,0)))}
A7: {=IF(IFERROR(MATCH(3,EngDash,0),"")="","",INDEX(ENGINE!$E$5:$E$304,MATCH(3,EngDash,0))&" @ "&INDEX(ENGINE!$F$5:$F$304,MATCH(3,EngDash,0))&IF(INDEX(ENGINE!$G$5:$G$304,MATCH(3,EngDash,0))="Y"," (N)",""))} -> CHI @ CAR | B7: {=IF($A7="","",INDEX(ENGINE!$D$5:$D$304,MATCH(3,EngDash,0)))} -> 46278 | C7: {=IF($A7="","",IF(INDEX(ENGINE!$U$5:$U$304,MATCH(3,EngDash,0))="","PENDING",INDEX(ENGINE!$F$5:$F$304,MATCH(3,EngDash,0))&" "&TEXT(INDEX(ENGINE!$U$5:$U$304,MATCH(3,EngDash,0)),"+0.0;-0.0;""PK""")))} -> PENDING | D7: {=IF($A7="","",INDEX(ENGINE!$T$5:$T$304,MATCH(3,EngDash,0)))} -> CHI -0.6 | E7: {=IF($A7="","",IF(INDEX(ENGINE!$V$5:$V$304,MATCH(3,EngDash,0))="","",TEXT(INDEX(ENGINE!$W$5:$W$304,MATCH(3,EngDash,0)),"0.0")&" — "&INDEX(ENGINE!$X$5:$X$304,MATCH(3,EngDash,0))))} | F7: {=IF($A7="","",INDEX(ENGINE!$Z$5:$Z$304,MATCH(3,EngDash,0)))} | G7: {=IF($A7="","",INDEX(ENGINE!$AH$5:$AH$304,MATCH(3,EngDash,0)))} | H7: {=IF($A7="","",INDEX(ENGINE!$AG$5:$AG$304,MATCH(3,EngDash,0)))} -> 0 | I7: {=IF($A7="","",IF(INDEX(ENGINE!$AI$5:$AI$304,MATCH(3,EngDash,0))="","",INDEX(ENGINE!$AK$5:$AK$304,MATCH(3,EngDash,0))&" "&TEXT(INDEX(ENGINE!$AJ$5:$AJ$304,MATCH(3,EngDash,0)),"0.0")))} | J7: {=IF($A7="","",INDEX(ENGINE!$AM$5:$AM$304,MATCH(3,EngDash,0)))} | K7: {=IF($A7="","",INDEX(ENGINE!$AN$5:$AN$304,MATCH(3,EngDash,0)))} -> BET OVER at ≤ -3.0 | BET UNDER at ≥ 3.0 | L7: {=IF($A7="","",INDEX(ENGINE!$AQ$5:$AQ$304,MATCH(3,EngDash,0)))} -> PENDING BOTH | M7: {=IF($A7="","",INDEX(ENGINE!$AP$5:$AP$304,MATCH(3,EngDash,0)))} -> READY | N7: {=IF($A7="","",INDEX(ENGINE!$AS$5:$AS$304,MATCH(3,EngDash,0)))} -> 50 | O7: {=IF($A7="","",INDEX(ENGINE!$AT$5:$AT$304,MATCH(3,EngDash,0)))} -> 1 | P7: {=IF($A7="","",INDEX(RatMode,MATCH(INDEX(ENGINE!$E$5:$E$304,MATCH(3,EngDash,0)),RatTeams,0))&"/"&INDEX(RatMode,MATCH(INDEX(ENGINE!$F$5:$F$304,MATCH(3,EngDash,0)),RatTeams,0)))} -> BASIC/BASIC | Q7: {=IF($A7="","",INDEX(ENGINE!$AU$5:$AU$304,MATCH(3,EngDash,0)))}
A8: {=IF(IFERROR(MATCH(4,EngDash,0),"")="","",INDEX(ENGINE!$E$5:$E$304,MATCH(4,EngDash,0))&" @ "&INDEX(ENGINE!$F$5:$F$304,MATCH(4,EngDash,0))&IF(INDEX(ENGINE!$G$5:$G$304,MATCH(4,EngDash,0))="Y"," (N)",""))} -> TB @ CIN | B8: {=IF($A8="","",INDEX(ENGINE!$D$5:$D$304,MATCH(4,EngDash,0)))} -> 46278 | C8: {=IF($A8="","",IF(INDEX(ENGINE!$U$5:$U$304,MATCH(4,EngDash,0))="","PENDING",INDEX(ENGINE!$F$5:$F$304,MATCH(4,EngDash,0))&" "&TEXT(INDEX(ENGINE!$U$5:$U$304,MATCH(4,EngDash,0)),"+0.0;-0.0;""PK""")))} -> PENDING | D8: {=IF($A8="","",INDEX(ENGINE!$T$5:$T$304,MATCH(4,EngDash,0)))} -> CIN -0.6 | E8: {=IF($A8="","",IF(INDEX(ENGINE!$V$5:$V$304,MATCH(4,EngDash,0))="","",TEXT(INDEX(ENGINE!$W$5:$W$304,MATCH(4,EngDash,0)),"0.0")&" — "&INDEX(ENGINE!$X$5:$X$304,MATCH(4,EngDash,0))))} | F8: {=IF($A8="","",INDEX(ENGINE!$Z$5:$Z$304,MATCH(4,EngDash,0)))} | G8: {=IF($A8="","",INDEX(ENGINE!$AH$5:$AH$304,MATCH(4,EngDash,0)))} | H8: {=IF($A8="","",INDEX(ENGINE!$AG$5:$AG$304,MATCH(4,EngDash,0)))} -> 0 | I8: {=IF($A8="","",IF(INDEX(ENGINE!$AI$5:$AI$304,MATCH(4,EngDash,0))="","",INDEX(ENGINE!$AK$5:$AK$304,MATCH(4,EngDash,0))&" "&TEXT(INDEX(ENGINE!$AJ$5:$AJ$304,MATCH(4,EngDash,0)),"0.0")))} | J8: {=IF($A8="","",INDEX(ENGINE!$AM$5:$AM$304,MATCH(4,EngDash,0)))} | K8: {=IF($A8="","",INDEX(ENGINE!$AN$5:$AN$304,MATCH(4,EngDash,0)))} -> BET OVER at ≤ -3.0 | BET UNDER at ≥ 3.0 | L8: {=IF($A8="","",INDEX(ENGINE!$AQ$5:$AQ$304,MATCH(4,EngDash,0)))} -> PENDING BOTH | M8: {=IF($A8="","",INDEX(ENGINE!$AP$5:$AP$304,MATCH(4,EngDash,0)))} -> READY | N8: {=IF($A8="","",INDEX(ENGINE!$AS$5:$AS$304,MATCH(4,EngDash,0)))} -> 50 | O8: {=IF($A8="","",INDEX(ENGINE!$AT$5:$AT$304,MATCH(4,EngDash,0)))} -> 1 | P8: {=IF($A8="","",INDEX(RatMode,MATCH(INDEX(ENGINE!$E$5:$E$304,MATCH(4,EngDash,0)),RatTeams,0))&"/"&INDEX(RatMode,MATCH(INDEX(ENGINE!$F$5:$F$304,MATCH(4,EngDash,0)),RatTeams,0)))} -> BASIC/BASIC | Q8: {=IF($A8="","",INDEX(ENGINE!$AU$5:$AU$304,MATCH(4,EngDash,0)))}
A9: {=IF(IFERROR(MATCH(5,EngDash,0),"")="","",INDEX(ENGINE!$E$5:$E$304,MATCH(5,EngDash,0))&" @ "&INDEX(ENGINE!$F$5:$F$304,MATCH(5,EngDash,0))&IF(INDEX(ENGINE!$G$5:$G$304,MATCH(5,EngDash,0))="Y"," (N)",""))} -> NO @ DET | B9: {=IF($A9="","",INDEX(ENGINE!$D$5:$D$304,MATCH(5,EngDash,0)))} -> 46278 | C9: {=IF($A9="","",IF(INDEX(ENGINE!$U$5:$U$304,MATCH(5,EngDash,0))="","PENDING",INDEX(ENGINE!$F$5:$F$304,MATCH(5,EngDash,0))&" "&TEXT(INDEX(ENGINE!$U$5:$U$304,MATCH(5,EngDash,0)),"+0.0;-0.0;""PK""")))} -> PENDING | D9: {=IF($A9="","",INDEX(ENGINE!$T$5:$T$304,MATCH(5,EngDash,0)))} -> DET -3.4 | E9: {=IF($A9="","",IF(INDEX(ENGINE!$V$5:$V$304,MATCH(5,EngDash,0))="","",TEXT(INDEX(ENGINE!$W$5:$W$304,MATCH(5,EngDash,0)),"0.0")&" — "&INDEX(ENGINE!$X$5:$X$304,MATCH(5,EngDash,0))))} | F9: {=IF($A9="","",INDEX(ENGINE!$Z$5:$Z$304,MATCH(5,EngDash,0)))} | G9: {=IF($A9="","",INDEX(ENGINE!$AH$5:$AH$304,MATCH(5,EngDash,0)))} | H9: {=IF($A9="","",INDEX(ENGINE!$AG$5:$AG$304,MATCH(5,EngDash,0)))} -> 0 | I9: {=IF($A9="","",IF(INDEX(ENGINE!$AI$5:$AI$304,MATCH(5,EngDash,0))="","",INDEX(ENGINE!$AK$5:$AK$304,MATCH(5,EngDash,0))&" "&TEXT(INDEX(ENGINE!$AJ$5:$AJ$304,MATCH(5,EngDash,0)),"0.0")))} | J9: {=IF($A9="","",INDEX(ENGINE!$AM$5:$AM$304,MATCH(5,EngDash,0)))} | K9: {=IF($A9="","",INDEX(ENGINE!$AN$5:$AN$304,MATCH(5,EngDash,0)))} -> BET OVER at ≤ -3.0 | BET UNDER at ≥ 3.0 | L9: {=IF($A9="","",INDEX(ENGINE!$AQ$5:$AQ$304,MATCH(5,EngDash,0)))} -> PENDING BOTH | M9: {=IF($A9="","",INDEX(ENGINE!$AP$5:$AP$304,MATCH(5,EngDash,0)))} -> READY | N9: {=IF($A9="","",INDEX(ENGINE!$AS$5:$AS$304,MATCH(5,EngDash,0)))} -> 50 | O9: {=IF($A9="","",INDEX(ENGINE!$AT$5:$AT$304,MATCH(5,EngDash,0)))} -> 1 | P9: {=IF($A9="","",INDEX(RatMode,MATCH(INDEX(ENGINE!$E$5:$E$304,MATCH(5,EngDash,0)),RatTeams,0))&"/"&INDEX(RatMode,MATCH(INDEX(ENGINE!$F$5:$F$304,MATCH(5,EngDash,0)),RatTeams,0)))} -> BASIC/BASIC | Q9: {=IF($A9="","",INDEX(ENGINE!$AU$5:$AU$304,MATCH(5,EngDash,0)))}
A10: {=IF(IFERROR(MATCH(6,EngDash,0),"")="","",INDEX(ENGINE!$E$5:$E$304,MATCH(6,EngDash,0))&" @ "&INDEX(ENGINE!$F$5:$F$304,MATCH(6,EngDash,0))&IF(INDEX(ENGINE!$G$5:$G$304,MATCH(6,EngDash,0))="Y"," (N)",""))} -> BUF @ HOU | B10: {=IF($A10="","",INDEX(ENGINE!$D$5:$D$304,MATCH(6,EngDash,0)))} -> 46278 | C10: {=IF($A10="","",IF(INDEX(ENGINE!$U$5:$U$304,MATCH(6,EngDash,0))="","PENDING",INDEX(ENGINE!$F$5:$F$304,MATCH(6,EngDash,0))&" "&TEXT(INDEX(ENGINE!$U$5:$U$304,MATCH(6,EngDash,0)),"+0.0;-0.0;""PK""")))} -> PENDING | D10: {=IF($A10="","",INDEX(ENGINE!$T$5:$T$304,MATCH(6,EngDash,0)))} -> HOU -2.6 | E10: {=IF($A10="","",IF(INDEX(ENGINE!$V$5:$V$304,MATCH(6,EngDash,0))="","",TEXT(INDEX(ENGINE!$W$5:$W$304,MATCH(6,EngDash,0)),"0.0")&" — "&INDEX(ENGINE!$X$5:$X$304,MATCH(6,EngDash,0))))} | F10: {=IF($A10="","",INDEX(ENGINE!$Z$5:$Z$304,MATCH(6,EngDash,0)))} | G10: {=IF($A10="","",INDEX(ENGINE!$AH$5:$AH$304,MATCH(6,EngDash,0)))} | H10: {=IF($A10="","",INDEX(ENGINE!$AG$5:$AG$304,MATCH(6,EngDash,0)))} -> 0 | I10: {=IF($A10="","",IF(INDEX(ENGINE!$AI$5:$AI$304,MATCH(6,EngDash,0))="","",INDEX(ENGINE!$AK$5:$AK$304,MATCH(6,EngDash,0))&" "&TEXT(INDEX(ENGINE!$AJ$5:$AJ$304,MATCH(6,EngDash,0)),"0.0")))} | J10: {=IF($A10="","",INDEX(ENGINE!$AM$5:$AM$304,MATCH(6,EngDash,0)))} | K10: {=IF($A10="","",INDEX(ENGINE!$AN$5:$AN$304,MATCH(6,EngDash,0)))} -> BET OVER at ≤ -3.0 | BET UNDER at ≥ 3.0 | L10: {=IF($A10="","",INDEX(ENGINE!$AQ$5:$AQ$304,MATCH(6,EngDash,0)))} -> PENDING BOTH | M10: {=IF($A10="","",INDEX(ENGINE!$AP$5:$AP$304,MATCH(6,EngDash,0)))} -> READY | N10: {=IF($A10="","",INDEX(ENGINE!$AS$5:$AS$304,MATCH(6,EngDash,0)))} -> 50 | O10: {=IF($A10="","",INDEX(ENGINE!$AT$5:$AT$304,MATCH(6,EngDash,0)))} -> 1 | P10: {=IF($A10="","",INDEX(RatMode,MATCH(INDEX(ENGINE!$E$5:$E$304,MATCH(6,EngDash,0)),RatTeams,0))&"/"&INDEX(RatMode,MATCH(INDEX(ENGINE!$F$5:$F$304,MATCH(6,EngDash,0)),RatTeams,0)))} -> BASIC/BASIC | Q10: {=IF($A10="","",INDEX(ENGINE!$AU$5:$AU$304,MATCH(6,EngDash,0)))}
A11: {=IF(IFERROR(MATCH(7,EngDash,0),"")="","",INDEX(ENGINE!$E$5:$E$304,MATCH(7,EngDash,0))&" @ "&INDEX(ENGINE!$F$5:$F$304,MATCH(7,EngDash,0))&IF(INDEX(ENGINE!$G$5:$G$304,MATCH(7,EngDash,0))="Y"," (N)",""))} -> BAL @ IND | B11: {=IF($A11="","",INDEX(ENGINE!$D$5:$D$304,MATCH(7,EngDash,0)))} -> 46278 | C11: {=IF($A11="","",IF(INDEX(ENGINE!$U$5:$U$304,MATCH(7,EngDash,0))="","PENDING",INDEX(ENGINE!$F$5:$F$304,MATCH(7,EngDash,0))&" "&TEXT(INDEX(ENGINE!$U$5:$U$304,MATCH(7,EngDash,0)),"+0.0;-0.0;""PK""")))} -> PENDING | D11: {=IF($A11="","",INDEX(ENGINE!$T$5:$T$304,MATCH(7,EngDash,0)))} -> IND -1.5 | E11: {=IF($A11="","",IF(INDEX(ENGINE!$V$5:$V$304,MATCH(7,EngDash,0))="","",TEXT(INDEX(ENGINE!$W$5:$W$304,MATCH(7,EngDash,0)),"0.0")&" — "&INDEX(ENGINE!$X$5:$X$304,MATCH(7,EngDash,0))))} | F11: {=IF($A11="","",INDEX(ENGINE!$Z$5:$Z$304,MATCH(7,EngDash,0)))} | G11: {=IF($A11="","",INDEX(ENGINE!$AH$5:$AH$304,MATCH(7,EngDash,0)))} | H11: {=IF($A11="","",INDEX(ENGINE!$AG$5:$AG$304,MATCH(7,EngDash,0)))} -> 0 | I11: {=IF($A11="","",IF(INDEX(ENGINE!$AI$5:$AI$304,MATCH(7,EngDash,0))="","",INDEX(ENGINE!$AK$5:$AK$304,MATCH(7,EngDash,0))&" "&TEXT(INDEX(ENGINE!$AJ$5:$AJ$304,MATCH(7,EngDash,0)),"0.0")))} | J11: {=IF($A11="","",INDEX(ENGINE!$AM$5:$AM$304,MATCH(7,EngDash,0)))} | K11: {=IF($A11="","",INDEX(ENGINE!$AN$5:$AN$304,MATCH(7,EngDash,0)))} -> BET OVER at ≤ -3.0 | BET UNDER at ≥ 3.0 | L11: {=IF($A11="","",INDEX(ENGINE!$AQ$5:$AQ$304,MATCH(7,EngDash,0)))} -> PENDING BOTH | M11: {=IF($A11="","",INDEX(ENGINE!$AP$5:$AP$304,MATCH(7,EngDash,0)))} -> READY | N11: {=IF($A11="","",INDEX(ENGINE!$AS$5:$AS$304,MATCH(7,EngDash,0)))} -> 50 | O11: {=IF($A11="","",INDEX(ENGINE!$AT$5:$AT$304,MATCH(7,EngDash,0)))} -> 1 | P11: {=IF($A11="","",INDEX(RatMode,MATCH(INDEX(ENGINE!$E$5:$E$304,MATCH(7,EngDash,0)),RatTeams,0))&"/"&INDEX(RatMode,MATCH(INDEX(ENGINE!$F$5:$F$304,MATCH(7,EngDash,0)),RatTeams,0)))} -> BASIC/BASIC | Q11: {=IF($A11="","",INDEX(ENGINE!$AU$5:$AU$304,MATCH(7,EngDash,0)))}
A12: {=IF(IFERROR(MATCH(8,EngDash,0),"")="","",INDEX(ENGINE!$E$5:$E$304,MATCH(8,EngDash,0))&" @ "&INDEX(ENGINE!$F$5:$F$304,MATCH(8,EngDash,0))&IF(INDEX(ENGINE!$G$5:$G$304,MATCH(8,EngDash,0))="Y"," (N)",""))} -> CLE @ JAX | B12: {=IF($A12="","",INDEX(ENGINE!$D$5:$D$304,MATCH(8,EngDash,0)))} -> 46278 | C12: {=IF($A12="","",IF(INDEX(ENGINE!$U$5:$U$304,MATCH(8,EngDash,0))="","PENDING",INDEX(ENGINE!$F$5:$F$304,MATCH(8,EngDash,0))&" "&TEXT(INDEX(ENGINE!$U$5:$U$304,MATCH(8,EngDash,0)),"+0.0;-0.0;""PK""")))} -> PENDING | D12: {=IF($A12="","",INDEX(ENGINE!$T$5:$T$304,MATCH(8,EngDash,0)))} -> JAX -7.4 | E12: {=IF($A12="","",IF(INDEX(ENGINE!$V$5:$V$304,MATCH(8,EngDash,0))="","",TEXT(INDEX(ENGINE!$W$5:$W$304,MATCH(8,EngDash,0)),"0.0")&" — "&INDEX(ENGINE!$X$5:$X$304,MATCH(8,EngDash,0))))} | F12: {=IF($A12="","",INDEX(ENGINE!$Z$5:$Z$304,MATCH(8,EngDash,0)))} | G12: {=IF($A12="","",INDEX(ENGINE!$AH$5:$AH$304,MATCH(8,EngDash,0)))} | H12: {=IF($A12="","",INDEX(ENGINE!$AG$5:$AG$304,MATCH(8,EngDash,0)))} -> 0 | I12: {=IF($A12="","",IF(INDEX(ENGINE!$AI$5:$AI$304,MATCH(8,EngDash,0))="","",INDEX(ENGINE!$AK$5:$AK$304,MATCH(8,EngDash,0))&" "&TEXT(INDEX(ENGINE!$AJ$5:$AJ$304,MATCH(8,EngDash,0)),"0.0")))} | J12: {=IF($A12="","",INDEX(ENGINE!$AM$5:$AM$304,MATCH(8,EngDash,0)))} | K12: {=IF($A12="","",INDEX(ENGINE!$AN$5:$AN$304,MATCH(8,EngDash,0)))} -> BET OVER at ≤ -3.0 | BET UNDER at ≥ 3.0 | L12: {=IF($A12="","",INDEX(ENGINE!$AQ$5:$AQ$304,MATCH(8,EngDash,0)))} -> PENDING BOTH | M12: {=IF($A12="","",INDEX(ENGINE!$AP$5:$AP$304,MATCH(8,EngDash,0)))} -> READY | N12: {=IF($A12="","",INDEX(ENGINE!$AS$5:$AS$304,MATCH(8,EngDash,0)))} -> 30 | O12: {=IF($A12="","",INDEX(ENGINE!$AT$5:$AT$304,MATCH(8,EngDash,0)))} -> 13 | P12: {=IF($A12="","",INDEX(RatMode,MATCH(INDEX(ENGINE!$E$5:$E$304,MATCH(8,EngDash,0)),RatTeams,0))&"/"&INDEX(RatMode,MATCH(INDEX(ENGINE!$F$5:$F$304,MATCH(8,EngDash,0)),RatTeams,0)))} -> BASIC/BASIC | Q12: {=IF($A12="","",INDEX(ENGINE!$AU$5:$AU$304,MATCH(8,EngDash,0)))}
A13: {=IF(IFERROR(MATCH(9,EngDash,0),"")="","",INDEX(ENGINE!$E$5:$E$304,MATCH(9,EngDash,0))&" @ "&INDEX(ENGINE!$F$5:$F$304,MATCH(9,EngDash,0))&IF(INDEX(ENGINE!$G$5:$G$304,MATCH(9,EngDash,0))="Y"," (N)",""))} -> ATL @ PIT | B13: {=IF($A13="","",INDEX(ENGINE!$D$5:$D$304,MATCH(9,EngDash,0)))} -> 46278 | C13: {=IF($A13="","",IF(INDEX(ENGINE!$U$5:$U$304,MATCH(9,EngDash,0))="","PENDING",INDEX(ENGINE!$F$5:$F$304,MATCH(9,EngDash,0))&" "&TEXT(INDEX(ENGINE!$U$5:$U$304,MATCH(9,EngDash,0)),"+0.0;-0.0;""PK""")))} -> PENDING | D13: {=IF($A13="","",INDEX(ENGINE!$T$5:$T$304,MATCH(9,EngDash,0)))} -> PIT -2.3 | E13: {=IF($A13="","",IF(INDEX(ENGINE!$V$5:$V$304,MATCH(9,EngDash,0))="","",TEXT(INDEX(ENGINE!$W$5:$W$304,MATCH(9,EngDash,0)),"0.0")&" — "&INDEX(ENGINE!$X$5:$X$304,MATCH(9,EngDash,0))))} | F13: {=IF($A13="","",INDEX(ENGINE!$Z$5:$Z$304,MATCH(9,EngDash,0)))} | G13: {=IF($A13="","",INDEX(ENGINE!$AH$5:$AH$304,MATCH(9,EngDash,0)))} | H13: {=IF($A13="","",INDEX(ENGINE!$AG$5:$AG$304,MATCH(9,EngDash,0)))} -> 0 | I13: {=IF($A13="","",IF(INDEX(ENGINE!$AI$5:$AI$304,MATCH(9,EngDash,0))="","",INDEX(ENGINE!$AK$5:$AK$304,MATCH(9,EngDash,0))&" "&TEXT(INDEX(ENGINE!$AJ$5:$AJ$304,MATCH(9,EngDash,0)),"0.0")))} | J13: {=IF($A13="","",INDEX(ENGINE!$AM$5:$AM$304,MATCH(9,EngDash,0)))} | K13: {=IF($A13="","",INDEX(ENGINE!$AN$5:$AN$304,MATCH(9,EngDash,0)))} -> BET OVER at ≤ -3.0 | BET UNDER at ≥ 3.0 | L13: {=IF($A13="","",INDEX(ENGINE!$AQ$5:$AQ$304,MATCH(9,EngDash,0)))} -> PENDING BOTH | M13: {=IF($A13="","",INDEX(ENGINE!$AP$5:$AP$304,MATCH(9,EngDash,0)))} -> READY | N13: {=IF($A13="","",INDEX(ENGINE!$AS$5:$AS$304,MATCH(9,EngDash,0)))} -> 30 | O13: {=IF($A13="","",INDEX(ENGINE!$AT$5:$AT$304,MATCH(9,EngDash,0)))} -> 13 | P13: {=IF($A13="","",INDEX(RatMode,MATCH(INDEX(ENGINE!$E$5:$E$304,MATCH(9,EngDash,0)),RatTeams,0))&"/"&INDEX(RatMode,MATCH(INDEX(ENGINE!$F$5:$F$304,MATCH(9,EngDash,0)),RatTeams,0)))} -> BASIC/BASIC | Q13: {=IF($A13="","",INDEX(ENGINE!$AU$5:$AU$304,MATCH(9,EngDash,0)))}
A14: {=IF(IFERROR(MATCH(10,EngDash,0),"")="","",INDEX(ENGINE!$E$5:$E$304,MATCH(10,EngDash,0))&" @ "&INDEX(ENGINE!$F$5:$F$304,MATCH(10,EngDash,0))&IF(INDEX(ENGINE!$G$5:$G$304,MATCH(10,EngDash,0))="Y"," (N)",""))} -> NYJ @ TEN | B14: {=IF($A14="","",INDEX(ENGINE!$D$5:$D$304,MATCH(10,EngDash,0)))} -> 46278 | C14: {=IF($A14="","",IF(INDEX(ENGINE!$U$5:$U$304,MATCH(10,EngDash,0))="","PENDING",INDEX(ENGINE!$F$5:$F$304,MATCH(10,EngDash,0))&" "&TEXT(INDEX(ENGINE!$U$5:$U$304,MATCH(10,EngDash,0)),"+0.0;-0.0;""PK""")))} -> PENDING | D14: {=IF($A14="","",INDEX(ENGINE!$T$5:$T$304,MATCH(10,EngDash,0)))} -> TEN -3.1 | E14: {=IF($A14="","",IF(INDEX(ENGINE!$V$5:$V$304,MATCH(10,EngDash,0))="","",TEXT(INDEX(ENGINE!$W$5:$W$304,MATCH(10,EngDash,0)),"0.0")&" — "&INDEX(ENGINE!$X$5:$X$304,MATCH(10,EngDash,0))))} | F14: {=IF($A14="","",INDEX(ENGINE!$Z$5:$Z$304,MATCH(10,EngDash,0)))} | G14: {=IF($A14="","",INDEX(ENGINE!$AH$5:$AH$304,MATCH(10,EngDash,0)))} | H14: {=IF($A14="","",INDEX(ENGINE!$AG$5:$AG$304,MATCH(10,EngDash,0)))} -> 0 | I14: {=IF($A14="","",IF(INDEX(ENGINE!$AI$5:$AI$304,MATCH(10,EngDash,0))="","",INDEX(ENGINE!$AK$5:$AK$304,MATCH(10,EngDash,0))&" "&TEXT(INDEX(ENGINE!$AJ$5:$AJ$304,MATCH(10,EngDash,0)),"0.0")))} | J14: {=IF($A14="","",INDEX(ENGINE!$AM$5:$AM$304,MATCH(10,EngDash,0)))} | K14: {=IF($A14="","",INDEX(ENGINE!$AN$5:$AN$304,MATCH(10,EngDash,0)))} -> BET OVER at ≤ -3.0 | BET UNDER at ≥ 3.0 | L14: {=IF($A14="","",INDEX(ENGINE!$AQ$5:$AQ$304,MATCH(10,EngDash,0)))} -> PENDING BOTH | M14: {=IF($A14="","",INDEX(ENGINE!$AP$5:$AP$304,MATCH(10,EngDash,0)))} -> READY | N14: {=IF($A14="","",INDEX(ENGINE!$AS$5:$AS$304,MATCH(10,EngDash,0)))} -> 50 | O14: {=IF($A14="","",INDEX(ENGINE!$AT$5:$AT$304,MATCH(10,EngDash,0)))} -> 1 | P14: {=IF($A14="","",INDEX(RatMode,MATCH(INDEX(ENGINE!$E$5:$E$304,MATCH(10,EngDash,0)),RatTeams,0))&"/"&INDEX(RatMode,MATCH(INDEX(ENGINE!$F$5:$F$304,MATCH(10,EngDash,0)),RatTeams,0)))} -> BASIC/BASIC | Q14: {=IF($A14="","",INDEX(ENGINE!$AU$5:$AU$304,MATCH(10,EngDash,0)))}
A15: {=IF(IFERROR(MATCH(11,EngDash,0),"")="","",INDEX(ENGINE!$E$5:$E$304,MATCH(11,EngDash,0))&" @ "&INDEX(ENGINE!$F$5:$F$304,MATCH(11,EngDash,0))&IF(INDEX(ENGINE!$G$5:$G$304,MATCH(11,EngDash,0))="Y"," (N)",""))} -> ARI @ LAC | B15: {=IF($A15="","",INDEX(ENGINE!$D$5:$D$304,MATCH(11,EngDash,0)))} -> 46278 | C15: {=IF($A15="","",IF(INDEX(ENGINE!$U$5:$U$304,MATCH(11,EngDash,0))="","PENDING",INDEX(ENGINE!$F$5:$F$304,MATCH(11,EngDash,0))&" "&TEXT(INDEX(ENGINE!$U$5:$U$304,MATCH(11,EngDash,0)),"+0.0;-0.0;""PK""")))} -> PENDING | D15: {=IF($A15="","",INDEX(ENGINE!$T$5:$T$304,MATCH(11,EngDash,0)))} -> LAC -4.2 | E15: {=IF($A15="","",IF(INDEX(ENGINE!$V$5:$V$304,MATCH(11,EngDash,0))="","",TEXT(INDEX(ENGINE!$W$5:$W$304,MATCH(11,EngDash,0)),"0.0")&" — "&INDEX(ENGINE!$X$5:$X$304,MATCH(11,EngDash,0))))} | F15: {=IF($A15="","",INDEX(ENGINE!$Z$5:$Z$304,MATCH(11,EngDash,0)))} | G15: {=IF($A15="","",INDEX(ENGINE!$AH$5:$AH$304,MATCH(11,EngDash,0)))} | H15: {=IF($A15="","",INDEX(ENGINE!$AG$5:$AG$304,MATCH(11,EngDash,0)))} -> 0 | I15: {=IF($A15="","",IF(INDEX(ENGINE!$AI$5:$AI$304,MATCH(11,EngDash,0))="","",INDEX(ENGINE!$AK$5:$AK$304,MATCH(11,EngDash,0))&" "&TEXT(INDEX(ENGINE!$AJ$5:$AJ$304,MATCH(11,EngDash,0)),"0.0")))} | J15: {=IF($A15="","",INDEX(ENGINE!$AM$5:$AM$304,MATCH(11,EngDash,0)))} | K15: {=IF($A15="","",INDEX(ENGINE!$AN$5:$AN$304,MATCH(11,EngDash,0)))} -> BET OVER at ≤ -3.0 | BET UNDER at ≥ 3.0 | L15: {=IF($A15="","",INDEX(ENGINE!$AQ$5:$AQ$304,MATCH(11,EngDash,0)))} -> PENDING BOTH | M15: {=IF($A15="","",INDEX(ENGINE!$AP$5:$AP$304,MATCH(11,EngDash,0)))} -> READY | N15: {=IF($A15="","",INDEX(ENGINE!$AS$5:$AS$304,MATCH(11,EngDash,0)))} -> 30 | O15: {=IF($A15="","",INDEX(ENGINE!$AT$5:$AT$304,MATCH(11,EngDash,0)))} -> 13 | P15: {=IF($A15="","",INDEX(RatMode,MATCH(INDEX(ENGINE!$E$5:$E$304,MATCH(11,EngDash,0)),RatTeams,0))&"/"&INDEX(RatMode,MATCH(INDEX(ENGINE!$F$5:$F$304,MATCH(11,EngDash,0)),RatTeams,0)))} -> BASIC/BASIC | Q15: {=IF($A15="","",INDEX(ENGINE!$AU$5:$AU$304,MATCH(11,EngDash,0)))}
A16: {=IF(IFERROR(MATCH(12,EngDash,0),"")="","",INDEX(ENGINE!$E$5:$E$304,MATCH(12,EngDash,0))&" @ "&INDEX(ENGINE!$F$5:$F$304,MATCH(12,EngDash,0))&IF(INDEX(ENGINE!$G$5:$G$304,MATCH(12,EngDash,0))="Y"," (N)",""))} -> MIA @ LV | B16: {=IF($A16="","",INDEX(ENGINE!$D$5:$D$304,MATCH(12,EngDash,0)))} -> 46278 | C16: {=IF($A16="","",IF(INDEX(ENGINE!$U$5:$U$304,MATCH(12,EngDash,0))="","PENDING",INDEX(ENGINE!$F$5:$F$304,MATCH(12,EngDash,0))&" "&TEXT(INDEX(ENGINE!$U$5:$U$304,MATCH(12,EngDash,0)),"+0.0;-0.0;""PK""")))} -> PENDING | D16: {=IF($A16="","",INDEX(ENGINE!$T$5:$T$304,MATCH(12,EngDash,0)))} -> LV -0.7 | E16: {=IF($A16="","",IF(INDEX(ENGINE!$V$5:$V$304,MATCH(12,EngDash,0))="","",TEXT(INDEX(ENGINE!$W$5:$W$304,MATCH(12,EngDash,0)),"0.0")&" — "&INDEX(ENGINE!$X$5:$X$304,MATCH(12,EngDash,0))))} | F16: {=IF($A16="","",INDEX(ENGINE!$Z$5:$Z$304,MATCH(12,EngDash,0)))} | G16: {=IF($A16="","",INDEX(ENGINE!$AH$5:$AH$304,MATCH(12,EngDash,0)))} | H16: {=IF($A16="","",INDEX(ENGINE!$AG$5:$AG$304,MATCH(12,EngDash,0)))} -> 0 | I16: {=IF($A16="","",IF(INDEX(ENGINE!$AI$5:$AI$304,MATCH(12,EngDash,0))="","",INDEX(ENGINE!$AK$5:$AK$304,MATCH(12,EngDash,0))&" "&TEXT(INDEX(ENGINE!$AJ$5:$AJ$304,MATCH(12,EngDash,0)),"0.0")))} | J16: {=IF($A16="","",INDEX(ENGINE!$AM$5:$AM$304,MATCH(12,EngDash,0)))} | K16: {=IF($A16="","",INDEX(ENGINE!$AN$5:$AN$304,MATCH(12,EngDash,0)))} -> BET OVER at ≤ -3.0 | BET UNDER at ≥ 3.0 | L16: {=IF($A16="","",INDEX(ENGINE!$AQ$5:$AQ$304,MATCH(12,EngDash,0)))} -> PENDING BOTH | M16: {=IF($A16="","",INDEX(ENGINE!$AP$5:$AP$304,MATCH(12,EngDash,0)))} -> READY | N16: {=IF($A16="","",INDEX(ENGINE!$AS$5:$AS$304,MATCH(12,EngDash,0)))} -> 50 | O16: {=IF($A16="","",INDEX(ENGINE!$AT$5:$AT$304,MATCH(12,EngDash,0)))} -> 1 | P16: {=IF($A16="","",INDEX(RatMode,MATCH(INDEX(ENGINE!$E$5:$E$304,MATCH(12,EngDash,0)),RatTeams,0))&"/"&INDEX(RatMode,MATCH(INDEX(ENGINE!$F$5:$F$304,MATCH(12,EngDash,0)),RatTeams,0)))} -> BASIC/BASIC | Q16: {=IF($A16="","",INDEX(ENGINE!$AU$5:$AU$304,MATCH(12,EngDash,0)))}
A17: {=IF(IFERROR(MATCH(13,EngDash,0),"")="","",INDEX(ENGINE!$E$5:$E$304,MATCH(13,EngDash,0))&" @ "&INDEX(ENGINE!$F$5:$F$304,MATCH(13,EngDash,0))&IF(INDEX(ENGINE!$G$5:$G$304,MATCH(13,EngDash,0))="Y"," (N)",""))} -> GB @ MIN | B17: {=IF($A17="","",INDEX(ENGINE!$D$5:$D$304,MATCH(13,EngDash,0)))} -> 46278 | C17: {=IF($A17="","",IF(INDEX(ENGINE!$U$5:$U$304,MATCH(13,EngDash,0))="","PENDING",INDEX(ENGINE!$F$5:$F$304,MATCH(13,EngDash,0))&" "&TEXT(INDEX(ENGINE!$U$5:$U$304,MATCH(13,EngDash,0)),"+0.0;-0.0;""PK""")))} -> PENDING | D17: {=IF($A17="","",INDEX(ENGINE!$T$5:$T$304,MATCH(13,EngDash,0)))} -> MIN -1.6 | E17: {=IF($A17="","",IF(INDEX(ENGINE!$V$5:$V$304,MATCH(13,EngDash,0))="","",TEXT(INDEX(ENGINE!$W$5:$W$304,MATCH(13,EngDash,0)),"0.0")&" — "&INDEX(ENGINE!$X$5:$X$304,MATCH(13,EngDash,0))))} | F17: {=IF($A17="","",INDEX(ENGINE!$Z$5:$Z$304,MATCH(13,EngDash,0)))} | G17: {=IF($A17="","",INDEX(ENGINE!$AH$5:$AH$304,MATCH(13,EngDash,0)))} | H17: {=IF($A17="","",INDEX(ENGINE!$AG$5:$AG$304,MATCH(13,EngDash,0)))} -> 0 | I17: {=IF($A17="","",IF(INDEX(ENGINE!$AI$5:$AI$304,MATCH(13,EngDash,0))="","",INDEX(ENGINE!$AK$5:$AK$304,MATCH(13,EngDash,0))&" "&TEXT(INDEX(ENGINE!$AJ$5:$AJ$304,MATCH(13,EngDash,0)),"0.0")))} | J17: {=IF($A17="","",INDEX(ENGINE!$AM$5:$AM$304,MATCH(13,EngDash,0)))} | K17: {=IF($A17="","",INDEX(ENGINE!$AN$5:$AN$304,MATCH(13,EngDash,0)))} -> BET OVER at ≤ -3.0 | BET UNDER at ≥ 3.0 | L17: {=IF($A17="","",INDEX(ENGINE!$AQ$5:$AQ$304,MATCH(13,EngDash,0)))} -> PENDING BOTH | M17: {=IF($A17="","",INDEX(ENGINE!$AP$5:$AP$304,MATCH(13,EngDash,0)))} -> READY | N17: {=IF($A17="","",INDEX(ENGINE!$AS$5:$AS$304,MATCH(13,EngDash,0)))} -> 30 | O17: {=IF($A17="","",INDEX(ENGINE!$AT$5:$AT$304,MATCH(13,EngDash,0)))} -> 13 | P17: {=IF($A17="","",INDEX(RatMode,MATCH(INDEX(ENGINE!$E$5:$E$304,MATCH(13,EngDash,0)),RatTeams,0))&"/"&INDEX(RatMode,MATCH(INDEX(ENGINE!$F$5:$F$304,MATCH(13,EngDash,0)),RatTeams,0)))} -> BASIC/BASIC | Q17: {=IF($A17="","",INDEX(ENGINE!$AU$5:$AU$304,MATCH(13,EngDash,0)))}
A18: {=IF(IFERROR(MATCH(14,EngDash,0),"")="","",INDEX(ENGINE!$E$5:$E$304,MATCH(14,EngDash,0))&" @ "&INDEX(ENGINE!$F$5:$F$304,MATCH(14,EngDash,0))&IF(INDEX(ENGINE!$G$5:$G$304,MATCH(14,EngDash,0))="Y"," (N)",""))} -> WAS @ PHI | B18: {=IF($A18="","",INDEX(ENGINE!$D$5:$D$304,MATCH(14,EngDash,0)))} -> 46278 | C18: {=IF($A18="","",IF(INDEX(ENGINE!$U$5:$U$304,MATCH(14,EngDash,0))="","PENDING",INDEX(ENGINE!$F$5:$F$304,MATCH(14,EngDash,0))&" "&TEXT(INDEX(ENGINE!$U$5:$U$304,MATCH(14,EngDash,0)),"+0.0;-0.0;""PK""")))} -> PENDING | D18: {=IF($A18="","",INDEX(ENGINE!$T$5:$T$304,MATCH(14,EngDash,0)))} -> PHI -5.1 | E18: {=IF($A18="","",IF(INDEX(ENGINE!$V$5:$V$304,MATCH(14,EngDash,0))="","",TEXT(INDEX(ENGINE!$W$5:$W$304,MATCH(14,EngDash,0)),"0.0")&" — "&INDEX(ENGINE!$X$5:$X$304,MATCH(14,EngDash,0))))} | F18: {=IF($A18="","",INDEX(ENGINE!$Z$5:$Z$304,MATCH(14,EngDash,0)))} | G18: {=IF($A18="","",INDEX(ENGINE!$AH$5:$AH$304,MATCH(14,EngDash,0)))} | H18: {=IF($A18="","",INDEX(ENGINE!$AG$5:$AG$304,MATCH(14,EngDash,0)))} -> 0 | I18: {=IF($A18="","",IF(INDEX(ENGINE!$AI$5:$AI$304,MATCH(14,EngDash,0))="","",INDEX(ENGINE!$AK$5:$AK$304,MATCH(14,EngDash,0))&" "&TEXT(INDEX(ENGINE!$AJ$5:$AJ$304,MATCH(14,EngDash,0)),"0.0")))} | J18: {=IF($A18="","",INDEX(ENGINE!$AM$5:$AM$304,MATCH(14,EngDash,0)))} | K18: {=IF($A18="","",INDEX(ENGINE!$AN$5:$AN$304,MATCH(14,EngDash,0)))} -> BET OVER at ≤ -3.0 | BET UNDER at ≥ 3.0 | L18: {=IF($A18="","",INDEX(ENGINE!$AQ$5:$AQ$304,MATCH(14,EngDash,0)))} -> PENDING BOTH | M18: {=IF($A18="","",INDEX(ENGINE!$AP$5:$AP$304,MATCH(14,EngDash,0)))} -> READY | N18: {=IF($A18="","",INDEX(ENGINE!$AS$5:$AS$304,MATCH(14,EngDash,0)))} -> 50 | O18: {=IF($A18="","",INDEX(ENGINE!$AT$5:$AT$304,MATCH(14,EngDash,0)))} -> 1 | P18: {=IF($A18="","",INDEX(RatMode,MATCH(INDEX(ENGINE!$E$5:$E$304,MATCH(14,EngDash,0)),RatTeams,0))&"/"&INDEX(RatMode,MATCH(INDEX(ENGINE!$F$5:$F$304,MATCH(14,EngDash,0)),RatTeams,0)))} -> BASIC/BASIC | Q18: {=IF($A18="","",INDEX(ENGINE!$AU$5:$AU$304,MATCH(14,EngDash,0)))}
A19: {=IF(IFERROR(MATCH(15,EngDash,0),"")="","",INDEX(ENGINE!$E$5:$E$304,MATCH(15,EngDash,0))&" @ "&INDEX(ENGINE!$F$5:$F$304,MATCH(15,EngDash,0))&IF(INDEX(ENGINE!$G$5:$G$304,MATCH(15,EngDash,0))="Y"," (N)",""))} -> DAL @ NYG | B19: {=IF($A19="","",INDEX(ENGINE!$D$5:$D$304,MATCH(15,EngDash,0)))} -> 46278 | C19: {=IF($A19="","",IF(INDEX(ENGINE!$U$5:$U$304,MATCH(15,EngDash,0))="","PENDING",INDEX(ENGINE!$F$5:$F$304,MATCH(15,EngDash,0))&" "&TEXT(INDEX(ENGINE!$U$5:$U$304,MATCH(15,EngDash,0)),"+0.0;-0.0;""PK""")))} -> PENDING | D19: {=IF($A19="","",INDEX(ENGINE!$T$5:$T$304,MATCH(15,EngDash,0)))} -> NYG -2.3 | E19: {=IF($A19="","",IF(INDEX(ENGINE!$V$5:$V$304,MATCH(15,EngDash,0))="","",TEXT(INDEX(ENGINE!$W$5:$W$304,MATCH(15,EngDash,0)),"0.0")&" — "&INDEX(ENGINE!$X$5:$X$304,MATCH(15,EngDash,0))))} | F19: {=IF($A19="","",INDEX(ENGINE!$Z$5:$Z$304,MATCH(15,EngDash,0)))} | G19: {=IF($A19="","",INDEX(ENGINE!$AH$5:$AH$304,MATCH(15,EngDash,0)))} | H19: {=IF($A19="","",INDEX(ENGINE!$AG$5:$AG$304,MATCH(15,EngDash,0)))} -> 0 | I19: {=IF($A19="","",IF(INDEX(ENGINE!$AI$5:$AI$304,MATCH(15,EngDash,0))="","",INDEX(ENGINE!$AK$5:$AK$304,MATCH(15,EngDash,0))&" "&TEXT(INDEX(ENGINE!$AJ$5:$AJ$304,MATCH(15,EngDash,0)),"0.0")))} | J19: {=IF($A19="","",INDEX(ENGINE!$AM$5:$AM$304,MATCH(15,EngDash,0)))} | K19: {=IF($A19="","",INDEX(ENGINE!$AN$5:$AN$304,MATCH(15,EngDash,0)))} -> BET OVER at ≤ -3.0 | BET UNDER at ≥ 3.0 | L19: {=IF($A19="","",INDEX(ENGINE!$AQ$5:$AQ$304,MATCH(15,EngDash,0)))} -> PENDING BOTH | M19: {=IF($A19="","",INDEX(ENGINE!$AP$5:$AP$304,MATCH(15,EngDash,0)))} -> READY | N19: {=IF($A19="","",INDEX(ENGINE!$AS$5:$AS$304,MATCH(15,EngDash,0)))} -> 50 | O19: {=IF($A19="","",INDEX(ENGINE!$AT$5:$AT$304,MATCH(15,EngDash,0)))} -> 1 | P19: {=IF($A19="","",INDEX(RatMode,MATCH(INDEX(ENGINE!$E$5:$E$304,MATCH(15,EngDash,0)),RatTeams,0))&"/"&INDEX(RatMode,MATCH(INDEX(ENGINE!$F$5:$F$304,MATCH(15,EngDash,0)),RatTeams,0)))} -> BASIC/BASIC | Q19: {=IF($A19="","",INDEX(ENGINE!$AU$5:$AU$304,MATCH(15,EngDash,0)))}
A20: {=IF(IFERROR(MATCH(16,EngDash,0),"")="","",INDEX(ENGINE!$E$5:$E$304,MATCH(16,EngDash,0))&" @ "&INDEX(ENGINE!$F$5:$F$304,MATCH(16,EngDash,0))&IF(INDEX(ENGINE!$G$5:$G$304,MATCH(16,EngDash,0))="Y"," (N)",""))} -> DEN @ KC | B20: {=IF($A20="","",INDEX(ENGINE!$D$5:$D$304,MATCH(16,EngDash,0)))} -> 46279 | C20: {=IF($A20="","",IF(INDEX(ENGINE!$U$5:$U$304,MATCH(16,EngDash,0))="","PENDING",INDEX(ENGINE!$F$5:$F$304,MATCH(16,EngDash,0))&" "&TEXT(INDEX(ENGINE!$U$5:$U$304,MATCH(16,EngDash,0)),"+0.0;-0.0;""PK""")))} -> PENDING | D20: {=IF($A20="","",INDEX(ENGINE!$T$5:$T$304,MATCH(16,EngDash,0)))} -> DEN -0.4 | E20: {=IF($A20="","",IF(INDEX(ENGINE!$V$5:$V$304,MATCH(16,EngDash,0))="","",TEXT(INDEX(ENGINE!$W$5:$W$304,MATCH(16,EngDash,0)),"0.0")&" — "&INDEX(ENGINE!$X$5:$X$304,MATCH(16,EngDash,0))))} | F20: {=IF($A20="","",INDEX(ENGINE!$Z$5:$Z$304,MATCH(16,EngDash,0)))} | G20: {=IF($A20="","",INDEX(ENGINE!$AH$5:$AH$304,MATCH(16,EngDash,0)))} | H20: {=IF($A20="","",INDEX(ENGINE!$AG$5:$AG$304,MATCH(16,EngDash,0)))} -> 0 | I20: {=IF($A20="","",IF(INDEX(ENGINE!$AI$5:$AI$304,MATCH(16,EngDash,0))="","",INDEX(ENGINE!$AK$5:$AK$304,MATCH(16,EngDash,0))&" "&TEXT(INDEX(ENGINE!$AJ$5:$AJ$304,MATCH(16,EngDash,0)),"0.0")))} | J20: {=IF($A20="","",INDEX(ENGINE!$AM$5:$AM$304,MATCH(16,EngDash,0)))} | K20: {=IF($A20="","",INDEX(ENGINE!$AN$5:$AN$304,MATCH(16,EngDash,0)))} -> BET OVER at ≤ -3.0 | BET UNDER at ≥ 3.0 | L20: {=IF($A20="","",INDEX(ENGINE!$AQ$5:$AQ$304,MATCH(16,EngDash,0)))} -> PENDING BOTH | M20: {=IF($A20="","",INDEX(ENGINE!$AP$5:$AP$304,MATCH(16,EngDash,0)))} -> READY | N20: {=IF($A20="","",INDEX(ENGINE!$AS$5:$AS$304,MATCH(16,EngDash,0)))} -> 50 | O20: {=IF($A20="","",INDEX(ENGINE!$AT$5:$AT$304,MATCH(16,EngDash,0)))} -> 1 | P20: {=IF($A20="","",INDEX(RatMode,MATCH(INDEX(ENGINE!$E$5:$E$304,MATCH(16,EngDash,0)),RatTeams,0))&"/"&INDEX(RatMode,MATCH(INDEX(ENGINE!$F$5:$F$304,MATCH(16,EngDash,0)),RatTeams,0)))} -> BASIC/BASIC | Q20: {=IF($A20="","",INDEX(ENGINE!$AU$5:$AU$304,MATCH(16,EngDash,0)))}

Sheet ENGINE
A1: MATCHUP ENGINE — full bridge from neutral-field rating difference to final number, one row per game
A2: Sign convention: FinalMargin = projected HOME margin (+ = home wins). Spreads display book-style (negative = favorite). SpreadEdge = FinalMargin + MarketHomeSpread: positive = value on HOME, negative = value on AWAY. Every step between ratings and final number is a visible column.
A4: Seq | B4: GameID | C4: Wk | D4: Date | E4: Away | F4: Home | G4: Neutral | H4: Roof | I4: DashOrd | J4: AwayEff | K4: HomeEff | L4: NeutralDiff | M4: HFA | N4: QBadj | O4: RestAdj | P4: ManualAdj | Q4: BaseMargin | R4: OverrideMargin | S4: FinalMargin | T4: ModelSpread | U4: MktHomeSpr | V4: SpreadEdge | W4: AbsEdge | X4: SupportedSide | Y4: ATSconf | Z4: ATS_REC | AA4: AwayExpPts | AB4: HomeExpPts | AC4: QBTotAdj | AD4: ManualTotAdj | AE4: BaseTotal | AF4: OverrideTotal | AG4: FinalTotal | AH4: MktTotal | AI4: TotalEdge | AJ4: AbsTotEdge | AK4: Direction | AL4: Totconf | AM4: TOTAL_REC | AN4: TotalTrigger | AO4: QBUnc | AP4: DQ | AQ4: OpsStatus | AR4: OverrideFlag | AS4: ReviewPriority | AT4: RPrank | AU4: Notes
A5: 1 | B5: {=IFERROR(INDEX(SchedZone,MATCH($A5,SchedSeq,0),MAP!$B$6),"")} -> 2026_01_NE_SEA | C5: {=IF($B5="","",INDEX(SchedZone,MATCH($A5,SchedSeq,0),MAP!$B$4))} -> 1 | D5: {=IF($B5="","",INDEX(SchedZone,MATCH($A5,SchedSeq,0),MAP!$B$7))} -> 46274 | E5: {=IF($B5="","",IF(COUNTIF(Teams,INDEX(SchedZone,MATCH($A5,SchedSeq,0),MAP!$B$10))>0,INDEX(SchedZone,MATCH($A5,SchedSeq,0),MAP!$B$10),IFERROR(INDEX(LISTS!$D$2:$D$12,MATCH(INDEX(SchedZone,MATCH($A5,SchedSeq,0),MAP!$B$10),LISTS!$C$2:$C$12,0)),"⚠ "&INDEX(SchedZone,MATCH($A5,SchedSeq,0),MAP!$B$10))))} -> NE | F5: {=IF($B5="","",IF(COUNTIF(Teams,INDEX(SchedZone,MATCH($A5,SchedSeq,0),MAP!$B$12))>0,INDEX(SchedZone,MATCH($A5,SchedSeq,0),MAP!$B$12),IFERROR(INDEX(LISTS!$D$2:$D$12,MATCH(INDEX(SchedZone,MATCH($A5,SchedSeq,0),MAP!$B$12),LISTS!$C$2:$C$12,0)),"⚠ "&INDEX(SchedZone,MATCH($A5,SchedSeq,0),MAP!$B$12))))} -> SEA | G5: {=IF($B5="","",IF(INDEX(SchedZone,MATCH($A5,SchedSeq,0),MAP!$B$14)="Neutral","Y",""))} | H5: {=IF($B5="","",INDEX(SchedZone,MATCH($A5,SchedSeq,0),MAP!$B$17))} -> outdoors | I5: =IF(OR($B5="",$C5<>CurrentWeek),"",COUNTIF($C$5:$C5,CurrentWeek)) -> 1 | J5: {=IF($B5="","",IFERROR(INDEX(RatEff,MATCH($E5,RatTeams,0)),"⚠ TEAM NOT FOUND"))} -> 2.09 | K5: {=IF($B5="","",IFERROR(INDEX(RatEff,MATCH($F5,RatTeams,0)),"⚠ TEAM NOT FOUND"))} -> 4.1 | L5: =IF(OR($B5="",NOT(ISNUMBER($J5)),NOT(ISNUMBER($K5))),"",$K5-$J5) -> 2.01 | M5: {=IF($B5="","",IF($G5="Y",NeutralHFA,IFERROR(INDEX(HFAexcVal,MATCH($F5,HFAexcTeam,0)),HFA_Base)))} -> 1.6 | N5: {=IF($B5="","",IFERROR(INDEX(QBSpreadEff,MATCH($F5,QBTeams,0)),0)-IFERROR(INDEX(QBSpreadEff,MATCH($E5,QBTeams,0)),0))} -> 0 | O5: {=IF($B5="","",IFERROR(MEDIAN(-RestCapPts,RestCapPts,RestPerDay*(INDEX(SchedZone,MATCH($A5,SchedSeq,0),MAP!$B$16)-INDEX(SchedZone,MATCH($A5,SchedSeq,0),MAP!$B$15))),0))} -> 0 | P5: =IF($B5="","",SUMIFS(AdjSpread,AdjGameID,$B5,AdjTeam,$F5,AdjActive,1)-SUMIFS(AdjSpread,AdjGameID,$B5,AdjTeam,$E5,AdjActive,1)) -> 0 | Q5: =IF($L5="","",ROUND($L5+$M5+$N5+$O5+$P5,2)) -> 3.61 | S5: =IF(AND($R5="",$Q5=""),"",IF($R5<>"",$R5,$Q5)) -> 3.61 | T5: =IF($S5="","",IF(ABS($S5)<0.05,"PK",IF($S5>0,$F5&" "&TEXT(-$S5,"+0.0;-0.0"),$E5&" "&TEXT($S5,"+0.0;-0.0")))) -> SEA -3.6 | U5: {=IF($B5="","",IFERROR(INDEX(MktHomeSpread,MATCH($B5,MktGameID,0)),""))} | V5: =IF(OR($S5="",$U5=""),"",ROUND($S5+$U5,2)) | W5: =IF($V5="","",ABS($V5)) | X5: =IF($V5="","",IF($V5>0,$F5&" "&TEXT($U5,"+0.0;-0.0;""PK"""),$E5&" "&TEXT(-$U5,"+0.0;-0.0;""PK"""))) | Y5: {=IF($B5="","",IF((IF(AND(IFERROR(INDEX(RatGP,MATCH($E5,RatTeams,0)),0)>=MinGamesTrust,IFERROR(INDEX(RatGP,MATCH($F5,RatTeams,0)),0)>=MinGamesTrust),1,0)+IF($AP5="READY",1,0)+IF(AND(IFERROR(INDEX(RatMode,MATCH($E5,RatTeams,0)),"")="ENHANCED",IFERROR(INDEX(RatMode,MATCH($F5,RatTeams,0)),"")="ENHANCED"),1,0)+IF($AO5="",1,0)+IF(IFERROR(INDEX(MktStale,MATCH($B5,MktGameID,0)),"")<>"STALE",1,0))>=5,"High",IF((IF(AND(IFERROR(INDEX(RatGP,MATCH($E5,RatTeams,0)),0)>=MinGamesTrust,IFERROR(INDEX(RatGP,MATCH($F5,RatTeams,0)),0)>=MinGamesTrust),1,0)+IF($AP5="READY",1,0)+IF(AND(IFERROR(INDEX(RatMode,MATCH($E5,RatTeams,0)),"")="ENHANCED",IFERROR(INDEX(RatMode,MATCH($F5,RatTeams,0)),"")="ENHANCED"),1,0)+IF($AO5="",1,0)+IF(IFERROR(INDEX(MktStale,MATCH($B5,MktGameID,0)),"")<>"STALE",1,0))>=4,"Medium","Low")))} -> Low | Z5: =IF(OR($B5="",$V5=""),"",IF(LEFT($AP5,7)="BLOCKED","",IF(AND($W5>=BetATS,$Y5<>"Low"),IF(AND(EnableBetLabels="Y",$Y5="High",$AP5="READY",ABS(IF($P5="",0,$P5))<=AdjCap),"BET","STRONG INVESTIGATE"),IF($W5>=InvATS,"INVESTIGATE",IF(AND($W5>=LeanATS,$Y5<>"Low"),"LEAN",""))))) | AA5: {=IF($B5="","",IFERROR(ROUND(((1-TotRegress)*0.5*(INDEX(CalcOffPl,MATCH($E5,CalcTeams,0))+INDEX(CalcDefPl,MATCH($F5,CalcTeams,0)))+TotRegress*LeaguePlays)*(INDEX(CalcOffAdj,MATCH($E5,CalcTeams,0))+INDEX(CalcDefAdj,MATCH($F5,CalcTeams,0))-LeaguePPP)+DstPts,2),""))} -> 0 | AB5: {=IF($B5="","",IFERROR(ROUND(((1-TotRegress)*0.5*(INDEX(CalcOffPl,MATCH($F5,CalcTeams,0))+INDEX(CalcDefPl,MATCH($E5,CalcTeams,0)))+TotRegress*LeaguePlays)*(INDEX(CalcOffAdj,MATCH($F5,CalcTeams,0))+INDEX(CalcDefAdj,MATCH($E5,CalcTeams,0))-LeaguePPP)+DstPts,2),""))} -> 0 | AC5: {=IF($B5="","",IFERROR(INDEX(QBTotEff,MATCH($F5,QBTeams,0)),0)+IFERROR(INDEX(QBTotEff,MATCH($E5,QBTeams,0)),0))} -> 0 | AD5: =IF($B5="","",SUMIFS(AdjTot,AdjGameID,$B5,AdjActive,1)) -> 0 | AE5: =IF(OR($AA5="",$AB5=""),"",ROUND($AA5+$AB5+$AC5+$AD5,2)) -> 0 | AG5: =IF(AND($AF5="",$AE5=""),"",IF($AF5<>"",$AF5,$AE5)) -> 0 | AH5: {=IF($B5="","",IFERROR(INDEX(MktTotal,MATCH($B5,MktGameID,0)),""))} | AI5: =IF(OR($AG5="",$AH5=""),"",ROUND($AG5-$AH5,2)) | AJ5: =IF($AI5="","",ABS($AI5)) | AK5: =IF($AI5="","",IF($AI5>0.05,"OVER",IF($AI5<-0.05,"UNDER","—"))) | AL5: {=IF($B5="","",IF((IF(AND(IFERROR(INDEX(RatGP,MATCH($E5,RatTeams,0)),0)>=MinGamesTrust,IFERROR(INDEX(RatGP,MATCH($F5,RatTeams,0)),0)>=MinGamesTrust),1,0)+IF($AP5="READY",1,0)+IF($AO5="",1,0)+IF(IFERROR(INDEX(MktStale,MATCH($B5,MktGameID,0)),"")<>"STALE",1,0)+IF(ABS(IF($AD5="",0,$AD5))<=AdjCap,1,0))>=5,"High",IF((IF(AND(IFERROR(INDEX(RatGP,MATCH($E5,RatTeams,0)),0)>=MinGamesTrust,IFERROR(INDEX(RatGP,MATCH($F5,RatTeams,0)),0)>=MinGamesTrust),1,0)+IF($AP5="READY",1,0)+IF($AO5="",1,0)+IF(IFERROR(INDEX(MktStale,MATCH($B5,MktGameID,0)),"")<>"STALE",1,0)+IF(ABS(IF($AD5="",0,$AD5))<=AdjCap,1,0))>=4,"Medium","Low")))} -> Medium | AM5: =IF(OR($B5="",$AI5=""),"",IF(LEFT($AP5,7)="BLOCKED","",IF(AND($AJ5>=BetTot,$AL5<>"Low"),IF(AND(EnableBetLabels="Y",$AL5="High",$AP5="READY"),"BET ","STRONG INVESTIGATE ")&$AK5,IF($AJ5>=InvTot,"INVESTIGATE "&$AK5,IF(AND($AJ5>=LeanTot,$AL5<>"Low"),"LEAN "&$AK5,""))))) | AN5: =IF($AG5="","","BET OVER at ≤ "&TEXT($AG5-BetTot,"0.0")&" | BET UNDER at ≥ "&TEXT($AG5+BetTot,"0.0")) -> BET OVER at ≤ -3.0 | BET UNDER at ≥ 3.0 | AO5: {=IF($B5="","",IF(OR(IFERROR(INDEX(QBFlag,MATCH($F5,QBTeams,0)),1)=1,IFERROR(INDEX(QBFlag,MATCH($E5,QBTeams,0)),1)=1),"QB UNCERTAIN",""))} | AP5: {=IF($B5="","",IFERROR(INDEX(DQStatus,MATCH($B5,DQGameID,0)),"BLOCKED — DQ ROW NOT FOUND"))} -> READY | AQ5: {=IF($B5="","",IF(LEFT($AP5,7)="BLOCKED",IF($AP5="BLOCKED","BLOCKED — see DATA QUALITY",$AP5),IF(AND($U5="",$AH5=""),"PENDING BOTH",IF($U5="","PENDING SPREAD",IF($AH5="","PENDING TOTAL",IF(IFERROR(INDEX(MktStale,MATCH($B5,MktGameID,0)),"")="STALE","STALE LINE",IF($AO5<>"",$AO5,IF(OR(NOT(ISNUMBER($J5)),NOT(ISNUMBER($K5))),"DATA INCOMPLETE","READY"))))))))} -> PENDING BOTH | AR5: =IF(OR($R5<>"",$AF5<>""),"OVERRIDE","") | AS5: {=IF(OR($B5="",$C5<>CurrentWeek),"",ROUND(25*MIN(1,IF($W5="",0,$W5)/5)+20*IF($AP5="READY",1,0)+20*IF($AO5="",1,0)+15*IF(IFERROR(INDEX(MktStale,MATCH($B5,MktGameID,0)),"x")="OK",1,0)+10*MAX(0,1-ABS(IF($P5="",0,$P5))/AdjCap)+10*IF(AND($Z5<>"",$AM5<>""),1,0),0))} -> 50 | AT5: =IF($AS5="","",RANK($AS5,$AS$5:$AS$304,0)) -> 1
A6: 2 | B6: {=IFERROR(INDEX(SchedZone,MATCH($A6,SchedSeq,0),MAP!$B$6),"")} -> 2026_01_SF_LA | C6: {=IF($B6="","",INDEX(SchedZone,MATCH($A6,SchedSeq,0),MAP!$B$4))} -> 1 | D6: {=IF($B6="","",INDEX(SchedZone,MATCH($A6,SchedSeq,0),MAP!$B$7))} -> 46275 | E6: {=IF($B6="","",IF(COUNTIF(Teams,INDEX(SchedZone,MATCH($A6,SchedSeq,0),MAP!$B$10))>0,INDEX(SchedZone,MATCH($A6,SchedSeq,0),MAP!$B$10),IFERROR(INDEX(LISTS!$D$2:$D$12,MATCH(INDEX(SchedZone,MATCH($A6,SchedSeq,0),MAP!$B$10),LISTS!$C$2:$C$12,0)),"⚠ "&INDEX(SchedZone,MATCH($A6,SchedSeq,0),MAP!$B$10))))} -> SF | F6: {=IF($B6="","",IF(COUNTIF(Teams,INDEX(SchedZone,MATCH($A6,SchedSeq,0),MAP!$B$12))>0,INDEX(SchedZone,MATCH($A6,SchedSeq,0),MAP!$B$12),IFERROR(INDEX(LISTS!$D$2:$D$12,MATCH(INDEX(SchedZone,MATCH($A6,SchedSeq,0),MAP!$B$12),LISTS!$C$2:$C$12,0)),"⚠ "&INDEX(SchedZone,MATCH($A6,SchedSeq,0),MAP!$B$12))))} -> LA | G6: {=IF($B6="","",IF(INDEX(SchedZone,MATCH($A6,SchedSeq,0),MAP!$B$14)="Neutral","Y",""))} -> Y | H6: {=IF($B6="","",INDEX(SchedZone,MATCH($A6,SchedSeq,0),MAP!$B$17))} -> dome | I6: =IF(OR($B6="",$C6<>CurrentWeek),"",COUNTIF($C$5:$C6,CurrentWeek)) -> 2 | J6: {=IF($B6="","",IFERROR(INDEX(RatEff,MATCH($E6,RatTeams,0)),"⚠ TEAM NOT FOUND"))} -> 1.78 | K6: {=IF($B6="","",IFERROR(INDEX(RatEff,MATCH($F6,RatTeams,0)),"⚠ TEAM NOT FOUND"))} -> 4.09 | L6: =IF(OR($B6="",NOT(ISNUMBER($J6)),NOT(ISNUMBER($K6))),"",$K6-$J6) -> 2.31 | M6: {=IF($B6="","",IF($G6="Y",NeutralHFA,IFERROR(INDEX(HFAexcVal,MATCH($F6,HFAexcTeam,0)),HFA_Base)))} -> 0 | N6: {=IF($B6="","",IFERROR(INDEX(QBSpreadEff,MATCH($F6,QBTeams,0)),0)-IFERROR(INDEX(QBSpreadEff,MATCH($E6,QBTeams,0)),0))} -> 0 | O6: {=IF($B6="","",IFERROR(MEDIAN(-RestCapPts,RestCapPts,RestPerDay*(INDEX(SchedZone,MATCH($A6,SchedSeq,0),MAP!$B$16)-INDEX(SchedZone,MATCH($A6,SchedSeq,0),MAP!$B$15))),0))} -> 0 | P6: =IF($B6="","",SUMIFS(AdjSpread,AdjGameID,$B6,AdjTeam,$F6,AdjActive,1)-SUMIFS(AdjSpread,AdjGameID,$B6,AdjTeam,$E6,AdjActive,1)) -> 0 | Q6: =IF($L6="","",ROUND($L6+$M6+$N6+$O6+$P6,2)) -> 2.31 | S6: =IF(AND($R6="",$Q6=""),"",IF($R6<>"",$R6,$Q6)) -> 2.31 | T6: =IF($S6="","",IF(ABS($S6)<0.05,"PK",IF($S6>0,$F6&" "&TEXT(-$S6,"+0.0;-0.0"),$E6&" "&TEXT($S6,"+0.0;-0.0")))) -> LA -2.3 | U6: {=IF($B6="","",IFERROR(INDEX(MktHomeSpread,MATCH($B6,MktGameID,0)),""))} | V6: =IF(OR($S6="",$U6=""),"",ROUND($S6+$U6,2)) | W6: =IF($V6="","",ABS($V6)) | X6: =IF($V6="","",IF($V6>0,$F6&" "&TEXT($U6,"+0.0;-0.0;""PK"""),$E6&" "&TEXT(-$U6,"+0.0;-0.0;""PK"""))) | Y6: {=IF($B6="","",IF((IF(AND(IFERROR(INDEX(RatGP,MATCH($E6,RatTeams,0)),0)>=MinGamesTrust,IFERROR(INDEX(RatGP,MATCH($F6,RatTeams,0)),0)>=MinGamesTrust),1,0)+IF($AP6="READY",1,0)+IF(AND(IFERROR(INDEX(RatMode,MATCH($E6,RatTeams,0)),"")="ENHANCED",IFERROR(INDEX(RatMode,MATCH($F6,RatTeams,0)),"")="ENHANCED"),1,0)+IF($AO6="",1,0)+IF(IFERROR(INDEX(MktStale,MATCH($B6,MktGameID,0)),"")<>"STALE",1,0))>=5,"High",IF((IF(AND(IFERROR(INDEX(RatGP,MATCH($E6,RatTeams,0)),0)>=MinGamesTrust,IFERROR(INDEX(RatGP,MATCH($F6,RatTeams,0)),0)>=MinGamesTrust),1,0)+IF($AP6="READY",1,0)+IF(AND(IFERROR(INDEX(RatMode,MATCH($E6,RatTeams,0)),"")="ENHANCED",IFERROR(INDEX(RatMode,MATCH($F6,RatTeams,0)),"")="ENHANCED"),1,0)+IF($AO6="",1,0)+IF(IFERROR(INDEX(MktStale,MATCH($B6,MktGameID,0)),"")<>"STALE",1,0))>=4,"Medium","Low")))} -> Low | Z6: =IF(OR($B6="",$V6=""),"",IF(LEFT($AP6,7)="BLOCKED","",IF(AND($W6>=BetATS,$Y6<>"Low"),IF(AND(EnableBetLabels="Y",$Y6="High",$AP6="READY",ABS(IF($P6="",0,$P6))<=AdjCap),"BET","STRONG INVESTIGATE"),IF($W6>=InvATS,"INVESTIGATE",IF(AND($W6>=LeanATS,$Y6<>"Low"),"LEAN",""))))) | AA6: {=IF($B6="","",IFERROR(ROUND(((1-TotRegress)*0.5*(INDEX(CalcOffPl,MATCH($E6,CalcTeams,0))+INDEX(CalcDefPl,MATCH($F6,CalcTeams,0)))+TotRegress*LeaguePlays)*(INDEX(CalcOffAdj,MATCH($E6,CalcTeams,0))+INDEX(CalcDefAdj,MATCH($F6,CalcTeams,0))-LeaguePPP)+DstPts,2),""))} -> 0 | AB6: {=IF($B6="","",IFERROR(ROUND(((1-TotRegress)*0.5*(INDEX(CalcOffPl,MATCH($F6,CalcTeams,0))+INDEX(CalcDefPl,MATCH($E6,CalcTeams,0)))+TotRegress*LeaguePlays)*(INDEX(CalcOffAdj,MATCH($F6,CalcTeams,0))+INDEX(CalcDefAdj,MATCH($E6,CalcTeams,0))-LeaguePPP)+DstPts,2),""))} -> 0 | AC6: {=IF($B6="","",IFERROR(INDEX(QBTotEff,MATCH($F6,QBTeams,0)),0)+IFERROR(INDEX(QBTotEff,MATCH($E6,QBTeams,0)),0))} -> 0 | AD6: =IF($B6="","",SUMIFS(AdjTot,AdjGameID,$B6,AdjActive,1)) -> 0 | AE6: =IF(OR($AA6="",$AB6=""),"",ROUND($AA6+$AB6+$AC6+$AD6,2)) -> 0 | AG6: =IF(AND($AF6="",$AE6=""),"",IF($AF6<>"",$AF6,$AE6)) -> 0 | AH6: {=IF($B6="","",IFERROR(INDEX(MktTotal,MATCH($B6,MktGameID,0)),""))} | AI6: =IF(OR($AG6="",$AH6=""),"",ROUND($AG6-$AH6,2)) | AJ6: =IF($AI6="","",ABS($AI6)) | AK6: =IF($AI6="","",IF($AI6>0.05,"OVER",IF($AI6<-0.05,"UNDER","—"))) | AL6: {=IF($B6="","",IF((IF(AND(IFERROR(INDEX(RatGP,MATCH($E6,RatTeams,0)),0)>=MinGamesTrust,IFERROR(INDEX(RatGP,MATCH($F6,RatTeams,0)),0)>=MinGamesTrust),1,0)+IF($AP6="READY",1,0)+IF($AO6="",1,0)+IF(IFERROR(INDEX(MktStale,MATCH($B6,MktGameID,0)),"")<>"STALE",1,0)+IF(ABS(IF($AD6="",0,$AD6))<=AdjCap,1,0))>=5,"High",IF((IF(AND(IFERROR(INDEX(RatGP,MATCH($E6,RatTeams,0)),0)>=MinGamesTrust,IFERROR(INDEX(RatGP,MATCH($F6,RatTeams,0)),0)>=MinGamesTrust),1,0)+IF($AP6="READY",1,0)+IF($AO6="",1,0)+IF(IFERROR(INDEX(MktStale,MATCH($B6,MktGameID,0)),"")<>"STALE",1,0)+IF(ABS(IF($AD6="",0,$AD6))<=AdjCap,1,0))>=4,"Medium","Low")))} -> Medium | AM6: =IF(OR($B6="",$AI6=""),"",IF(LEFT($AP6,7)="BLOCKED","",IF(AND($AJ6>=BetTot,$AL6<>"Low"),IF(AND(EnableBetLabels="Y",$AL6="High",$AP6="READY"),"BET ","STRONG INVESTIGATE ")&$AK6,IF($AJ6>=InvTot,"INVESTIGATE "&$AK6,IF(AND($AJ6>=LeanTot,$AL6<>"Low"),"LEAN "&$AK6,""))))) | AN6: =IF($AG6="","","BET OVER at ≤ "&TEXT($AG6-BetTot,"0.0")&" | BET UNDER at ≥ "&TEXT($AG6+BetTot,"0.0")) -> BET OVER at ≤ -3.0 | BET UNDER at ≥ 3.0 | AO6: {=IF($B6="","",IF(OR(IFERROR(INDEX(QBFlag,MATCH($F6,QBTeams,0)),1)=1,IFERROR(INDEX(QBFlag,MATCH($E6,QBTeams,0)),1)=1),"QB UNCERTAIN",""))} | AP6: {=IF($B6="","",IFERROR(INDEX(DQStatus,MATCH($B6,DQGameID,0)),"BLOCKED — DQ ROW NOT FOUND"))} -> READY | AQ6: {=IF($B6="","",IF(LEFT($AP6,7)="BLOCKED",IF($AP6="BLOCKED","BLOCKED — see DATA QUALITY",$AP6),IF(AND($U6="",$AH6=""),"PENDING BOTH",IF($U6="","PENDING SPREAD",IF($AH6="","PENDING TOTAL",IF(IFERROR(INDEX(MktStale,MATCH($B6,MktGameID,0)),"")="STALE","STALE LINE",IF($AO6<>"",$AO6,IF(OR(NOT(ISNUMBER($J6)),NOT(ISNUMBER($K6))),"DATA INCOMPLETE","READY"))))))))} -> PENDING BOTH | AR6: =IF(OR($R6<>"",$AF6<>""),"OVERRIDE","") | AS6: {=IF(OR($B6="",$C6<>CurrentWeek),"",ROUND(25*MIN(1,IF($W6="",0,$W6)/5)+20*IF($AP6="READY",1,0)+20*IF($AO6="",1,0)+15*IF(IFERROR(INDEX(MktStale,MATCH($B6,MktGameID,0)),"x")="OK",1,0)+10*MAX(0,1-ABS(IF($P6="",0,$P6))/AdjCap)+10*IF(AND($Z6<>"",$AM6<>""),1,0),0))} -> 50 | AT6: =IF($AS6="","",RANK($AS6,$AS$5:$AS$304,0)) -> 1
A7: 3 | B7: {=IFERROR(INDEX(SchedZone,MATCH($A7,SchedSeq,0),MAP!$B$6),"")} -> 2026_01_CHI_CAR | C7: {=IF($B7="","",INDEX(SchedZone,MATCH($A7,SchedSeq,0),MAP!$B$4))} -> 1 | D7: {=IF($B7="","",INDEX(SchedZone,MATCH($A7,SchedSeq,0),MAP!$B$7))} -> 46278 | E7: {=IF($B7="","",IF(COUNTIF(Teams,INDEX(SchedZone,MATCH($A7,SchedSeq,0),MAP!$B$10))>0,INDEX(SchedZone,MATCH($A7,SchedSeq,0),MAP!$B$10),IFERROR(INDEX(LISTS!$D$2:$D$12,MATCH(INDEX(SchedZone,MATCH($A7,SchedSeq,0),MAP!$B$10),LISTS!$C$2:$C$12,0)),"⚠ "&INDEX(SchedZone,MATCH($A7,SchedSeq,0),MAP!$B$10))))} -> CHI | F7: {=IF($B7="","",IF(COUNTIF(Teams,INDEX(SchedZone,MATCH($A7,SchedSeq,0),MAP!$B$12))>0,INDEX(SchedZone,MATCH($A7,SchedSeq,0),MAP!$B$12),IFERROR(INDEX(LISTS!$D$2:$D$12,MATCH(INDEX(SchedZone,MATCH($A7,SchedSeq,0),MAP!$B$12),LISTS!$C$2:$C$12,0)),"⚠ "&INDEX(SchedZone,MATCH($A7,SchedSeq,0),MAP!$B$12))))} -> CAR | G7: {=IF($B7="","",IF(INDEX(SchedZone,MATCH($A7,SchedSeq,0),MAP!$B$14)="Neutral","Y",""))} | H7: {=IF($B7="","",INDEX(SchedZone,MATCH($A7,SchedSeq,0),MAP!$B$17))} -> outdoors | I7: =IF(OR($B7="",$C7<>CurrentWeek),"",COUNTIF($C$5:$C7,CurrentWeek)) -> 3 | J7: {=IF($B7="","",IFERROR(INDEX(RatEff,MATCH($E7,RatTeams,0)),"⚠ TEAM NOT FOUND"))} -> 0.86 | K7: {=IF($B7="","",IFERROR(INDEX(RatEff,MATCH($F7,RatTeams,0)),"⚠ TEAM NOT FOUND"))} -> -1.3 | L7: =IF(OR($B7="",NOT(ISNUMBER($J7)),NOT(ISNUMBER($K7))),"",$K7-$J7) -> -2.16 | M7: {=IF($B7="","",IF($G7="Y",NeutralHFA,IFERROR(INDEX(HFAexcVal,MATCH($F7,HFAexcTeam,0)),HFA_Base)))} -> 1.6 | N7: {=IF($B7="","",IFERROR(INDEX(QBSpreadEff,MATCH($F7,QBTeams,0)),0)-IFERROR(INDEX(QBSpreadEff,MATCH($E7,QBTeams,0)),0))} -> 0 | O7: {=IF($B7="","",IFERROR(MEDIAN(-RestCapPts,RestCapPts,RestPerDay*(INDEX(SchedZone,MATCH($A7,SchedSeq,0),MAP!$B$16)-INDEX(SchedZone,MATCH($A7,SchedSeq,0),MAP!$B$15))),0))} -> 0 | P7: =IF($B7="","",SUMIFS(AdjSpread,AdjGameID,$B7,AdjTeam,$F7,AdjActive,1)-SUMIFS(AdjSpread,AdjGameID,$B7,AdjTeam,$E7,AdjActive,1)) -> 0 | Q7: =IF($L7="","",ROUND($L7+$M7+$N7+$O7+$P7,2)) -> -0.56 | S7: =IF(AND($R7="",$Q7=""),"",IF($R7<>"",$R7,$Q7)) -> -0.56 | T7: =IF($S7="","",IF(ABS($S7)<0.05,"PK",IF($S7>0,$F7&" "&TEXT(-$S7,"+0.0;-0.0"),$E7&" "&TEXT($S7,"+0.0;-0.0")))) -> CHI -0.6 | U7: {=IF($B7="","",IFERROR(INDEX(MktHomeSpread,MATCH($B7,MktGameID,0)),""))} | V7: =IF(OR($S7="",$U7=""),"",ROUND($S7+$U7,2)) | W7: =IF($V7="","",ABS($V7)) | X7: =IF($V7="","",IF($V7>0,$F7&" "&TEXT($U7,"+0.0;-0.0;""PK"""),$E7&" "&TEXT(-$U7,"+0.0;-0.0;""PK"""))) | Y7: {=IF($B7="","",IF((IF(AND(IFERROR(INDEX(RatGP,MATCH($E7,RatTeams,0)),0)>=MinGamesTrust,IFERROR(INDEX(RatGP,MATCH($F7,RatTeams,0)),0)>=MinGamesTrust),1,0)+IF($AP7="READY",1,0)+IF(AND(IFERROR(INDEX(RatMode,MATCH($E7,RatTeams,0)),"")="ENHANCED",IFERROR(INDEX(RatMode,MATCH($F7,RatTeams,0)),"")="ENHANCED"),1,0)+IF($AO7="",1,0)+IF(IFERROR(INDEX(MktStale,MATCH($B7,MktGameID,0)),"")<>"STALE",1,0))>=5,"High",IF((IF(AND(IFERROR(INDEX(RatGP,MATCH($E7,RatTeams,0)),0)>=MinGamesTrust,IFERROR(INDEX(RatGP,MATCH($F7,RatTeams,0)),0)>=MinGamesTrust),1,0)+IF($AP7="READY",1,0)+IF(AND(IFERROR(INDEX(RatMode,MATCH($E7,RatTeams,0)),"")="ENHANCED",IFERROR(INDEX(RatMode,MATCH($F7,RatTeams,0)),"")="ENHANCED"),1,0)+IF($AO7="",1,0)+IF(IFERROR(INDEX(MktStale,MATCH($B7,MktGameID,0)),"")<>"STALE",1,0))>=4,"Medium","Low")))} -> Low | Z7: =IF(OR($B7="",$V7=""),"",IF(LEFT($AP7,7)="BLOCKED","",IF(AND($W7>=BetATS,$Y7<>"Low"),IF(AND(EnableBetLabels="Y",$Y7="High",$AP7="READY",ABS(IF($P7="",0,$P7))<=AdjCap),"BET","STRONG INVESTIGATE"),IF($W7>=InvATS,"INVESTIGATE",IF(AND($W7>=LeanATS,$Y7<>"Low"),"LEAN",""))))) | AA7: {=IF($B7="","",IFERROR(ROUND(((1-TotRegress)*0.5*(INDEX(CalcOffPl,MATCH($E7,CalcTeams,0))+INDEX(CalcDefPl,MATCH($F7,CalcTeams,0)))+TotRegress*LeaguePlays)*(INDEX(CalcOffAdj,MATCH($E7,CalcTeams,0))+INDEX(CalcDefAdj,MATCH($F7,CalcTeams,0))-LeaguePPP)+DstPts,2),""))} -> 0 | AB7: {=IF($B7="","",IFERROR(ROUND(((1-TotRegress)*0.5*(INDEX(CalcOffPl,MATCH($F7,CalcTeams,0))+INDEX(CalcDefPl,MATCH($E7,CalcTeams,0)))+TotRegress*LeaguePlays)*(INDEX(CalcOffAdj,MATCH($F7,CalcTeams,0))+INDEX(CalcDefAdj,MATCH($E7,CalcTeams,0))-LeaguePPP)+DstPts,2),""))} -> 0 | AC7: {=IF($B7="","",IFERROR(INDEX(QBTotEff,MATCH($F7,QBTeams,0)),0)+IFERROR(INDEX(QBTotEff,MATCH($E7,QBTeams,0)),0))} -> 0 | AD7: =IF($B7="","",SUMIFS(AdjTot,AdjGameID,$B7,AdjActive,1)) -> 0 | AE7: =IF(OR($AA7="",$AB7=""),"",ROUND($AA7+$AB7+$AC7+$AD7,2)) -> 0 | AG7: =IF(AND($AF7="",$AE7=""),"",IF($AF7<>"",$AF7,$AE7)) -> 0 | AH7: {=IF($B7="","",IFERROR(INDEX(MktTotal,MATCH($B7,MktGameID,0)),""))} | AI7: =IF(OR($AG7="",$AH7=""),"",ROUND($AG7-$AH7,2)) | AJ7: =IF($AI7="","",ABS($AI7)) | AK7: =IF($AI7="","",IF($AI7>0.05,"OVER",IF($AI7<-0.05,"UNDER","—"))) | AL7: {=IF($B7="","",IF((IF(AND(IFERROR(INDEX(RatGP,MATCH($E7,RatTeams,0)),0)>=MinGamesTrust,IFERROR(INDEX(RatGP,MATCH($F7,RatTeams,0)),0)>=MinGamesTrust),1,0)+IF($AP7="READY",1,0)+IF($AO7="",1,0)+IF(IFERROR(INDEX(MktStale,MATCH($B7,MktGameID,0)),"")<>"STALE",1,0)+IF(ABS(IF($AD7="",0,$AD7))<=AdjCap,1,0))>=5,"High",IF((IF(AND(IFERROR(INDEX(RatGP,MATCH($E7,RatTeams,0)),0)>=MinGamesTrust,IFERROR(INDEX(RatGP,MATCH($F7,RatTeams,0)),0)>=MinGamesTrust),1,0)+IF($AP7="READY",1,0)+IF($AO7="",1,0)+IF(IFERROR(INDEX(MktStale,MATCH($B7,MktGameID,0)),"")<>"STALE",1,0)+IF(ABS(IF($AD7="",0,$AD7))<=AdjCap,1,0))>=4,"Medium","Low")))} -> Medium | AM7: =IF(OR($B7="",$AI7=""),"",IF(LEFT($AP7,7)="BLOCKED","",IF(AND($AJ7>=BetTot,$AL7<>"Low"),IF(AND(EnableBetLabels="Y",$AL7="High",$AP7="READY"),"BET ","STRONG INVESTIGATE ")&$AK7,IF($AJ7>=InvTot,"INVESTIGATE "&$AK7,IF(AND($AJ7>=LeanTot,$AL7<>"Low"),"LEAN "&$AK7,""))))) | AN7: =IF($AG7="","","BET OVER at ≤ "&TEXT($AG7-BetTot,"0.0")&" | BET UNDER at ≥ "&TEXT($AG7+BetTot,"0.0")) -> BET OVER at ≤ -3.0 | BET UNDER at ≥ 3.0 | AO7: {=IF($B7="","",IF(OR(IFERROR(INDEX(QBFlag,MATCH($F7,QBTeams,0)),1)=1,IFERROR(INDEX(QBFlag,MATCH($E7,QBTeams,0)),1)=1),"QB UNCERTAIN",""))} | AP7: {=IF($B7="","",IFERROR(INDEX(DQStatus,MATCH($B7,DQGameID,0)),"BLOCKED — DQ ROW NOT FOUND"))} -> READY | AQ7: {=IF($B7="","",IF(LEFT($AP7,7)="BLOCKED",IF($AP7="BLOCKED","BLOCKED — see DATA QUALITY",$AP7),IF(AND($U7="",$AH7=""),"PENDING BOTH",IF($U7="","PENDING SPREAD",IF($AH7="","PENDING TOTAL",IF(IFERROR(INDEX(MktStale,MATCH($B7,MktGameID,0)),"")="STALE","STALE LINE",IF($AO7<>"",$AO7,IF(OR(NOT(ISNUMBER($J7)),NOT(ISNUMBER($K7))),"DATA INCOMPLETE","READY"))))))))} -> PENDING BOTH | AR7: =IF(OR($R7<>"",$AF7<>""),"OVERRIDE","") | AS7: {=IF(OR($B7="",$C7<>CurrentWeek),"",ROUND(25*MIN(1,IF($W7="",0,$W7)/5)+20*IF($AP7="READY",1,0)+20*IF($AO7="",1,0)+15*IF(IFERROR(INDEX(MktStale,MATCH($B7,MktGameID,0)),"x")="OK",1,0)+10*MAX(0,1-ABS(IF($P7="",0,$P7))/AdjCap)+10*IF(AND($Z7<>"",$AM7<>""),1,0),0))} -> 50 | AT7: =IF($AS7="","",RANK($AS7,$AS$5:$AS$304,0)) -> 1
A8: 4 | B8: {=IFERROR(INDEX(SchedZone,MATCH($A8,SchedSeq,0),MAP!$B$6),"")} -> 2026_01_TB_CIN | C8: {=IF($B8="","",INDEX(SchedZone,MATCH($A8,SchedSeq,0),MAP!$B$4))} -> 1 | D8: {=IF($B8="","",INDEX(SchedZone,MATCH($A8,SchedSeq,0),MAP!$B$7))} -> 46278 | E8: {=IF($B8="","",IF(COUNTIF(Teams,INDEX(SchedZone,MATCH($A8,SchedSeq,0),MAP!$B$10))>0,INDEX(SchedZone,MATCH($A8,SchedSeq,0),MAP!$B$10),IFERROR(INDEX(LISTS!$D$2:$D$12,MATCH(INDEX(SchedZone,MATCH($A8,SchedSeq,0),MAP!$B$10),LISTS!$C$2:$C$12,0)),"⚠ "&INDEX(SchedZone,MATCH($A8,SchedSeq,0),MAP!$B$10))))} -> TB | F8: {=IF($B8="","",IF(COUNTIF(Teams,INDEX(SchedZone,MATCH($A8,SchedSeq,0),MAP!$B$12))>0,INDEX(SchedZone,MATCH($A8,SchedSeq,0),MAP!$B$12),IFERROR(INDEX(LISTS!$D$2:$D$12,MATCH(INDEX(SchedZone,MATCH($A8,SchedSeq,0),MAP!$B$12),LISTS!$C$2:$C$12,0)),"⚠ "&INDEX(SchedZone,MATCH($A8,SchedSeq,0),MAP!$B$12))))} -> CIN | G8: {=IF($B8="","",IF(INDEX(SchedZone,MATCH($A8,SchedSeq,0),MAP!$B$14)="Neutral","Y",""))} | H8: {=IF($B8="","",INDEX(SchedZone,MATCH($A8,SchedSeq,0),MAP!$B$17))} -> outdoors | I8: =IF(OR($B8="",$C8<>CurrentWeek),"",COUNTIF($C$5:$C8,CurrentWeek)) -> 4 | J8: {=IF($B8="","",IFERROR(INDEX(RatEff,MATCH($E8,RatTeams,0)),"⚠ TEAM NOT FOUND"))} -> -0.48 | K8: {=IF($B8="","",IFERROR(INDEX(RatEff,MATCH($F8,RatTeams,0)),"⚠ TEAM NOT FOUND"))} -> -1.53 | L8: =IF(OR($B8="",NOT(ISNUMBER($J8)),NOT(ISNUMBER($K8))),"",$K8-$J8) -> -1.05 | M8: {=IF($B8="","",IF($G8="Y",NeutralHFA,IFERROR(INDEX(HFAexcVal,MATCH($F8,HFAexcTeam,0)),HFA_Base)))} -> 1.6 | N8: {=IF($B8="","",IFERROR(INDEX(QBSpreadEff,MATCH($F8,QBTeams,0)),0)-IFERROR(INDEX(QBSpreadEff,MATCH($E8,QBTeams,0)),0))} -> 0 | O8: {=IF($B8="","",IFERROR(MEDIAN(-RestCapPts,RestCapPts,RestPerDay*(INDEX(SchedZone,MATCH($A8,SchedSeq,0),MAP!$B$16)-INDEX(SchedZone,MATCH($A8,SchedSeq,0),MAP!$B$15))),0))} -> 0 | P8: =IF($B8="","",SUMIFS(AdjSpread,AdjGameID,$B8,AdjTeam,$F8,AdjActive,1)-SUMIFS(AdjSpread,AdjGameID,$B8,AdjTeam,$E8,AdjActive,1)) -> 0 | Q8: =IF($L8="","",ROUND($L8+$M8+$N8+$O8+$P8,2)) -> 0.55 | S8: =IF(AND($R8="",$Q8=""),"",IF($R8<>"",$R8,$Q8)) -> 0.55 | T8: =IF($S8="","",IF(ABS($S8)<0.05,"PK",IF($S8>0,$F8&" "&TEXT(-$S8,"+0.0;-0.0"),$E8&" "&TEXT($S8,"+0.0;-0.0")))) -> CIN -0.6 | U8: {=IF($B8="","",IFERROR(INDEX(MktHomeSpread,MATCH($B8,MktGameID,0)),""))} | V8: =IF(OR($S8="",$U8=""),"",ROUND($S8+$U8,2)) | W8: =IF($V8="","",ABS($V8)) | X8: =IF($V8="","",IF($V8>0,$F8&" "&TEXT($U8,"+0.0;-0.0;""PK"""),$E8&" "&TEXT(-$U8,"+0.0;-0.0;""PK"""))) | Y8: {=IF($B8="","",IF((IF(AND(IFERROR(INDEX(RatGP,MATCH($E8,RatTeams,0)),0)>=MinGamesTrust,IFERROR(INDEX(RatGP,MATCH($F8,RatTeams,0)),0)>=MinGamesTrust),1,0)+IF($AP8="READY",1,0)+IF(AND(IFERROR(INDEX(RatMode,MATCH($E8,RatTeams,0)),"")="ENHANCED",IFERROR(INDEX(RatMode,MATCH($F8,RatTeams,0)),"")="ENHANCED"),1,0)+IF($AO8="",1,0)+IF(IFERROR(INDEX(MktStale,MATCH($B8,MktGameID,0)),"")<>"STALE",1,0))>=5,"High",IF((IF(AND(IFERROR(INDEX(RatGP,MATCH($E8,RatTeams,0)),0)>=MinGamesTrust,IFERROR(INDEX(RatGP,MATCH($F8,RatTeams,0)),0)>=MinGamesTrust),1,0)+IF($AP8="READY",1,0)+IF(AND(IFERROR(INDEX(RatMode,MATCH($E8,RatTeams,0)),"")="ENHANCED",IFERROR(INDEX(RatMode,MATCH($F8,RatTeams,0)),"")="ENHANCED"),1,0)+IF($AO8="",1,0)+IF(IFERROR(INDEX(MktStale,MATCH($B8,MktGameID,0)),"")<>"STALE",1,0))>=4,"Medium","Low")))} -> Low | Z8: =IF(OR($B8="",$V8=""),"",IF(LEFT($AP8,7)="BLOCKED","",IF(AND($W8>=BetATS,$Y8<>"Low"),IF(AND(EnableBetLabels="Y",$Y8="High",$AP8="READY",ABS(IF($P8="",0,$P8))<=AdjCap),"BET","STRONG INVESTIGATE"),IF($W8>=InvATS,"INVESTIGATE",IF(AND($W8>=LeanATS,$Y8<>"Low"),"LEAN",""))))) | AA8: {=IF($B8="","",IFERROR(ROUND(((1-TotRegress)*0.5*(INDEX(CalcOffPl,MATCH($E8,CalcTeams,0))+INDEX(CalcDefPl,MATCH($F8,CalcTeams,0)))+TotRegress*LeaguePlays)*(INDEX(CalcOffAdj,MATCH($E8,CalcTeams,0))+INDEX(CalcDefAdj,MATCH($F8,CalcTeams,0))-LeaguePPP)+DstPts,2),""))} -> 0 | AB8: {=IF($B8="","",IFERROR(ROUND(((1-TotRegress)*0.5*(INDEX(CalcOffPl,MATCH($F8,CalcTeams,0))+INDEX(CalcDefPl,MATCH($E8,CalcTeams,0)))+TotRegress*LeaguePlays)*(INDEX(CalcOffAdj,MATCH($F8,CalcTeams,0))+INDEX(CalcDefAdj,MATCH($E8,CalcTeams,0))-LeaguePPP)+DstPts,2),""))} -> 0 | AC8: {=IF($B8="","",IFERROR(INDEX(QBTotEff,MATCH($F8,QBTeams,0)),0)+IFERROR(INDEX(QBTotEff,MATCH($E8,QBTeams,0)),0))} -> 0 | AD8: =IF($B8="","",SUMIFS(AdjTot,AdjGameID,$B8,AdjActive,1)) -> 0 | AE8: =IF(OR($AA8="",$AB8=""),"",ROUND($AA8+$AB8+$AC8+$AD8,2)) -> 0 | AG8: =IF(AND($AF8="",$AE8=""),"",IF($AF8<>"",$AF8,$AE8)) -> 0 | AH8: {=IF($B8="","",IFERROR(INDEX(MktTotal,MATCH($B8,MktGameID,0)),""))} | AI8: =IF(OR($AG8="",$AH8=""),"",ROUND($AG8-$AH8,2)) | AJ8: =IF($AI8="","",ABS($AI8)) | AK8: =IF($AI8="","",IF($AI8>0.05,"OVER",IF($AI8<-0.05,"UNDER","—"))) | AL8: {=IF($B8="","",IF((IF(AND(IFERROR(INDEX(RatGP,MATCH($E8,RatTeams,0)),0)>=MinGamesTrust,IFERROR(INDEX(RatGP,MATCH($F8,RatTeams,0)),0)>=MinGamesTrust),1,0)+IF($AP8="READY",1,0)+IF($AO8="",1,0)+IF(IFERROR(INDEX(MktStale,MATCH($B8,MktGameID,0)),"")<>"STALE",1,0)+IF(ABS(IF($AD8="",0,$AD8))<=AdjCap,1,0))>=5,"High",IF((IF(AND(IFERROR(INDEX(RatGP,MATCH($E8,RatTeams,0)),0)>=MinGamesTrust,IFERROR(INDEX(RatGP,MATCH($F8,RatTeams,0)),0)>=MinGamesTrust),1,0)+IF($AP8="READY",1,0)+IF($AO8="",1,0)+IF(IFERROR(INDEX(MktStale,MATCH($B8,MktGameID,0)),"")<>"STALE",1,0)+IF(ABS(IF($AD8="",0,$AD8))<=AdjCap,1,0))>=4,"Medium","Low")))} -> Medium | AM8: =IF(OR($B8="",$AI8=""),"",IF(LEFT($AP8,7)="BLOCKED","",IF(AND($AJ8>=BetTot,$AL8<>"Low"),IF(AND(EnableBetLabels="Y",$AL8="High",$AP8="READY"),"BET ","STRONG INVESTIGATE ")&$AK8,IF($AJ8>=InvTot,"INVESTIGATE "&$AK8,IF(AND($AJ8>=LeanTot,$AL8<>"Low"),"LEAN "&$AK8,""))))) | AN8: =IF($AG8="","","BET OVER at ≤ "&TEXT($AG8-BetTot,"0.0")&" | BET UNDER at ≥ "&TEXT($AG8+BetTot,"0.0")) -> BET OVER at ≤ -3.0 | BET UNDER at ≥ 3.0 | AO8: {=IF($B8="","",IF(OR(IFERROR(INDEX(QBFlag,MATCH($F8,QBTeams,0)),1)=1,IFERROR(INDEX(QBFlag,MATCH($E8,QBTeams,0)),1)=1),"QB UNCERTAIN",""))} | AP8: {=IF($B8="","",IFERROR(INDEX(DQStatus,MATCH($B8,DQGameID,0)),"BLOCKED — DQ ROW NOT FOUND"))} -> READY | AQ8: {=IF($B8="","",IF(LEFT($AP8,7)="BLOCKED",IF($AP8="BLOCKED","BLOCKED — see DATA QUALITY",$AP8),IF(AND($U8="",$AH8=""),"PENDING BOTH",IF($U8="","PENDING SPREAD",IF($AH8="","PENDING TOTAL",IF(IFERROR(INDEX(MktStale,MATCH($B8,MktGameID,0)),"")="STALE","STALE LINE",IF($AO8<>"",$AO8,IF(OR(NOT(ISNUMBER($J8)),NOT(ISNUMBER($K8))),"DATA INCOMPLETE","READY"))))))))} -> PENDING BOTH | AR8: =IF(OR($R8<>"",$AF8<>""),"OVERRIDE","") | AS8: {=IF(OR($B8="",$C8<>CurrentWeek),"",ROUND(25*MIN(1,IF($W8="",0,$W8)/5)+20*IF($AP8="READY",1,0)+20*IF($AO8="",1,0)+15*IF(IFERROR(INDEX(MktStale,MATCH($B8,MktGameID,0)),"x")="OK",1,0)+10*MAX(0,1-ABS(IF($P8="",0,$P8))/AdjCap)+10*IF(AND($Z8<>"",$AM8<>""),1,0),0))} -> 50 | AT8: =IF($AS8="","",RANK($AS8,$AS$5:$AS$304,0)) -> 1
A9: 5 | B9: {=IFERROR(INDEX(SchedZone,MATCH($A9,SchedSeq,0),MAP!$B$6),"")} -> 2026_01_NO_DET | C9: {=IF($B9="","",INDEX(SchedZone,MATCH($A9,SchedSeq,0),MAP!$B$4))} -> 1 | D9: {=IF($B9="","",INDEX(SchedZone,MATCH($A9,SchedSeq,0),MAP!$B$7))} -> 46278 | E9: {=IF($B9="","",IF(COUNTIF(Teams,INDEX(SchedZone,MATCH($A9,SchedSeq,0),MAP!$B$10))>0,INDEX(SchedZone,MATCH($A9,SchedSeq,0),MAP!$B$10),IFERROR(INDEX(LISTS!$D$2:$D$12,MATCH(INDEX(SchedZone,MATCH($A9,SchedSeq,0),MAP!$B$10),LISTS!$C$2:$C$12,0)),"⚠ "&INDEX(SchedZone,MATCH($A9,SchedSeq,0),MAP!$B$10))))} -> NO | F9: {=IF($B9="","",IF(COUNTIF(Teams,INDEX(SchedZone,MATCH($A9,SchedSeq,0),MAP!$B$12))>0,INDEX(SchedZone,MATCH($A9,SchedSeq,0),MAP!$B$12),IFERROR(INDEX(LISTS!$D$2:$D$12,MATCH(INDEX(SchedZone,MATCH($A9,SchedSeq,0),MAP!$B$12),LISTS!$C$2:$C$12,0)),"⚠ "&INDEX(SchedZone,MATCH($A9,SchedSeq,0),MAP!$B$12))))} -> DET | G9: {=IF($B9="","",IF(INDEX(SchedZone,MATCH($A9,SchedSeq,0),MAP!$B$14)="Neutral","Y",""))} | H9: {=IF($B9="","",INDEX(SchedZone,MATCH($A9,SchedSeq,0),MAP!$B$17))} -> dome | I9: =IF(OR($B9="",$C9<>CurrentWeek),"",COUNTIF($C$5:$C9,CurrentWeek)) -> 5 | J9: {=IF($B9="","",IFERROR(INDEX(RatEff,MATCH($E9,RatTeams,0)),"⚠ TEAM NOT FOUND"))} -> -0.94 | K9: {=IF($B9="","",IFERROR(INDEX(RatEff,MATCH($F9,RatTeams,0)),"⚠ TEAM NOT FOUND"))} -> 0.86 | L9: =IF(OR($B9="",NOT(ISNUMBER($J9)),NOT(ISNUMBER($K9))),"",$K9-$J9) -> 1.8 | M9: {=IF($B9="","",IF($G9="Y",NeutralHFA,IFERROR(INDEX(HFAexcVal,MATCH($F9,HFAexcTeam,0)),HFA_Base)))} -> 1.6 | N9: {=IF($B9="","",IFERROR(INDEX(QBSpreadEff,MATCH($F9,QBTeams,0)),0)-IFERROR(INDEX(QBSpreadEff,MATCH($E9,QBTeams,0)),0))} -> 0 | O9: {=IF($B9="","",IFERROR(MEDIAN(-RestCapPts,RestCapPts,RestPerDay*(INDEX(SchedZone,MATCH($A9,SchedSeq,0),MAP!$B$16)-INDEX(SchedZone,MATCH($A9,SchedSeq,0),MAP!$B$15))),0))} -> 0 | P9: =IF($B9="","",SUMIFS(AdjSpread,AdjGameID,$B9,AdjTeam,$F9,AdjActive,1)-SUMIFS(AdjSpread,AdjGameID,$B9,AdjTeam,$E9,AdjActive,1)) -> 0 | Q9: =IF($L9="","",ROUND($L9+$M9+$N9+$O9+$P9,2)) -> 3.4 | S9: =IF(AND($R9="",$Q9=""),"",IF($R9<>"",$R9,$Q9)) -> 3.4 | T9: =IF($S9="","",IF(ABS($S9)<0.05,"PK",IF($S9>0,$F9&" "&TEXT(-$S9,"+0.0;-0.0"),$E9&" "&TEXT($S9,"+0.0;-0.0")))) -> DET -3.4 | U9: {=IF($B9="","",IFERROR(INDEX(MktHomeSpread,MATCH($B9,MktGameID,0)),""))} | V9: =IF(OR($S9="",$U9=""),"",ROUND($S9+$U9,2)) | W9: =IF($V9="","",ABS($V9)) | X9: =IF($V9="","",IF($V9>0,$F9&" "&TEXT($U9,"+0.0;-0.0;""PK"""),$E9&" "&TEXT(-$U9,"+0.0;-0.0;""PK"""))) | Y9: {=IF($B9="","",IF((IF(AND(IFERROR(INDEX(RatGP,MATCH($E9,RatTeams,0)),0)>=MinGamesTrust,IFERROR(INDEX(RatGP,MATCH($F9,RatTeams,0)),0)>=MinGamesTrust),1,0)+IF($AP9="READY",1,0)+IF(AND(IFERROR(INDEX(RatMode,MATCH($E9,RatTeams,0)),"")="ENHANCED",IFERROR(INDEX(RatMode,MATCH($F9,RatTeams,0)),"")="ENHANCED"),1,0)+IF($AO9="",1,0)+IF(IFERROR(INDEX(MktStale,MATCH($B9,MktGameID,0)),"")<>"STALE",1,0))>=5,"High",IF((IF(AND(IFERROR(INDEX(RatGP,MATCH($E9,RatTeams,0)),0)>=MinGamesTrust,IFERROR(INDEX(RatGP,MATCH($F9,RatTeams,0)),0)>=MinGamesTrust),1,0)+IF($AP9="READY",1,0)+IF(AND(IFERROR(INDEX(RatMode,MATCH($E9,RatTeams,0)),"")="ENHANCED",IFERROR(INDEX(RatMode,MATCH($F9,RatTeams,0)),"")="ENHANCED"),1,0)+IF($AO9="",1,0)+IF(IFERROR(INDEX(MktStale,MATCH($B9,MktGameID,0)),"")<>"STALE",1,0))>=4,"Medium","Low")))} -> Low | Z9: =IF(OR($B9="",$V9=""),"",IF(LEFT($AP9,7)="BLOCKED","",IF(AND($W9>=BetATS,$Y9<>"Low"),IF(AND(EnableBetLabels="Y",$Y9="High",$AP9="READY",ABS(IF($P9="",0,$P9))<=AdjCap),"BET","STRONG INVESTIGATE"),IF($W9>=InvATS,"INVESTIGATE",IF(AND($W9>=LeanATS,$Y9<>"Low"),"LEAN",""))))) | AA9: {=IF($B9="","",IFERROR(ROUND(((1-TotRegress)*0.5*(INDEX(CalcOffPl,MATCH($E9,CalcTeams,0))+INDEX(CalcDefPl,MATCH($F9,CalcTeams,0)))+TotRegress*LeaguePlays)*(INDEX(CalcOffAdj,MATCH($E9,CalcTeams,0))+INDEX(CalcDefAdj,MATCH($F9,CalcTeams,0))-LeaguePPP)+DstPts,2),""))} -> 0 | AB9: {=IF($B9="","",IFERROR(ROUND(((1-TotRegress)*0.5*(INDEX(CalcOffPl,MATCH($F9,CalcTeams,0))+INDEX(CalcDefPl,MATCH($E9,CalcTeams,0)))+TotRegress*LeaguePlays)*(INDEX(CalcOffAdj,MATCH($F9,CalcTeams,0))+INDEX(CalcDefAdj,MATCH($E9,CalcTeams,0))-LeaguePPP)+DstPts,2),""))} -> 0 | AC9: {=IF($B9="","",IFERROR(INDEX(QBTotEff,MATCH($F9,QBTeams,0)),0)+IFERROR(INDEX(QBTotEff,MATCH($E9,QBTeams,0)),0))} -> 0 | AD9: =IF($B9="","",SUMIFS(AdjTot,AdjGameID,$B9,AdjActive,1)) -> 0 | AE9: =IF(OR($AA9="",$AB9=""),"",ROUND($AA9+$AB9+$AC9+$AD9,2)) -> 0 | AG9: =IF(AND($AF9="",$AE9=""),"",IF($AF9<>"",$AF9,$AE9)) -> 0 | AH9: {=IF($B9="","",IFERROR(INDEX(MktTotal,MATCH($B9,MktGameID,0)),""))} | AI9: =IF(OR($AG9="",$AH9=""),"",ROUND($AG9-$AH9,2)) | AJ9: =IF($AI9="","",ABS($AI9)) | AK9: =IF($AI9="","",IF($AI9>0.05,"OVER",IF($AI9<-0.05,"UNDER","—"))) | AL9: {=IF($B9="","",IF((IF(AND(IFERROR(INDEX(RatGP,MATCH($E9,RatTeams,0)),0)>=MinGamesTrust,IFERROR(INDEX(RatGP,MATCH($F9,RatTeams,0)),0)>=MinGamesTrust),1,0)+IF($AP9="READY",1,0)+IF($AO9="",1,0)+IF(IFERROR(INDEX(MktStale,MATCH($B9,MktGameID,0)),"")<>"STALE",1,0)+IF(ABS(IF($AD9="",0,$AD9))<=AdjCap,1,0))>=5,"High",IF((IF(AND(IFERROR(INDEX(RatGP,MATCH($E9,RatTeams,0)),0)>=MinGamesTrust,IFERROR(INDEX(RatGP,MATCH($F9,RatTeams,0)),0)>=MinGamesTrust),1,0)+IF($AP9="READY",1,0)+IF($AO9="",1,0)+IF(IFERROR(INDEX(MktStale,MATCH($B9,MktGameID,0)),"")<>"STALE",1,0)+IF(ABS(IF($AD9="",0,$AD9))<=AdjCap,1,0))>=4,"Medium","Low")))} -> Medium | AM9: =IF(OR($B9="",$AI9=""),"",IF(LEFT($AP9,7)="BLOCKED","",IF(AND($AJ9>=BetTot,$AL9<>"Low"),IF(AND(EnableBetLabels="Y",$AL9="High",$AP9="READY"),"BET ","STRONG INVESTIGATE ")&$AK9,IF($AJ9>=InvTot,"INVESTIGATE "&$AK9,IF(AND($AJ9>=LeanTot,$AL9<>"Low"),"LEAN "&$AK9,""))))) | AN9: =IF($AG9="","","BET OVER at ≤ "&TEXT($AG9-BetTot,"0.0")&" | BET UNDER at ≥ "&TEXT($AG9+BetTot,"0.0")) -> BET OVER at ≤ -3.0 | BET UNDER at ≥ 3.0 | AO9: {=IF($B9="","",IF(OR(IFERROR(INDEX(QBFlag,MATCH($F9,QBTeams,0)),1)=1,IFERROR(INDEX(QBFlag,MATCH($E9,QBTeams,0)),1)=1),"QB UNCERTAIN",""))} | AP9: {=IF($B9="","",IFERROR(INDEX(DQStatus,MATCH($B9,DQGameID,0)),"BLOCKED — DQ ROW NOT FOUND"))} -> READY | AQ9: {=IF($B9="","",IF(LEFT($AP9,7)="BLOCKED",IF($AP9="BLOCKED","BLOCKED — see DATA QUALITY",$AP9),IF(AND($U9="",$AH9=""),"PENDING BOTH",IF($U9="","PENDING SPREAD",IF($AH9="","PENDING TOTAL",IF(IFERROR(INDEX(MktStale,MATCH($B9,MktGameID,0)),"")="STALE","STALE LINE",IF($AO9<>"",$AO9,IF(OR(NOT(ISNUMBER($J9)),NOT(ISNUMBER($K9))),"DATA INCOMPLETE","READY"))))))))} -> PENDING BOTH | AR9: =IF(OR($R9<>"",$AF9<>""),"OVERRIDE","") | AS9: {=IF(OR($B9="",$C9<>CurrentWeek),"",ROUND(25*MIN(1,IF($W9="",0,$W9)/5)+20*IF($AP9="READY",1,0)+20*IF($AO9="",1,0)+15*IF(IFERROR(INDEX(MktStale,MATCH($B9,MktGameID,0)),"x")="OK",1,0)+10*MAX(0,1-ABS(IF($P9="",0,$P9))/AdjCap)+10*IF(AND($Z9<>"",$AM9<>""),1,0),0))} -> 50 | AT9: =IF($AS9="","",RANK($AS9,$AS$5:$AS$304,0)) -> 1
A10: 6 | B10: {=IFERROR(INDEX(SchedZone,MATCH($A10,SchedSeq,0),MAP!$B$6),"")} -> 2026_01_BUF_HOU | C10: {=IF($B10="","",INDEX(SchedZone,MATCH($A10,SchedSeq,0),MAP!$B$4))} -> 1 | D10: {=IF($B10="","",INDEX(SchedZone,MATCH($A10,SchedSeq,0),MAP!$B$7))} -> 46278 | E10: {=IF($B10="","",IF(COUNTIF(Teams,INDEX(SchedZone,MATCH($A10,SchedSeq,0),MAP!$B$10))>0,INDEX(SchedZone,MATCH($A10,SchedSeq,0),MAP!$B$10),IFERROR(INDEX(LISTS!$D$2:$D$12,MATCH(INDEX(SchedZone,MATCH($A10,SchedSeq,0),MAP!$B$10),LISTS!$C$2:$C$12,0)),"⚠ "&INDEX(SchedZone,MATCH($A10,SchedSeq,0),MAP!$B$10))))} -> BUF | F10: {=IF($B10="","",IF(COUNTIF(Teams,INDEX(SchedZone,MATCH($A10,SchedSeq,0),MAP!$B$12))>0,INDEX(SchedZone,MATCH($A10,SchedSeq,0),MAP!$B$12),IFERROR(INDEX(LISTS!$D$2:$D$12,MATCH(INDEX(SchedZone,MATCH($A10,SchedSeq,0),MAP!$B$12),LISTS!$C$2:$C$12,0)),"⚠ "&INDEX(SchedZone,MATCH($A10,SchedSeq,0),MAP!$B$12))))} -> HOU | G10: {=IF($B10="","",IF(INDEX(SchedZone,MATCH($A10,SchedSeq,0),MAP!$B$14)="Neutral","Y",""))} | H10: {=IF($B10="","",INDEX(SchedZone,MATCH($A10,SchedSeq,0),MAP!$B$17))} | I10: =IF(OR($B10="",$C10<>CurrentWeek),"",COUNTIF($C$5:$C10,CurrentWeek)) -> 6 | J10: {=IF($B10="","",IFERROR(INDEX(RatEff,MATCH($E10,RatTeams,0)),"⚠ TEAM NOT FOUND"))} -> 1.75 | K10: {=IF($B10="","",IFERROR(INDEX(RatEff,MATCH($F10,RatTeams,0)),"⚠ TEAM NOT FOUND"))} -> 2.71 | L10: =IF(OR($B10="",NOT(ISNUMBER($J10)),NOT(ISNUMBER($K10))),"",$K10-$J10) -> 0.96 | M10: {=IF($B10="","",IF($G10="Y",NeutralHFA,IFERROR(INDEX(HFAexcVal,MATCH($F10,HFAexcTeam,0)),HFA_Base)))} -> 1.6 | N10: {=IF($B10="","",IFERROR(INDEX(QBSpreadEff,MATCH($F10,QBTeams,0)),0)-IFERROR(INDEX(QBSpreadEff,MATCH($E10,QBTeams,0)),0))} -> 0 | O10: {=IF($B10="","",IFERROR(MEDIAN(-RestCapPts,RestCapPts,RestPerDay*(INDEX(SchedZone,MATCH($A10,SchedSeq,0),MAP!$B$16)-INDEX(SchedZone,MATCH($A10,SchedSeq,0),MAP!$B$15))),0))} -> 0 | P10: =IF($B10="","",SUMIFS(AdjSpread,AdjGameID,$B10,AdjTeam,$F10,AdjActive,1)-SUMIFS(AdjSpread,AdjGameID,$B10,AdjTeam,$E10,AdjActive,1)) -> 0 | Q10: =IF($L10="","",ROUND($L10+$M10+$N10+$O10+$P10,2)) -> 2.56 | S10: =IF(AND($R10="",$Q10=""),"",IF($R10<>"",$R10,$Q10)) -> 2.56 | T10: =IF($S10="","",IF(ABS($S10)<0.05,"PK",IF($S10>0,$F10&" "&TEXT(-$S10,"+0.0;-0.0"),$E10&" "&TEXT($S10,"+0.0;-0.0")))) -> HOU -2.6 | U10: {=IF($B10="","",IFERROR(INDEX(MktHomeSpread,MATCH($B10,MktGameID,0)),""))} | V10: =IF(OR($S10="",$U10=""),"",ROUND($S10+$U10,2)) | W10: =IF($V10="","",ABS($V10)) | X10: =IF($V10="","",IF($V10>0,$F10&" "&TEXT($U10,"+0.0;-0.0;""PK"""),$E10&" "&TEXT(-$U10,"+0.0;-0.0;""PK"""))) | Y10: {=IF($B10="","",IF((IF(AND(IFERROR(INDEX(RatGP,MATCH($E10,RatTeams,0)),0)>=MinGamesTrust,IFERROR(INDEX(RatGP,MATCH($F10,RatTeams,0)),0)>=MinGamesTrust),1,0)+IF($AP10="READY",1,0)+IF(AND(IFERROR(INDEX(RatMode,MATCH($E10,RatTeams,0)),"")="ENHANCED",IFERROR(INDEX(RatMode,MATCH($F10,RatTeams,0)),"")="ENHANCED"),1,0)+IF($AO10="",1,0)+IF(IFERROR(INDEX(MktStale,MATCH($B10,MktGameID,0)),"")<>"STALE",1,0))>=5,"High",IF((IF(AND(IFERROR(INDEX(RatGP,MATCH($E10,RatTeams,0)),0)>=MinGamesTrust,IFERROR(INDEX(RatGP,MATCH($F10,RatTeams,0)),0)>=MinGamesTrust),1,0)+IF($AP10="READY",1,0)+IF(AND(IFERROR(INDEX(RatMode,MATCH($E10,RatTeams,0)),"")="ENHANCED",IFERROR(INDEX(RatMode,MATCH($F10,RatTeams,0)),"")="ENHANCED"),1,0)+IF($AO10="",1,0)+IF(IFERROR(INDEX(MktStale,MATCH($B10,MktGameID,0)),"")<>"STALE",1,0))>=4,"Medium","Low")))} -> Low | Z10: =IF(OR($B10="",$V10=""),"",IF(LEFT($AP10,7)="BLOCKED","",IF(AND($W10>=BetATS,$Y10<>"Low"),IF(AND(EnableBetLabels="Y",$Y10="High",$AP10="READY",ABS(IF($P10="",0,$P10))<=AdjCap),"BET","STRONG INVESTIGATE"),IF($W10>=InvATS,"INVESTIGATE",IF(AND($W10>=LeanATS,$Y10<>"Low"),"LEAN",""))))) | AA10: {=IF($B10="","",IFERROR(ROUND(((1-TotRegress)*0.5*(INDEX(CalcOffPl,MATCH($E10,CalcTeams,0))+INDEX(CalcDefPl,MATCH($F10,CalcTeams,0)))+TotRegress*LeaguePlays)*(INDEX(CalcOffAdj,MATCH($E10,CalcTeams,0))+INDEX(CalcDefAdj,MATCH($F10,CalcTeams,0))-LeaguePPP)+DstPts,2),""))} -> 0 | AB10: {=IF($B10="","",IFERROR(ROUND(((1-TotRegress)*0.5*(INDEX(CalcOffPl,MATCH($F10,CalcTeams,0))+INDEX(CalcDefPl,MATCH($E10,CalcTeams,0)))+TotRegress*LeaguePlays)*(INDEX(CalcOffAdj,MATCH($F10,CalcTeams,0))+INDEX(CalcDefAdj,MATCH($E10,CalcTeams,0))-LeaguePPP)+DstPts,2),""))} -> 0 | AC10: {=IF($B10="","",IFERROR(INDEX(QBTotEff,MATCH($F10,QBTeams,0)),0)+IFERROR(INDEX(QBTotEff,MATCH($E10,QBTeams,0)),0))} -> 0 | AD10: =IF($B10="","",SUMIFS(AdjTot,AdjGameID,$B10,AdjActive,1)) -> 0 | AE10: =IF(OR($AA10="",$AB10=""),"",ROUND($AA10+$AB10+$AC10+$AD10,2)) -> 0 | AG10: =IF(AND($AF10="",$AE10=""),"",IF($AF10<>"",$AF10,$AE10)) -> 0 | AH10: {=IF($B10="","",IFERROR(INDEX(MktTotal,MATCH($B10,MktGameID,0)),""))} | AI10: =IF(OR($AG10="",$AH10=""),"",ROUND($AG10-$AH10,2)) | AJ10: =IF($AI10="","",ABS($AI10)) | AK10: =IF($AI10="","",IF($AI10>0.05,"OVER",IF($AI10<-0.05,"UNDER","—"))) | AL10: {=IF($B10="","",IF((IF(AND(IFERROR(INDEX(RatGP,MATCH($E10,RatTeams,0)),0)>=MinGamesTrust,IFERROR(INDEX(RatGP,MATCH($F10,RatTeams,0)),0)>=MinGamesTrust),1,0)+IF($AP10="READY",1,0)+IF($AO10="",1,0)+IF(IFERROR(INDEX(MktStale,MATCH($B10,MktGameID,0)),"")<>"STALE",1,0)+IF(ABS(IF($AD10="",0,$AD10))<=AdjCap,1,0))>=5,"High",IF((IF(AND(IFERROR(INDEX(RatGP,MATCH($E10,RatTeams,0)),0)>=MinGamesTrust,IFERROR(INDEX(RatGP,MATCH($F10,RatTeams,0)),0)>=MinGamesTrust),1,0)+IF($AP10="READY",1,0)+IF($AO10="",1,0)+IF(IFERROR(INDEX(MktStale,MATCH($B10,MktGameID,0)),"")<>"STALE",1,0)+IF(ABS(IF($AD10="",0,$AD10))<=AdjCap,1,0))>=4,"Medium","Low")))} -> Medium | AM10: =IF(OR($B10="",$AI10=""),"",IF(LEFT($AP10,7)="BLOCKED","",IF(AND($AJ10>=BetTot,$AL10<>"Low"),IF(AND(EnableBetLabels="Y",$AL10="High",$AP10="READY"),"BET ","STRONG INVESTIGATE ")&$AK10,IF($AJ10>=InvTot,"INVESTIGATE "&$AK10,IF(AND($AJ10>=LeanTot,$AL10<>"Low"),"LEAN "&$AK10,""))))) | AN10: =IF($AG10="","","BET OVER at ≤ "&TEXT($AG10-BetTot,"0.0")&" | BET UNDER at ≥ "&TEXT($AG10+BetTot,"0.0")) -> BET OVER at ≤ -3.0 | BET UNDER at ≥ 3.0 | AO10: {=IF($B10="","",IF(OR(IFERROR(INDEX(QBFlag,MATCH($F10,QBTeams,0)),1)=1,IFERROR(INDEX(QBFlag,MATCH($E10,QBTeams,0)),1)=1),"QB UNCERTAIN",""))} | AP10: {=IF($B10="","",IFERROR(INDEX(DQStatus,MATCH($B10,DQGameID,0)),"BLOCKED — DQ ROW NOT FOUND"))} -> READY | AQ10: {=IF($B10="","",IF(LEFT($AP10,7)="BLOCKED",IF($AP10="BLOCKED","BLOCKED — see DATA QUALITY",$AP10),IF(AND($U10="",$AH10=""),"PENDING BOTH",IF($U10="","PENDING SPREAD",IF($AH10="","PENDING TOTAL",IF(IFERROR(INDEX(MktStale,MATCH($B10,MktGameID,0)),"")="STALE","STALE LINE",IF($AO10<>"",$AO10,IF(OR(NOT(ISNUMBER($J10)),NOT(ISNUMBER($K10))),"DATA INCOMPLETE","READY"))))))))} -> PENDING BOTH | AR10: =IF(OR($R10<>"",$AF10<>""),"OVERRIDE","") | AS10: {=IF(OR($B10="",$C10<>CurrentWeek),"",ROUND(25*MIN(1,IF($W10="",0,$W10)/5)+20*IF($AP10="READY",1,0)+20*IF($AO10="",1,0)+15*IF(IFERROR(INDEX(MktStale,MATCH($B10,MktGameID,0)),"x")="OK",1,0)+10*MAX(0,1-ABS(IF($P10="",0,$P10))/AdjCap)+10*IF(AND($Z10<>"",$AM10<>""),1,0),0))} -> 50 | AT10: =IF($AS10="","",RANK($AS10,$AS$5:$AS$304,0)) -> 1
A11: 7 | B11: {=IFERROR(INDEX(SchedZone,MATCH($A11,SchedSeq,0),MAP!$B$6),"")} -> 2026_01_BAL_IND | C11: {=IF($B11="","",INDEX(SchedZone,MATCH($A11,SchedSeq,0),MAP!$B$4))} -> 1 | D11: {=IF($B11="","",INDEX(SchedZone,MATCH($A11,SchedSeq,0),MAP!$B$7))} -> 46278 | E11: {=IF($B11="","",IF(COUNTIF(Teams,INDEX(SchedZone,MATCH($A11,SchedSeq,0),MAP!$B$10))>0,INDEX(SchedZone,MATCH($A11,SchedSeq,0),MAP!$B$10),IFERROR(INDEX(LISTS!$D$2:$D$12,MATCH(INDEX(SchedZone,MATCH($A11,SchedSeq,0),MAP!$B$10),LISTS!$C$2:$C$12,0)),"⚠ "&INDEX(SchedZone,MATCH($A11,SchedSeq,0),MAP!$B$10))))} -> BAL | F11: {=IF($B11="","",IF(COUNTIF(Teams,INDEX(SchedZone,MATCH($A11,SchedSeq,0),MAP!$B$12))>0,INDEX(SchedZone,MATCH($A11,SchedSeq,0),MAP!$B$12),IFERROR(INDEX(LISTS!$D$2:$D$12,MATCH(INDEX(SchedZone,MATCH($A11,SchedSeq,0),MAP!$B$12),LISTS!$C$2:$C$12,0)),"⚠ "&INDEX(SchedZone,MATCH($A11,SchedSeq,0),MAP!$B$12))))} -> IND | G11: {=IF($B11="","",IF(INDEX(SchedZone,MATCH($A11,SchedSeq,0),MAP!$B$14)="Neutral","Y",""))} | H11: {=IF($B11="","",INDEX(SchedZone,MATCH($A11,SchedSeq,0),MAP!$B$17))} | I11: =IF(OR($B11="",$C11<>CurrentWeek),"",COUNTIF($C$5:$C11,CurrentWeek)) -> 7 | J11: {=IF($B11="","",IFERROR(INDEX(RatEff,MATCH($E11,RatTeams,0)),"⚠ TEAM NOT FOUND"))} -> 0.92 | K11: {=IF($B11="","",IFERROR(INDEX(RatEff,MATCH($F11,RatTeams,0)),"⚠ TEAM NOT FOUND"))} -> 0.82 | L11: =IF(OR($B11="",NOT(ISNUMBER($J11)),NOT(ISNUMBER($K11))),"",$K11-$J11) -> -0.1 | M11: {=IF($B11="","",IF($G11="Y",NeutralHFA,IFERROR(INDEX(HFAexcVal,MATCH($F11,HFAexcTeam,0)),HFA_Base)))} -> 1.6 | N11: {=IF($B11="","",IFERROR(INDEX(QBSpreadEff,MATCH($F11,QBTeams,0)),0)-IFERROR(INDEX(QBSpreadEff,MATCH($E11,QBTeams,0)),0))} -> 0 | O11: {=IF($B11="","",IFERROR(MEDIAN(-RestCapPts,RestCapPts,RestPerDay*(INDEX(SchedZone,MATCH($A11,SchedSeq,0),MAP!$B$16)-INDEX(SchedZone,MATCH($A11,SchedSeq,0),MAP!$B$15))),0))} -> 0 | P11: =IF($B11="","",SUMIFS(AdjSpread,AdjGameID,$B11,AdjTeam,$F11,AdjActive,1)-SUMIFS(AdjSpread,AdjGameID,$B11,AdjTeam,$E11,AdjActive,1)) -> 0 | Q11: =IF($L11="","",ROUND($L11+$M11+$N11+$O11+$P11,2)) -> 1.5 | S11: =IF(AND($R11="",$Q11=""),"",IF($R11<>"",$R11,$Q11)) -> 1.5 | T11: =IF($S11="","",IF(ABS($S11)<0.05,"PK",IF($S11>0,$F11&" "&TEXT(-$S11,"+0.0;-0.0"),$E11&" "&TEXT($S11,"+0.0;-0.0")))) -> IND -1.5 | U11: {=IF($B11="","",IFERROR(INDEX(MktHomeSpread,MATCH($B11,MktGameID,0)),""))} | V11: =IF(OR($S11="",$U11=""),"",ROUND($S11+$U11,2)) | W11: =IF($V11="","",ABS($V11)) | X11: =IF($V11="","",IF($V11>0,$F11&" "&TEXT($U11,"+0.0;-0.0;""PK"""),$E11&" "&TEXT(-$U11,"+0.0;-0.0;""PK"""))) | Y11: {=IF($B11="","",IF((IF(AND(IFERROR(INDEX(RatGP,MATCH($E11,RatTeams,0)),0)>=MinGamesTrust,IFERROR(INDEX(RatGP,MATCH($F11,RatTeams,0)),0)>=MinGamesTrust),1,0)+IF($AP11="READY",1,0)+IF(AND(IFERROR(INDEX(RatMode,MATCH($E11,RatTeams,0)),"")="ENHANCED",IFERROR(INDEX(RatMode,MATCH($F11,RatTeams,0)),"")="ENHANCED"),1,0)+IF($AO11="",1,0)+IF(IFERROR(INDEX(MktStale,MATCH($B11,MktGameID,0)),"")<>"STALE",1,0))>=5,"High",IF((IF(AND(IFERROR(INDEX(RatGP,MATCH($E11,RatTeams,0)),0)>=MinGamesTrust,IFERROR(INDEX(RatGP,MATCH($F11,RatTeams,0)),0)>=MinGamesTrust),1,0)+IF($AP11="READY",1,0)+IF(AND(IFERROR(INDEX(RatMode,MATCH($E11,RatTeams,0)),"")="ENHANCED",IFERROR(INDEX(RatMode,MATCH($F11,RatTeams,0)),"")="ENHANCED"),1,0)+IF($AO11="",1,0)+IF(IFERROR(INDEX(MktStale,MATCH($B11,MktGameID,0)),"")<>"STALE",1,0))>=4,"Medium","Low")))} -> Low | Z11: =IF(OR($B11="",$V11=""),"",IF(LEFT($AP11,7)="BLOCKED","",IF(AND($W11>=BetATS,$Y11<>"Low"),IF(AND(EnableBetLabels="Y",$Y11="High",$AP11="READY",ABS(IF($P11="",0,$P11))<=AdjCap),"BET","STRONG INVESTIGATE"),IF($W11>=InvATS,"INVESTIGATE",IF(AND($W11>=LeanATS,$Y11<>"Low"),"LEAN",""))))) | AA11: {=IF($B11="","",IFERROR(ROUND(((1-TotRegress)*0.5*(INDEX(CalcOffPl,MATCH($E11,CalcTeams,0))+INDEX(CalcDefPl,MATCH($F11,CalcTeams,0)))+TotRegress*LeaguePlays)*(INDEX(CalcOffAdj,MATCH($E11,CalcTeams,0))+INDEX(CalcDefAdj,MATCH($F11,CalcTeams,0))-LeaguePPP)+DstPts,2),""))} -> 0 | AB11: {=IF($B11="","",IFERROR(ROUND(((1-TotRegress)*0.5*(INDEX(CalcOffPl,MATCH($F11,CalcTeams,0))+INDEX(CalcDefPl,MATCH($E11,CalcTeams,0)))+TotRegress*LeaguePlays)*(INDEX(CalcOffAdj,MATCH($F11,CalcTeams,0))+INDEX(CalcDefAdj,MATCH($E11,CalcTeams,0))-LeaguePPP)+DstPts,2),""))} -> 0 | AC11: {=IF($B11="","",IFERROR(INDEX(QBTotEff,MATCH($F11,QBTeams,0)),0)+IFERROR(INDEX(QBTotEff,MATCH($E11,QBTeams,0)),0))} -> 0 | AD11: =IF($B11="","",SUMIFS(AdjTot,AdjGameID,$B11,AdjActive,1)) -> 0 | AE11: =IF(OR($AA11="",$AB11=""),"",ROUND($AA11+$AB11+$AC11+$AD11,2)) -> 0 | AG11: =IF(AND($AF11="",$AE11=""),"",IF($AF11<>"",$AF11,$AE11)) -> 0 | AH11: {=IF($B11="","",IFERROR(INDEX(MktTotal,MATCH($B11,MktGameID,0)),""))} | AI11: =IF(OR($AG11="",$AH11=""),"",ROUND($AG11-$AH11,2)) | AJ11: =IF($AI11="","",ABS($AI11)) | AK11: =IF($AI11="","",IF($AI11>0.05,"OVER",IF($AI11<-0.05,"UNDER","—"))) | AL11: {=IF($B11="","",IF((IF(AND(IFERROR(INDEX(RatGP,MATCH($E11,RatTeams,0)),0)>=MinGamesTrust,IFERROR(INDEX(RatGP,MATCH($F11,RatTeams,0)),0)>=MinGamesTrust),1,0)+IF($AP11="READY",1,0)+IF($AO11="",1,0)+IF(IFERROR(INDEX(MktStale,MATCH($B11,MktGameID,0)),"")<>"STALE",1,0)+IF(ABS(IF($AD11="",0,$AD11))<=AdjCap,1,0))>=5,"High",IF((IF(AND(IFERROR(INDEX(RatGP,MATCH($E11,RatTeams,0)),0)>=MinGamesTrust,IFERROR(INDEX(RatGP,MATCH($F11,RatTeams,0)),0)>=MinGamesTrust),1,0)+IF($AP11="READY",1,0)+IF($AO11="",1,0)+IF(IFERROR(INDEX(MktStale,MATCH($B11,MktGameID,0)),"")<>"STALE",1,0)+IF(ABS(IF($AD11="",0,$AD11))<=AdjCap,1,0))>=4,"Medium","Low")))} -> Medium | AM11: =IF(OR($B11="",$AI11=""),"",IF(LEFT($AP11,7)="BLOCKED","",IF(AND($AJ11>=BetTot,$AL11<>"Low"),IF(AND(EnableBetLabels="Y",$AL11="High",$AP11="READY"),"BET ","STRONG INVESTIGATE ")&$AK11,IF($AJ11>=InvTot,"INVESTIGATE "&$AK11,IF(AND($AJ11>=LeanTot,$AL11<>"Low"),"LEAN "&$AK11,""))))) | AN11: =IF($AG11="","","BET OVER at ≤ "&TEXT($AG11-BetTot,"0.0")&" | BET UNDER at ≥ "&TEXT($AG11+BetTot,"0.0")) -> BET OVER at ≤ -3.0 | BET UNDER at ≥ 3.0 | AO11: {=IF($B11="","",IF(OR(IFERROR(INDEX(QBFlag,MATCH($F11,QBTeams,0)),1)=1,IFERROR(INDEX(QBFlag,MATCH($E11,QBTeams,0)),1)=1),"QB UNCERTAIN",""))} | AP11: {=IF($B11="","",IFERROR(INDEX(DQStatus,MATCH($B11,DQGameID,0)),"BLOCKED — DQ ROW NOT FOUND"))} -> READY | AQ11: {=IF($B11="","",IF(LEFT($AP11,7)="BLOCKED",IF($AP11="BLOCKED","BLOCKED — see DATA QUALITY",$AP11),IF(AND($U11="",$AH11=""),"PENDING BOTH",IF($U11="","PENDING SPREAD",IF($AH11="","PENDING TOTAL",IF(IFERROR(INDEX(MktStale,MATCH($B11,MktGameID,0)),"")="STALE","STALE LINE",IF($AO11<>"",$AO11,IF(OR(NOT(ISNUMBER($J11)),NOT(ISNUMBER($K11))),"DATA INCOMPLETE","READY"))))))))} -> PENDING BOTH | AR11: =IF(OR($R11<>"",$AF11<>""),"OVERRIDE","") | AS11: {=IF(OR($B11="",$C11<>CurrentWeek),"",ROUND(25*MIN(1,IF($W11="",0,$W11)/5)+20*IF($AP11="READY",1,0)+20*IF($AO11="",1,0)+15*IF(IFERROR(INDEX(MktStale,MATCH($B11,MktGameID,0)),"x")="OK",1,0)+10*MAX(0,1-ABS(IF($P11="",0,$P11))/AdjCap)+10*IF(AND($Z11<>"",$AM11<>""),1,0),0))} -> 50 | AT11: =IF($AS11="","",RANK($AS11,$AS$5:$AS$304,0)) -> 1
A12: 8 | B12: {=IFERROR(INDEX(SchedZone,MATCH($A12,SchedSeq,0),MAP!$B$6),"")} -> 2026_01_CLE_JAX | C12: {=IF($B12="","",INDEX(SchedZone,MATCH($A12,SchedSeq,0),MAP!$B$4))} -> 1 | D12: {=IF($B12="","",INDEX(SchedZone,MATCH($A12,SchedSeq,0),MAP!$B$7))} -> 46278 | E12: {=IF($B12="","",IF(COUNTIF(Teams,INDEX(SchedZone,MATCH($A12,SchedSeq,0),MAP!$B$10))>0,INDEX(SchedZone,MATCH($A12,SchedSeq,0),MAP!$B$10),IFERROR(INDEX(LISTS!$D$2:$D$12,MATCH(INDEX(SchedZone,MATCH($A12,SchedSeq,0),MAP!$B$10),LISTS!$C$2:$C$12,0)),"⚠ "&INDEX(SchedZone,MATCH($A12,SchedSeq,0),MAP!$B$10))))} -> CLE | F12: {=IF($B12="","",IF(COUNTIF(Teams,INDEX(SchedZone,MATCH($A12,SchedSeq,0),MAP!$B$12))>0,INDEX(SchedZone,MATCH($A12,SchedSeq,0),MAP!$B$12),IFERROR(INDEX(LISTS!$D$2:$D$12,MATCH(INDEX(SchedZone,MATCH($A12,SchedSeq,0),MAP!$B$12),LISTS!$C$2:$C$12,0)),"⚠ "&INDEX(SchedZone,MATCH($A12,SchedSeq,0),MAP!$B$12))))} -> JAX | G12: {=IF($B12="","",IF(INDEX(SchedZone,MATCH($A12,SchedSeq,0),MAP!$B$14)="Neutral","Y",""))} | H12: {=IF($B12="","",INDEX(SchedZone,MATCH($A12,SchedSeq,0),MAP!$B$17))} -> outdoors | I12: =IF(OR($B12="",$C12<>CurrentWeek),"",COUNTIF($C$5:$C12,CurrentWeek)) -> 8 | J12: {=IF($B12="","",IFERROR(INDEX(RatEff,MATCH($E12,RatTeams,0)),"⚠ TEAM NOT FOUND"))} -> -2.6 | K12: {=IF($B12="","",IFERROR(INDEX(RatEff,MATCH($F12,RatTeams,0)),"⚠ TEAM NOT FOUND"))} -> 3.22 | L12: =IF(OR($B12="",NOT(ISNUMBER($J12)),NOT(ISNUMBER($K12))),"",$K12-$J12) -> 5.82 | M12: {=IF($B12="","",IF($G12="Y",NeutralHFA,IFERROR(INDEX(HFAexcVal,MATCH($F12,HFAexcTeam,0)),HFA_Base)))} -> 1.6 | N12: {=IF($B12="","",IFERROR(INDEX(QBSpreadEff,MATCH($F12,QBTeams,0)),0)-IFERROR(INDEX(QBSpreadEff,MATCH($E12,QBTeams,0)),0))} -> 0 | O12: {=IF($B12="","",IFERROR(MEDIAN(-RestCapPts,RestCapPts,RestPerDay*(INDEX(SchedZone,MATCH($A12,SchedSeq,0),MAP!$B$16)-INDEX(SchedZone,MATCH($A12,SchedSeq,0),MAP!$B$15))),0))} -> 0 | P12: =IF($B12="","",SUMIFS(AdjSpread,AdjGameID,$B12,AdjTeam,$F12,AdjActive,1)-SUMIFS(AdjSpread,AdjGameID,$B12,AdjTeam,$E12,AdjActive,1)) -> 0 | Q12: =IF($L12="","",ROUND($L12+$M12+$N12+$O12+$P12,2)) -> 7.42 | S12: =IF(AND($R12="",$Q12=""),"",IF($R12<>"",$R12,$Q12)) -> 7.42 | T12: =IF($S12="","",IF(ABS($S12)<0.05,"PK",IF($S12>0,$F12&" "&TEXT(-$S12,"+0.0;-0.0"),$E12&" "&TEXT($S12,"+0.0;-0.0")))) -> JAX -7.4 | U12: {=IF($B12="","",IFERROR(INDEX(MktHomeSpread,MATCH($B12,MktGameID,0)),""))} | V12: =IF(OR($S12="",$U12=""),"",ROUND($S12+$U12,2)) | W12: =IF($V12="","",ABS($V12)) | X12: =IF($V12="","",IF($V12>0,$F12&" "&TEXT($U12,"+0.0;-0.0;""PK"""),$E12&" "&TEXT(-$U12,"+0.0;-0.0;""PK"""))) | Y12: {=IF($B12="","",IF((IF(AND(IFERROR(INDEX(RatGP,MATCH($E12,RatTeams,0)),0)>=MinGamesTrust,IFERROR(INDEX(RatGP,MATCH($F12,RatTeams,0)),0)>=MinGamesTrust),1,0)+IF($AP12="READY",1,0)+IF(AND(IFERROR(INDEX(RatMode,MATCH($E12,RatTeams,0)),"")="ENHANCED",IFERROR(INDEX(RatMode,MATCH($F12,RatTeams,0)),"")="ENHANCED"),1,0)+IF($AO12="",1,0)+IF(IFERROR(INDEX(MktStale,MATCH($B12,MktGameID,0)),"")<>"STALE",1,0))>=5,"High",IF((IF(AND(IFERROR(INDEX(RatGP,MATCH($E12,RatTeams,0)),0)>=MinGamesTrust,IFERROR(INDEX(RatGP,MATCH($F12,RatTeams,0)),0)>=MinGamesTrust),1,0)+IF($AP12="READY",1,0)+IF(AND(IFERROR(INDEX(RatMode,MATCH($E12,RatTeams,0)),"")="ENHANCED",IFERROR(INDEX(RatMode,MATCH($F12,RatTeams,0)),"")="ENHANCED"),1,0)+IF($AO12="",1,0)+IF(IFERROR(INDEX(MktStale,MATCH($B12,MktGameID,0)),"")<>"STALE",1,0))>=4,"Medium","Low")))} -> Low | Z12: =IF(OR($B12="",$V12=""),"",IF(LEFT($AP12,7)="BLOCKED","",IF(AND($W12>=BetATS,$Y12<>"Low"),IF(AND(EnableBetLabels="Y",$Y12="High",$AP12="READY",ABS(IF($P12="",0,$P12))<=AdjCap),"BET","STRONG INVESTIGATE"),IF($W12>=InvATS,"INVESTIGATE",IF(AND($W12>=LeanATS,$Y12<>"Low"),"LEAN",""))))) | AA12: {=IF($B12="","",IFERROR(ROUND(((1-TotRegress)*0.5*(INDEX(CalcOffPl,MATCH($E12,CalcTeams,0))+INDEX(CalcDefPl,MATCH($F12,CalcTeams,0)))+TotRegress*LeaguePlays)*(INDEX(CalcOffAdj,MATCH($E12,CalcTeams,0))+INDEX(CalcDefAdj,MATCH($F12,CalcTeams,0))-LeaguePPP)+DstPts,2),""))} -> 0 | AB12: {=IF($B12="","",IFERROR(ROUND(((1-TotRegress)*0.5*(INDEX(CalcOffPl,MATCH($F12,CalcTeams,0))+INDEX(CalcDefPl,MATCH($E12,CalcTeams,0)))+TotRegress*LeaguePlays)*(INDEX(CalcOffAdj,MATCH($F12,CalcTeams,0))+INDEX(CalcDefAdj,MATCH($E12,CalcTeams,0))-LeaguePPP)+DstPts,2),""))} -> 0 | AC12: {=IF($B12="","",IFERROR(INDEX(QBTotEff,MATCH($F12,QBTeams,0)),0)+IFERROR(INDEX(QBTotEff,MATCH($E12,QBTeams,0)),0))} -> 0 | AD12: =IF($B12="","",SUMIFS(AdjTot,AdjGameID,$B12,AdjActive,1)) -> 0 | AE12: =IF(OR($AA12="",$AB12=""),"",ROUND($AA12+$AB12+$AC12+$AD12,2)) -> 0 | AG12: =IF(AND($AF12="",$AE12=""),"",IF($AF12<>"",$AF12,$AE12)) -> 0 | AH12: {=IF($B12="","",IFERROR(INDEX(MktTotal,MATCH($B12,MktGameID,0)),""))} | AI12: =IF(OR($AG12="",$AH12=""),"",ROUND($AG12-$AH12,2)) | AJ12: =IF($AI12="","",ABS($AI12)) | AK12: =IF($AI12="","",IF($AI12>0.05,"OVER",IF($AI12<-0.05,"UNDER","—"))) | AL12: {=IF($B12="","",IF((IF(AND(IFERROR(INDEX(RatGP,MATCH($E12,RatTeams,0)),0)>=MinGamesTrust,IFERROR(INDEX(RatGP,MATCH($F12,RatTeams,0)),0)>=MinGamesTrust),1,0)+IF($AP12="READY",1,0)+IF($AO12="",1,0)+IF(IFERROR(INDEX(MktStale,MATCH($B12,MktGameID,0)),"")<>"STALE",1,0)+IF(ABS(IF($AD12="",0,$AD12))<=AdjCap,1,0))>=5,"High",IF((IF(AND(IFERROR(INDEX(RatGP,MATCH($E12,RatTeams,0)),0)>=MinGamesTrust,IFERROR(INDEX(RatGP,MATCH($F12,RatTeams,0)),0)>=MinGamesTrust),1,0)+IF($AP12="READY",1,0)+IF($AO12="",1,0)+IF(IFERROR(INDEX(MktStale,MATCH($B12,MktGameID,0)),"")<>"STALE",1,0)+IF(ABS(IF($AD12="",0,$AD12))<=AdjCap,1,0))>=4,"Medium","Low")))} -> Low | AM12: =IF(OR($B12="",$AI12=""),"",IF(LEFT($AP12,7)="BLOCKED","",IF(AND($AJ12>=BetTot,$AL12<>"Low"),IF(AND(EnableBetLabels="Y",$AL12="High",$AP12="READY"),"BET ","STRONG INVESTIGATE ")&$AK12,IF($AJ12>=InvTot,"INVESTIGATE "&$AK12,IF(AND($AJ12>=LeanTot,$AL12<>"Low"),"LEAN "&$AK12,""))))) | AN12: =IF($AG12="","","BET OVER at ≤ "&TEXT($AG12-BetTot,"0.0")&" | BET UNDER at ≥ "&TEXT($AG12+BetTot,"0.0")) -> BET OVER at ≤ -3.0 | BET UNDER at ≥ 3.0 | AO12: {=IF($B12="","",IF(OR(IFERROR(INDEX(QBFlag,MATCH($F12,QBTeams,0)),1)=1,IFERROR(INDEX(QBFlag,MATCH($E12,QBTeams,0)),1)=1),"QB UNCERTAIN",""))} -> QB UNCERTAIN | AP12: {=IF($B12="","",IFERROR(INDEX(DQStatus,MATCH($B12,DQGameID,0)),"BLOCKED — DQ ROW NOT FOUND"))} -> READY | AQ12: {=IF($B12="","",IF(LEFT($AP12,7)="BLOCKED",IF($AP12="BLOCKED","BLOCKED — see DATA QUALITY",$AP12),IF(AND($U12="",$AH12=""),"PENDING BOTH",IF($U12="","PENDING SPREAD",IF($AH12="","PENDING TOTAL",IF(IFERROR(INDEX(MktStale,MATCH($B12,MktGameID,0)),"")="STALE","STALE LINE",IF($AO12<>"",$AO12,IF(OR(NOT(ISNUMBER($J12)),NOT(ISNUMBER($K12))),"DATA INCOMPLETE","READY"))))))))} -> PENDING BOTH | AR12: =IF(OR($R12<>"",$AF12<>""),"OVERRIDE","") | AS12: {=IF(OR($B12="",$C12<>CurrentWeek),"",ROUND(25*MIN(1,IF($W12="",0,$W12)/5)+20*IF($AP12="READY",1,0)+20*IF($AO12="",1,0)+15*IF(IFERROR(INDEX(MktStale,MATCH($B12,MktGameID,0)),"x")="OK",1,0)+10*MAX(0,1-ABS(IF($P12="",0,$P12))/AdjCap)+10*IF(AND($Z12<>"",$AM12<>""),1,0),0))} -> 30 | AT12: =IF($AS12="","",RANK($AS12,$AS$5:$AS$304,0)) -> 13
A13: 9 | B13: {=IFERROR(INDEX(SchedZone,MATCH($A13,SchedSeq,0),MAP!$B$6),"")} -> 2026_01_ATL_PIT | C13: {=IF($B13="","",INDEX(SchedZone,MATCH($A13,SchedSeq,0),MAP!$B$4))} -> 1 | D13: {=IF($B13="","",INDEX(SchedZone,MATCH($A13,SchedSeq,0),MAP!$B$7))} -> 46278 | E13: {=IF($B13="","",IF(COUNTIF(Teams,INDEX(SchedZone,MATCH($A13,SchedSeq,0),MAP!$B$10))>0,INDEX(SchedZone,MATCH($A13,SchedSeq,0),MAP!$B$10),IFERROR(INDEX(LISTS!$D$2:$D$12,MATCH(INDEX(SchedZone,MATCH($A13,SchedSeq,0),MAP!$B$10),LISTS!$C$2:$C$12,0)),"⚠ "&INDEX(SchedZone,MATCH($A13,SchedSeq,0),MAP!$B$10))))} -> ATL | F13: {=IF($B13="","",IF(COUNTIF(Teams,INDEX(SchedZone,MATCH($A13,SchedSeq,0),MAP!$B$12))>0,INDEX(SchedZone,MATCH($A13,SchedSeq,0),MAP!$B$12),IFERROR(INDEX(LISTS!$D$2:$D$12,MATCH(INDEX(SchedZone,MATCH($A13,SchedSeq,0),MAP!$B$12),LISTS!$C$2:$C$12,0)),"⚠ "&INDEX(SchedZone,MATCH($A13,SchedSeq,0),MAP!$B$12))))} -> PIT | G13: {=IF($B13="","",IF(INDEX(SchedZone,MATCH($A13,SchedSeq,0),MAP!$B$14)="Neutral","Y",""))} | H13: {=IF($B13="","",INDEX(SchedZone,MATCH($A13,SchedSeq,0),MAP!$B$17))} -> outdoors | I13: =IF(OR($B13="",$C13<>CurrentWeek),"",COUNTIF($C$5:$C13,CurrentWeek)) -> 9 | J13: {=IF($B13="","",IFERROR(INDEX(RatEff,MATCH($E13,RatTeams,0)),"⚠ TEAM NOT FOUND"))} -> -0.06 | K13: {=IF($B13="","",IFERROR(INDEX(RatEff,MATCH($F13,RatTeams,0)),"⚠ TEAM NOT FOUND"))} -> 0.66 | L13: =IF(OR($B13="",NOT(ISNUMBER($J13)),NOT(ISNUMBER($K13))),"",$K13-$J13) -> 0.72 | M13: {=IF($B13="","",IF($G13="Y",NeutralHFA,IFERROR(INDEX(HFAexcVal,MATCH($F13,HFAexcTeam,0)),HFA_Base)))} -> 1.6 | N13: {=IF($B13="","",IFERROR(INDEX(QBSpreadEff,MATCH($F13,QBTeams,0)),0)-IFERROR(INDEX(QBSpreadEff,MATCH($E13,QBTeams,0)),0))} -> 0 | O13: {=IF($B13="","",IFERROR(MEDIAN(-RestCapPts,RestCapPts,RestPerDay*(INDEX(SchedZone,MATCH($A13,SchedSeq,0),MAP!$B$16)-INDEX(SchedZone,MATCH($A13,SchedSeq,0),MAP!$B$15))),0))} -> 0 | P13: =IF($B13="","",SUMIFS(AdjSpread,AdjGameID,$B13,AdjTeam,$F13,AdjActive,1)-SUMIFS(AdjSpread,AdjGameID,$B13,AdjTeam,$E13,AdjActive,1)) -> 0 | Q13: =IF($L13="","",ROUND($L13+$M13+$N13+$O13+$P13,2)) -> 2.32 | S13: =IF(AND($R13="",$Q13=""),"",IF($R13<>"",$R13,$Q13)) -> 2.32 | T13: =IF($S13="","",IF(ABS($S13)<0.05,"PK",IF($S13>0,$F13&" "&TEXT(-$S13,"+0.0;-0.0"),$E13&" "&TEXT($S13,"+0.0;-0.0")))) -> PIT -2.3 | U13: {=IF($B13="","",IFERROR(INDEX(MktHomeSpread,MATCH($B13,MktGameID,0)),""))} | V13: =IF(OR($S13="",$U13=""),"",ROUND($S13+$U13,2)) | W13: =IF($V13="","",ABS($V13)) | X13: =IF($V13="","",IF($V13>0,$F13&" "&TEXT($U13,"+0.0;-0.0;""PK"""),$E13&" "&TEXT(-$U13,"+0.0;-0.0;""PK"""))) | Y13: {=IF($B13="","",IF((IF(AND(IFERROR(INDEX(RatGP,MATCH($E13,RatTeams,0)),0)>=MinGamesTrust,IFERROR(INDEX(RatGP,MATCH($F13,RatTeams,0)),0)>=MinGamesTrust),1,0)+IF($AP13="READY",1,0)+IF(AND(IFERROR(INDEX(RatMode,MATCH($E13,RatTeams,0)),"")="ENHANCED",IFERROR(INDEX(RatMode,MATCH($F13,RatTeams,0)),"")="ENHANCED"),1,0)+IF($AO13="",1,0)+IF(IFERROR(INDEX(MktStale,MATCH($B13,MktGameID,0)),"")<>"STALE",1,0))>=5,"High",IF((IF(AND(IFERROR(INDEX(RatGP,MATCH($E13,RatTeams,0)),0)>=MinGamesTrust,IFERROR(INDEX(RatGP,MATCH($F13,RatTeams,0)),0)>=MinGamesTrust),1,0)+IF($AP13="READY",1,0)+IF(AND(IFERROR(INDEX(RatMode,MATCH($E13,RatTeams,0)),"")="ENHANCED",IFERROR(INDEX(RatMode,MATCH($F13,RatTeams,0)),"")="ENHANCED"),1,0)+IF($AO13="",1,0)+IF(IFERROR(INDEX(MktStale,MATCH($B13,MktGameID,0)),"")<>"STALE",1,0))>=4,"Medium","Low")))} -> Low | Z13: =IF(OR($B13="",$V13=""),"",IF(LEFT($AP13,7)="BLOCKED","",IF(AND($W13>=BetATS,$Y13<>"Low"),IF(AND(EnableBetLabels="Y",$Y13="High",$AP13="READY",ABS(IF($P13="",0,$P13))<=AdjCap),"BET","STRONG INVESTIGATE"),IF($W13>=InvATS,"INVESTIGATE",IF(AND($W13>=LeanATS,$Y13<>"Low"),"LEAN",""))))) | AA13: {=IF($B13="","",IFERROR(ROUND(((1-TotRegress)*0.5*(INDEX(CalcOffPl,MATCH($E13,CalcTeams,0))+INDEX(CalcDefPl,MATCH($F13,CalcTeams,0)))+TotRegress*LeaguePlays)*(INDEX(CalcOffAdj,MATCH($E13,CalcTeams,0))+INDEX(CalcDefAdj,MATCH($F13,CalcTeams,0))-LeaguePPP)+DstPts,2),""))} -> 0 | AB13: {=IF($B13="","",IFERROR(ROUND(((1-TotRegress)*0.5*(INDEX(CalcOffPl,MATCH($F13,CalcTeams,0))+INDEX(CalcDefPl,MATCH($E13,CalcTeams,0)))+TotRegress*LeaguePlays)*(INDEX(CalcOffAdj,MATCH($F13,CalcTeams,0))+INDEX(CalcDefAdj,MATCH($E13,CalcTeams,0))-LeaguePPP)+DstPts,2),""))} -> 0 | AC13: {=IF($B13="","",IFERROR(INDEX(QBTotEff,MATCH($F13,QBTeams,0)),0)+IFERROR(INDEX(QBTotEff,MATCH($E13,QBTeams,0)),0))} -> 0 | AD13: =IF($B13="","",SUMIFS(AdjTot,AdjGameID,$B13,AdjActive,1)) -> 0 | AE13: =IF(OR($AA13="",$AB13=""),"",ROUND($AA13+$AB13+$AC13+$AD13,2)) -> 0 | AG13: =IF(AND($AF13="",$AE13=""),"",IF($AF13<>"",$AF13,$AE13)) -> 0 | AH13: {=IF($B13="","",IFERROR(INDEX(MktTotal,MATCH($B13,MktGameID,0)),""))} | AI13: =IF(OR($AG13="",$AH13=""),"",ROUND($AG13-$AH13,2)) | AJ13: =IF($AI13="","",ABS($AI13)) | AK13: =IF($AI13="","",IF($AI13>0.05,"OVER",IF($AI13<-0.05,"UNDER","—"))) | AL13: {=IF($B13="","",IF((IF(AND(IFERROR(INDEX(RatGP,MATCH($E13,RatTeams,0)),0)>=MinGamesTrust,IFERROR(INDEX(RatGP,MATCH($F13,RatTeams,0)),0)>=MinGamesTrust),1,0)+IF($AP13="READY",1,0)+IF($AO13="",1,0)+IF(IFERROR(INDEX(MktStale,MATCH($B13,MktGameID,0)),"")<>"STALE",1,0)+IF(ABS(IF($AD13="",0,$AD13))<=AdjCap,1,0))>=5,"High",IF((IF(AND(IFERROR(INDEX(RatGP,MATCH($E13,RatTeams,0)),0)>=MinGamesTrust,IFERROR(INDEX(RatGP,MATCH($F13,RatTeams,0)),0)>=MinGamesTrust),1,0)+IF($AP13="READY",1,0)+IF($AO13="",1,0)+IF(IFERROR(INDEX(MktStale,MATCH($B13,MktGameID,0)),"")<>"STALE",1,0)+IF(ABS(IF($AD13="",0,$AD13))<=AdjCap,1,0))>=4,"Medium","Low")))} -> Low | AM13: =IF(OR($B13="",$AI13=""),"",IF(LEFT($AP13,7)="BLOCKED","",IF(AND($AJ13>=BetTot,$AL13<>"Low"),IF(AND(EnableBetLabels="Y",$AL13="High",$AP13="READY"),"BET ","STRONG INVESTIGATE ")&$AK13,IF($AJ13>=InvTot,"INVESTIGATE "&$AK13,IF(AND($AJ13>=LeanTot,$AL13<>"Low"),"LEAN "&$AK13,""))))) | AN13: =IF($AG13="","","BET OVER at ≤ "&TEXT($AG13-BetTot,"0.0")&" | BET UNDER at ≥ "&TEXT($AG13+BetTot,"0.0")) -> BET OVER at ≤ -3.0 | BET UNDER at ≥ 3.0 | AO13: {=IF($B13="","",IF(OR(IFERROR(INDEX(QBFlag,MATCH($F13,QBTeams,0)),1)=1,IFERROR(INDEX(QBFlag,MATCH($E13,QBTeams,0)),1)=1),"QB UNCERTAIN",""))} -> QB UNCERTAIN | AP13: {=IF($B13="","",IFERROR(INDEX(DQStatus,MATCH($B13,DQGameID,0)),"BLOCKED — DQ ROW NOT FOUND"))} -> READY | AQ13: {=IF($B13="","",IF(LEFT($AP13,7)="BLOCKED",IF($AP13="BLOCKED","BLOCKED — see DATA QUALITY",$AP13),IF(AND($U13="",$AH13=""),"PENDING BOTH",IF($U13="","PENDING SPREAD",IF($AH13="","PENDING TOTAL",IF(IFERROR(INDEX(MktStale,MATCH($B13,MktGameID,0)),"")="STALE","STALE LINE",IF($AO13<>"",$AO13,IF(OR(NOT(ISNUMBER($J13)),NOT(ISNUMBER($K13))),"DATA INCOMPLETE","READY"))))))))} -> PENDING BOTH | AR13: =IF(OR($R13<>"",$AF13<>""),"OVERRIDE","") | AS13: {=IF(OR($B13="",$C13<>CurrentWeek),"",ROUND(25*MIN(1,IF($W13="",0,$W13)/5)+20*IF($AP13="READY",1,0)+20*IF($AO13="",1,0)+15*IF(IFERROR(INDEX(MktStale,MATCH($B13,MktGameID,0)),"x")="OK",1,0)+10*MAX(0,1-ABS(IF($P13="",0,$P13))/AdjCap)+10*IF(AND($Z13<>"",$AM13<>""),1,0),0))} -> 30 | AT13: =IF($AS13="","",RANK($AS13,$AS$5:$AS$304,0)) -> 13
A14: 10 | B14: {=IFERROR(INDEX(SchedZone,MATCH($A14,SchedSeq,0),MAP!$B$6),"")} -> 2026_01_NYJ_TEN | C14: {=IF($B14="","",INDEX(SchedZone,MATCH($A14,SchedSeq,0),MAP!$B$4))} -> 1 | D14: {=IF($B14="","",INDEX(SchedZone,MATCH($A14,SchedSeq,0),MAP!$B$7))} -> 46278 | E14: {=IF($B14="","",IF(COUNTIF(Teams,INDEX(SchedZone,MATCH($A14,SchedSeq,0),MAP!$B$10))>0,INDEX(SchedZone,MATCH($A14,SchedSeq,0),MAP!$B$10),IFERROR(INDEX(LISTS!$D$2:$D$12,MATCH(INDEX(SchedZone,MATCH($A14,SchedSeq,0),MAP!$B$10),LISTS!$C$2:$C$12,0)),"⚠ "&INDEX(SchedZone,MATCH($A14,SchedSeq,0),MAP!$B$10))))} -> NYJ | F14: {=IF($B14="","",IF(COUNTIF(Teams,INDEX(SchedZone,MATCH($A14,SchedSeq,0),MAP!$B$12))>0,INDEX(SchedZone,MATCH($A14,SchedSeq,0),MAP!$B$12),IFERROR(INDEX(LISTS!$D$2:$D$12,MATCH(INDEX(SchedZone,MATCH($A14,SchedSeq,0),MAP!$B$12),LISTS!$C$2:$C$12,0)),"⚠ "&INDEX(SchedZone,MATCH($A14,SchedSeq,0),MAP!$B$12))))} -> TEN | G14: {=IF($B14="","",IF(INDEX(SchedZone,MATCH($A14,SchedSeq,0),MAP!$B$14)="Neutral","Y",""))} | H14: {=IF($B14="","",INDEX(SchedZone,MATCH($A14,SchedSeq,0),MAP!$B$17))} -> outdoors | I14: =IF(OR($B14="",$C14<>CurrentWeek),"",COUNTIF($C$5:$C14,CurrentWeek)) -> 10 | J14: {=IF($B14="","",IFERROR(INDEX(RatEff,MATCH($E14,RatTeams,0)),"⚠ TEAM NOT FOUND"))} -> -4.67 | K14: {=IF($B14="","",IFERROR(INDEX(RatEff,MATCH($F14,RatTeams,0)),"⚠ TEAM NOT FOUND"))} -> -3.14 | L14: =IF(OR($B14="",NOT(ISNUMBER($J14)),NOT(ISNUMBER($K14))),"",$K14-$J14) -> 1.53 | M14: {=IF($B14="","",IF($G14="Y",NeutralHFA,IFERROR(INDEX(HFAexcVal,MATCH($F14,HFAexcTeam,0)),HFA_Base)))} -> 1.6 | N14: {=IF($B14="","",IFERROR(INDEX(QBSpreadEff,MATCH($F14,QBTeams,0)),0)-IFERROR(INDEX(QBSpreadEff,MATCH($E14,QBTeams,0)),0))} -> 0 | O14: {=IF($B14="","",IFERROR(MEDIAN(-RestCapPts,RestCapPts,RestPerDay*(INDEX(SchedZone,MATCH($A14,SchedSeq,0),MAP!$B$16)-INDEX(SchedZone,MATCH($A14,SchedSeq,0),MAP!$B$15))),0))} -> 0 | P14: =IF($B14="","",SUMIFS(AdjSpread,AdjGameID,$B14,AdjTeam,$F14,AdjActive,1)-SUMIFS(AdjSpread,AdjGameID,$B14,AdjTeam,$E14,AdjActive,1)) -> 0 | Q14: =IF($L14="","",ROUND($L14+$M14+$N14+$O14+$P14,2)) -> 3.13 | S14: =IF(AND($R14="",$Q14=""),"",IF($R14<>"",$R14,$Q14)) -> 3.13 | T14: =IF($S14="","",IF(ABS($S14)<0.05,"PK",IF($S14>0,$F14&" "&TEXT(-$S14,"+0.0;-0.0"),$E14&" "&TEXT($S14,"+0.0;-0.0")))) -> TEN -3.1 | U14: {=IF($B14="","",IFERROR(INDEX(MktHomeSpread,MATCH($B14,MktGameID,0)),""))} | V14: =IF(OR($S14="",$U14=""),"",ROUND($S14+$U14,2)) | W14: =IF($V14="","",ABS($V14)) | X14: =IF($V14="","",IF($V14>0,$F14&" "&TEXT($U14,"+0.0;-0.0;""PK"""),$E14&" "&TEXT(-$U14,"+0.0;-0.0;""PK"""))) | Y14: {=IF($B14="","",IF((IF(AND(IFERROR(INDEX(RatGP,MATCH($E14,RatTeams,0)),0)>=MinGamesTrust,IFERROR(INDEX(RatGP,MATCH($F14,RatTeams,0)),0)>=MinGamesTrust),1,0)+IF($AP14="READY",1,0)+IF(AND(IFERROR(INDEX(RatMode,MATCH($E14,RatTeams,0)),"")="ENHANCED",IFERROR(INDEX(RatMode,MATCH($F14,RatTeams,0)),"")="ENHANCED"),1,0)+IF($AO14="",1,0)+IF(IFERROR(INDEX(MktStale,MATCH($B14,MktGameID,0)),"")<>"STALE",1,0))>=5,"High",IF((IF(AND(IFERROR(INDEX(RatGP,MATCH($E14,RatTeams,0)),0)>=MinGamesTrust,IFERROR(INDEX(RatGP,MATCH($F14,RatTeams,0)),0)>=MinGamesTrust),1,0)+IF($AP14="READY",1,0)+IF(AND(IFERROR(INDEX(RatMode,MATCH($E14,RatTeams,0)),"")="ENHANCED",IFERROR(INDEX(RatMode,MATCH($F14,RatTeams,0)),"")="ENHANCED"),1,0)+IF($AO14="",1,0)+IF(IFERROR(INDEX(MktStale,MATCH($B14,MktGameID,0)),"")<>"STALE",1,0))>=4,"Medium","Low")))} -> Low | Z14: =IF(OR($B14="",$V14=""),"",IF(LEFT($AP14,7)="BLOCKED","",IF(AND($W14>=BetATS,$Y14<>"Low"),IF(AND(EnableBetLabels="Y",$Y14="High",$AP14="READY",ABS(IF($P14="",0,$P14))<=AdjCap),"BET","STRONG INVESTIGATE"),IF($W14>=InvATS,"INVESTIGATE",IF(AND($W14>=LeanATS,$Y14<>"Low"),"LEAN",""))))) | AA14: {=IF($B14="","",IFERROR(ROUND(((1-TotRegress)*0.5*(INDEX(CalcOffPl,MATCH($E14,CalcTeams,0))+INDEX(CalcDefPl,MATCH($F14,CalcTeams,0)))+TotRegress*LeaguePlays)*(INDEX(CalcOffAdj,MATCH($E14,CalcTeams,0))+INDEX(CalcDefAdj,MATCH($F14,CalcTeams,0))-LeaguePPP)+DstPts,2),""))} -> 0 | AB14: {=IF($B14="","",IFERROR(ROUND(((1-TotRegress)*0.5*(INDEX(CalcOffPl,MATCH($F14,CalcTeams,0))+INDEX(CalcDefPl,MATCH($E14,CalcTeams,0)))+TotRegress*LeaguePlays)*(INDEX(CalcOffAdj,MATCH($F14,CalcTeams,0))+INDEX(CalcDefAdj,MATCH($E14,CalcTeams,0))-LeaguePPP)+DstPts,2),""))} -> 0 | AC14: {=IF($B14="","",IFERROR(INDEX(QBTotEff,MATCH($F14,QBTeams,0)),0)+IFERROR(INDEX(QBTotEff,MATCH($E14,QBTeams,0)),0))} -> 0 | AD14: =IF($B14="","",SUMIFS(AdjTot,AdjGameID,$B14,AdjActive,1)) -> 0 | AE14: =IF(OR($AA14="",$AB14=""),"",ROUND($AA14+$AB14+$AC14+$AD14,2)) -> 0 | AG14: =IF(AND($AF14="",$AE14=""),"",IF($AF14<>"",$AF14,$AE14)) -> 0 | AH14: {=IF($B14="","",IFERROR(INDEX(MktTotal,MATCH($B14,MktGameID,0)),""))} | AI14: =IF(OR($AG14="",$AH14=""),"",ROUND($AG14-$AH14,2)) | AJ14: =IF($AI14="","",ABS($AI14)) | AK14: =IF($AI14="","",IF($AI14>0.05,"OVER",IF($AI14<-0.05,"UNDER","—"))) | AL14: {=IF($B14="","",IF((IF(AND(IFERROR(INDEX(RatGP,MATCH($E14,RatTeams,0)),0)>=MinGamesTrust,IFERROR(INDEX(RatGP,MATCH($F14,RatTeams,0)),0)>=MinGamesTrust),1,0)+IF($AP14="READY",1,0)+IF($AO14="",1,0)+IF(IFERROR(INDEX(MktStale,MATCH($B14,MktGameID,0)),"")<>"STALE",1,0)+IF(ABS(IF($AD14="",0,$AD14))<=AdjCap,1,0))>=5,"High",IF((IF(AND(IFERROR(INDEX(RatGP,MATCH($E14,RatTeams,0)),0)>=MinGamesTrust,IFERROR(INDEX(RatGP,MATCH($F14,RatTeams,0)),0)>=MinGamesTrust),1,0)+IF($AP14="READY",1,0)+IF($AO14="",1,0)+IF(IFERROR(INDEX(MktStale,MATCH($B14,MktGameID,0)),"")<>"STALE",1,0)+IF(ABS(IF($AD14="",0,$AD14))<=AdjCap,1,0))>=4,"Medium","Low")))} -> Medium | AM14: =IF(OR($B14="",$AI14=""),"",IF(LEFT($AP14,7)="BLOCKED","",IF(AND($AJ14>=BetTot,$AL14<>"Low"),IF(AND(EnableBetLabels="Y",$AL14="High",$AP14="READY"),"BET ","STRONG INVESTIGATE ")&$AK14,IF($AJ14>=InvTot,"INVESTIGATE "&$AK14,IF(AND($AJ14>=LeanTot,$AL14<>"Low"),"LEAN "&$AK14,""))))) | AN14: =IF($AG14="","","BET OVER at ≤ "&TEXT($AG14-BetTot,"0.0")&" | BET UNDER at ≥ "&TEXT($AG14+BetTot,"0.0")) -> BET OVER at ≤ -3.0 | BET UNDER at ≥ 3.0 | AO14: {=IF($B14="","",IF(OR(IFERROR(INDEX(QBFlag,MATCH($F14,QBTeams,0)),1)=1,IFERROR(INDEX(QBFlag,MATCH($E14,QBTeams,0)),1)=1),"QB UNCERTAIN",""))} | AP14: {=IF($B14="","",IFERROR(INDEX(DQStatus,MATCH($B14,DQGameID,0)),"BLOCKED — DQ ROW NOT FOUND"))} -> READY | AQ14: {=IF($B14="","",IF(LEFT($AP14,7)="BLOCKED",IF($AP14="BLOCKED","BLOCKED — see DATA QUALITY",$AP14),IF(AND($U14="",$AH14=""),"PENDING BOTH",IF($U14="","PENDING SPREAD",IF($AH14="","PENDING TOTAL",IF(IFERROR(INDEX(MktStale,MATCH($B14,MktGameID,0)),"")="STALE","STALE LINE",IF($AO14<>"",$AO14,IF(OR(NOT(ISNUMBER($J14)),NOT(ISNUMBER($K14))),"DATA INCOMPLETE","READY"))))))))} -> PENDING BOTH | AR14: =IF(OR($R14<>"",$AF14<>""),"OVERRIDE","") | AS14: {=IF(OR($B14="",$C14<>CurrentWeek),"",ROUND(25*MIN(1,IF($W14="",0,$W14)/5)+20*IF($AP14="READY",1,0)+20*IF($AO14="",1,0)+15*IF(IFERROR(INDEX(MktStale,MATCH($B14,MktGameID,0)),"x")="OK",1,0)+10*MAX(0,1-ABS(IF($P14="",0,$P14))/AdjCap)+10*IF(AND($Z14<>"",$AM14<>""),1,0),0))} -> 50 | AT14: =IF($AS14="","",RANK($AS14,$AS$5:$AS$304,0)) -> 1
A15: 11 | B15: {=IFERROR(INDEX(SchedZone,MATCH($A15,SchedSeq,0),MAP!$B$6),"")} -> 2026_01_ARI_LAC | C15: {=IF($B15="","",INDEX(SchedZone,MATCH($A15,SchedSeq,0),MAP!$B$4))} -> 1 | D15: {=IF($B15="","",INDEX(SchedZone,MATCH($A15,SchedSeq,0),MAP!$B$7))} -> 46278 | E15: {=IF($B15="","",IF(COUNTIF(Teams,INDEX(SchedZone,MATCH($A15,SchedSeq,0),MAP!$B$10))>0,INDEX(SchedZone,MATCH($A15,SchedSeq,0),MAP!$B$10),IFERROR(INDEX(LISTS!$D$2:$D$12,MATCH(INDEX(SchedZone,MATCH($A15,SchedSeq,0),MAP!$B$10),LISTS!$C$2:$C$12,0)),"⚠ "&INDEX(SchedZone,MATCH($A15,SchedSeq,0),MAP!$B$10))))} -> ARI | F15: {=IF($B15="","",IF(COUNTIF(Teams,INDEX(SchedZone,MATCH($A15,SchedSeq,0),MAP!$B$12))>0,INDEX(SchedZone,MATCH($A15,SchedSeq,0),MAP!$B$12),IFERROR(INDEX(LISTS!$D$2:$D$12,MATCH(INDEX(SchedZone,MATCH($A15,SchedSeq,0),MAP!$B$12),LISTS!$C$2:$C$12,0)),"⚠ "&INDEX(SchedZone,MATCH($A15,SchedSeq,0),MAP!$B$12))))} -> LAC | G15: {=IF($B15="","",IF(INDEX(SchedZone,MATCH($A15,SchedSeq,0),MAP!$B$14)="Neutral","Y",""))} | H15: {=IF($B15="","",INDEX(SchedZone,MATCH($A15,SchedSeq,0),MAP!$B$17))} -> dome | I15: =IF(OR($B15="",$C15<>CurrentWeek),"",COUNTIF($C$5:$C15,CurrentWeek)) -> 11 | J15: {=IF($B15="","",IFERROR(INDEX(RatEff,MATCH($E15,RatTeams,0)),"⚠ TEAM NOT FOUND"))} -> -2.07 | K15: {=IF($B15="","",IFERROR(INDEX(RatEff,MATCH($F15,RatTeams,0)),"⚠ TEAM NOT FOUND"))} -> 0.56 | L15: =IF(OR($B15="",NOT(ISNUMBER($J15)),NOT(ISNUMBER($K15))),"",$K15-$J15) -> 2.63 | M15: {=IF($B15="","",IF($G15="Y",NeutralHFA,IFERROR(INDEX(HFAexcVal,MATCH($F15,HFAexcTeam,0)),HFA_Base)))} -> 1.6 | N15: {=IF($B15="","",IFERROR(INDEX(QBSpreadEff,MATCH($F15,QBTeams,0)),0)-IFERROR(INDEX(QBSpreadEff,MATCH($E15,QBTeams,0)),0))} -> 0 | O15: {=IF($B15="","",IFERROR(MEDIAN(-RestCapPts,RestCapPts,RestPerDay*(INDEX(SchedZone,MATCH($A15,SchedSeq,0),MAP!$B$16)-INDEX(SchedZone,MATCH($A15,SchedSeq,0),MAP!$B$15))),0))} -> 0 | P15: =IF($B15="","",SUMIFS(AdjSpread,AdjGameID,$B15,AdjTeam,$F15,AdjActive,1)-SUMIFS(AdjSpread,AdjGameID,$B15,AdjTeam,$E15,AdjActive,1)) -> 0 | Q15: =IF($L15="","",ROUND($L15+$M15+$N15+$O15+$P15,2)) -> 4.23 | S15: =IF(AND($R15="",$Q15=""),"",IF($R15<>"",$R15,$Q15)) -> 4.23 | T15: =IF($S15="","",IF(ABS($S15)<0.05,"PK",IF($S15>0,$F15&" "&TEXT(-$S15,"+0.0;-0.0"),$E15&" "&TEXT($S15,"+0.0;-0.0")))) -> LAC -4.2 | U15: {=IF($B15="","",IFERROR(INDEX(MktHomeSpread,MATCH($B15,MktGameID,0)),""))} | V15: =IF(OR($S15="",$U15=""),"",ROUND($S15+$U15,2)) | W15: =IF($V15="","",ABS($V15)) | X15: =IF($V15="","",IF($V15>0,$F15&" "&TEXT($U15,"+0.0;-0.0;""PK"""),$E15&" "&TEXT(-$U15,"+0.0;-0.0;""PK"""))) | Y15: {=IF($B15="","",IF((IF(AND(IFERROR(INDEX(RatGP,MATCH($E15,RatTeams,0)),0)>=MinGamesTrust,IFERROR(INDEX(RatGP,MATCH($F15,RatTeams,0)),0)>=MinGamesTrust),1,0)+IF($AP15="READY",1,0)+IF(AND(IFERROR(INDEX(RatMode,MATCH($E15,RatTeams,0)),"")="ENHANCED",IFERROR(INDEX(RatMode,MATCH($F15,RatTeams,0)),"")="ENHANCED"),1,0)+IF($AO15="",1,0)+IF(IFERROR(INDEX(MktStale,MATCH($B15,MktGameID,0)),"")<>"STALE",1,0))>=5,"High",IF((IF(AND(IFERROR(INDEX(RatGP,MATCH($E15,RatTeams,0)),0)>=MinGamesTrust,IFERROR(INDEX(RatGP,MATCH($F15,RatTeams,0)),0)>=MinGamesTrust),1,0)+IF($AP15="READY",1,0)+IF(AND(IFERROR(INDEX(RatMode,MATCH($E15,RatTeams,0)),"")="ENHANCED",IFERROR(INDEX(RatMode,MATCH($F15,RatTeams,0)),"")="ENHANCED"),1,0)+IF($AO15="",1,0)+IF(IFERROR(INDEX(MktStale,MATCH($B15,MktGameID,0)),"")<>"STALE",1,0))>=4,"Medium","Low")))} -> Low | Z15: =IF(OR($B15="",$V15=""),"",IF(LEFT($AP15,7)="BLOCKED","",IF(AND($W15>=BetATS,$Y15<>"Low"),IF(AND(EnableBetLabels="Y",$Y15="High",$AP15="READY",ABS(IF($P15="",0,$P15))<=AdjCap),"BET","STRONG INVESTIGATE"),IF($W15>=InvATS,"INVESTIGATE",IF(AND($W15>=LeanATS,$Y15<>"Low"),"LEAN",""))))) | AA15: {=IF($B15="","",IFERROR(ROUND(((1-TotRegress)*0.5*(INDEX(CalcOffPl,MATCH($E15,CalcTeams,0))+INDEX(CalcDefPl,MATCH($F15,CalcTeams,0)))+TotRegress*LeaguePlays)*(INDEX(CalcOffAdj,MATCH($E15,CalcTeams,0))+INDEX(CalcDefAdj,MATCH($F15,CalcTeams,0))-LeaguePPP)+DstPts,2),""))} -> 0 | AB15: {=IF($B15="","",IFERROR(ROUND(((1-TotRegress)*0.5*(INDEX(CalcOffPl,MATCH($F15,CalcTeams,0))+INDEX(CalcDefPl,MATCH($E15,CalcTeams,0)))+TotRegress*LeaguePlays)*(INDEX(CalcOffAdj,MATCH($F15,CalcTeams,0))+INDEX(CalcDefAdj,MATCH($E15,CalcTeams,0))-LeaguePPP)+DstPts,2),""))} -> 0 | AC15: {=IF($B15="","",IFERROR(INDEX(QBTotEff,MATCH($F15,QBTeams,0)),0)+IFERROR(INDEX(QBTotEff,MATCH($E15,QBTeams,0)),0))} -> 0 | AD15: =IF($B15="","",SUMIFS(AdjTot,AdjGameID,$B15,AdjActive,1)) -> 0 | AE15: =IF(OR($AA15="",$AB15=""),"",ROUND($AA15+$AB15+$AC15+$AD15,2)) -> 0 | AG15: =IF(AND($AF15="",$AE15=""),"",IF($AF15<>"",$AF15,$AE15)) -> 0 | AH15: {=IF($B15="","",IFERROR(INDEX(MktTotal,MATCH($B15,MktGameID,0)),""))} | AI15: =IF(OR($AG15="",$AH15=""),"",ROUND($AG15-$AH15,2)) | AJ15: =IF($AI15="","",ABS($AI15)) | AK15: =IF($AI15="","",IF($AI15>0.05,"OVER",IF($AI15<-0.05,"UNDER","—"))) | AL15: {=IF($B15="","",IF((IF(AND(IFERROR(INDEX(RatGP,MATCH($E15,RatTeams,0)),0)>=MinGamesTrust,IFERROR(INDEX(RatGP,MATCH($F15,RatTeams,0)),0)>=MinGamesTrust),1,0)+IF($AP15="READY",1,0)+IF($AO15="",1,0)+IF(IFERROR(INDEX(MktStale,MATCH($B15,MktGameID,0)),"")<>"STALE",1,0)+IF(ABS(IF($AD15="",0,$AD15))<=AdjCap,1,0))>=5,"High",IF((IF(AND(IFERROR(INDEX(RatGP,MATCH($E15,RatTeams,0)),0)>=MinGamesTrust,IFERROR(INDEX(RatGP,MATCH($F15,RatTeams,0)),0)>=MinGamesTrust),1,0)+IF($AP15="READY",1,0)+IF($AO15="",1,0)+IF(IFERROR(INDEX(MktStale,MATCH($B15,MktGameID,0)),"")<>"STALE",1,0)+IF(ABS(IF($AD15="",0,$AD15))<=AdjCap,1,0))>=4,"Medium","Low")))} -> Low | AM15: =IF(OR($B15="",$AI15=""),"",IF(LEFT($AP15,7)="BLOCKED","",IF(AND($AJ15>=BetTot,$AL15<>"Low"),IF(AND(EnableBetLabels="Y",$AL15="High",$AP15="READY"),"BET ","STRONG INVESTIGATE ")&$AK15,IF($AJ15>=InvTot,"INVESTIGATE "&$AK15,IF(AND($AJ15>=LeanTot,$AL15<>"Low"),"LEAN "&$AK15,""))))) | AN15: =IF($AG15="","","BET OVER at ≤ "&TEXT($AG15-BetTot,"0.0")&" | BET UNDER at ≥ "&TEXT($AG15+BetTot,"0.0")) -> BET OVER at ≤ -3.0 | BET UNDER at ≥ 3.0 | AO15: {=IF($B15="","",IF(OR(IFERROR(INDEX(QBFlag,MATCH($F15,QBTeams,0)),1)=1,IFERROR(INDEX(QBFlag,MATCH($E15,QBTeams,0)),1)=1),"QB UNCERTAIN",""))} -> QB UNCERTAIN | AP15: {=IF($B15="","",IFERROR(INDEX(DQStatus,MATCH($B15,DQGameID,0)),"BLOCKED — DQ ROW NOT FOUND"))} -> READY | AQ15: {=IF($B15="","",IF(LEFT($AP15,7)="BLOCKED",IF($AP15="BLOCKED","BLOCKED — see DATA QUALITY",$AP15),IF(AND($U15="",$AH15=""),"PENDING BOTH",IF($U15="","PENDING SPREAD",IF($AH15="","PENDING TOTAL",IF(IFERROR(INDEX(MktStale,MATCH($B15,MktGameID,0)),"")="STALE","STALE LINE",IF($AO15<>"",$AO15,IF(OR(NOT(ISNUMBER($J15)),NOT(ISNUMBER($K15))),"DATA INCOMPLETE","READY"))))))))} -> PENDING BOTH | AR15: =IF(OR($R15<>"",$AF15<>""),"OVERRIDE","") | AS15: {=IF(OR($B15="",$C15<>CurrentWeek),"",ROUND(25*MIN(1,IF($W15="",0,$W15)/5)+20*IF($AP15="READY",1,0)+20*IF($AO15="",1,0)+15*IF(IFERROR(INDEX(MktStale,MATCH($B15,MktGameID,0)),"x")="OK",1,0)+10*MAX(0,1-ABS(IF($P15="",0,$P15))/AdjCap)+10*IF(AND($Z15<>"",$AM15<>""),1,0),0))} -> 30 | AT15: =IF($AS15="","",RANK($AS15,$AS$5:$AS$304,0)) -> 13
A16: 12 | B16: {=IFERROR(INDEX(SchedZone,MATCH($A16,SchedSeq,0),MAP!$B$6),"")} -> 2026_01_MIA_LV | C16: {=IF($B16="","",INDEX(SchedZone,MATCH($A16,SchedSeq,0),MAP!$B$4))} -> 1 | D16: {=IF($B16="","",INDEX(SchedZone,MATCH($A16,SchedSeq,0),MAP!$B$7))} -> 46278 | E16: {=IF($B16="","",IF(COUNTIF(Teams,INDEX(SchedZone,MATCH($A16,SchedSeq,0),MAP!$B$10))>0,INDEX(SchedZone,MATCH($A16,SchedSeq,0),MAP!$B$10),IFERROR(INDEX(LISTS!$D$2:$D$12,MATCH(INDEX(SchedZone,MATCH($A16,SchedSeq,0),MAP!$B$10),LISTS!$C$2:$C$12,0)),"⚠ "&INDEX(SchedZone,MATCH($A16,SchedSeq,0),MAP!$B$10))))} -> MIA | F16: {=IF($B16="","",IF(COUNTIF(Teams,INDEX(SchedZone,MATCH($A16,SchedSeq,0),MAP!$B$12))>0,INDEX(SchedZone,MATCH($A16,SchedSeq,0),MAP!$B$12),IFERROR(INDEX(LISTS!$D$2:$D$12,MATCH(INDEX(SchedZone,MATCH($A16,SchedSeq,0),MAP!$B$12),LISTS!$C$2:$C$12,0)),"⚠ "&INDEX(SchedZone,MATCH($A16,SchedSeq,0),MAP!$B$12))))} -> LV | G16: {=IF($B16="","",IF(INDEX(SchedZone,MATCH($A16,SchedSeq,0),MAP!$B$14)="Neutral","Y",""))} | H16: {=IF($B16="","",INDEX(SchedZone,MATCH($A16,SchedSeq,0),MAP!$B$17))} -> dome | I16: =IF(OR($B16="",$C16<>CurrentWeek),"",COUNTIF($C$5:$C16,CurrentWeek)) -> 12 | J16: {=IF($B16="","",IFERROR(INDEX(RatEff,MATCH($E16,RatTeams,0)),"⚠ TEAM NOT FOUND"))} -> -2.64 | K16: {=IF($B16="","",IFERROR(INDEX(RatEff,MATCH($F16,RatTeams,0)),"⚠ TEAM NOT FOUND"))} -> -3.52 | L16: =IF(OR($B16="",NOT(ISNUMBER($J16)),NOT(ISNUMBER($K16))),"",$K16-$J16) -> -0.88 | M16: {=IF($B16="","",IF($G16="Y",NeutralHFA,IFERROR(INDEX(HFAexcVal,MATCH($F16,HFAexcTeam,0)),HFA_Base)))} -> 1.6 | N16: {=IF($B16="","",IFERROR(INDEX(QBSpreadEff,MATCH($F16,QBTeams,0)),0)-IFERROR(INDEX(QBSpreadEff,MATCH($E16,QBTeams,0)),0))} -> 0 | O16: {=IF($B16="","",IFERROR(MEDIAN(-RestCapPts,RestCapPts,RestPerDay*(INDEX(SchedZone,MATCH($A16,SchedSeq,0),MAP!$B$16)-INDEX(SchedZone,MATCH($A16,SchedSeq,0),MAP!$B$15))),0))} -> 0 | P16: =IF($B16="","",SUMIFS(AdjSpread,AdjGameID,$B16,AdjTeam,$F16,AdjActive,1)-SUMIFS(AdjSpread,AdjGameID,$B16,AdjTeam,$E16,AdjActive,1)) -> 0 | Q16: =IF($L16="","",ROUND($L16+$M16+$N16+$O16+$P16,2)) -> 0.72 | S16: =IF(AND($R16="",$Q16=""),"",IF($R16<>"",$R16,$Q16)) -> 0.72 | T16: =IF($S16="","",IF(ABS($S16)<0.05,"PK",IF($S16>0,$F16&" "&TEXT(-$S16,"+0.0;-0.0"),$E16&" "&TEXT($S16,"+0.0;-0.0")))) -> LV -0.7 | U16: {=IF($B16="","",IFERROR(INDEX(MktHomeSpread,MATCH($B16,MktGameID,0)),""))} | V16: =IF(OR($S16="",$U16=""),"",ROUND($S16+$U16,2)) | W16: =IF($V16="","",ABS($V16)) | X16: =IF($V16="","",IF($V16>0,$F16&" "&TEXT($U16,"+0.0;-0.0;""PK"""),$E16&" "&TEXT(-$U16,"+0.0;-0.0;""PK"""))) | Y16: {=IF($B16="","",IF((IF(AND(IFERROR(INDEX(RatGP,MATCH($E16,RatTeams,0)),0)>=MinGamesTrust,IFERROR(INDEX(RatGP,MATCH($F16,RatTeams,0)),0)>=MinGamesTrust),1,0)+IF($AP16="READY",1,0)+IF(AND(IFERROR(INDEX(RatMode,MATCH($E16,RatTeams,0)),"")="ENHANCED",IFERROR(INDEX(RatMode,MATCH($F16,RatTeams,0)),"")="ENHANCED"),1,0)+IF($AO16="",1,0)+IF(IFERROR(INDEX(MktStale,MATCH($B16,MktGameID,0)),"")<>"STALE",1,0))>=5,"High",IF((IF(AND(IFERROR(INDEX(RatGP,MATCH($E16,RatTeams,0)),0)>=MinGamesTrust,IFERROR(INDEX(RatGP,MATCH($F16,RatTeams,0)),0)>=MinGamesTrust),1,0)+IF($AP16="READY",1,0)+IF(AND(IFERROR(INDEX(RatMode,MATCH($E16,RatTeams,0)),"")="ENHANCED",IFERROR(INDEX(RatMode,MATCH($F16,RatTeams,0)),"")="ENHANCED"),1,0)+IF($AO16="",1,0)+IF(IFERROR(INDEX(MktStale,MATCH($B16,MktGameID,0)),"")<>"STALE",1,0))>=4,"Medium","Low")))} -> Low | Z16: =IF(OR($B16="",$V16=""),"",IF(LEFT($AP16,7)="BLOCKED","",IF(AND($W16>=BetATS,$Y16<>"Low"),IF(AND(EnableBetLabels="Y",$Y16="High",$AP16="READY",ABS(IF($P16="",0,$P16))<=AdjCap),"BET","STRONG INVESTIGATE"),IF($W16>=InvATS,"INVESTIGATE",IF(AND($W16>=LeanATS,$Y16<>"Low"),"LEAN",""))))) | AA16: {=IF($B16="","",IFERROR(ROUND(((1-TotRegress)*0.5*(INDEX(CalcOffPl,MATCH($E16,CalcTeams,0))+INDEX(CalcDefPl,MATCH($F16,CalcTeams,0)))+TotRegress*LeaguePlays)*(INDEX(CalcOffAdj,MATCH($E16,CalcTeams,0))+INDEX(CalcDefAdj,MATCH($F16,CalcTeams,0))-LeaguePPP)+DstPts,2),""))} -> 0 | AB16: {=IF($B16="","",IFERROR(ROUND(((1-TotRegress)*0.5*(INDEX(CalcOffPl,MATCH($F16,CalcTeams,0))+INDEX(CalcDefPl,MATCH($E16,CalcTeams,0)))+TotRegress*LeaguePlays)*(INDEX(CalcOffAdj,MATCH($F16,CalcTeams,0))+INDEX(CalcDefAdj,MATCH($E16,CalcTeams,0))-LeaguePPP)+DstPts,2),""))} -> 0 | AC16: {=IF($B16="","",IFERROR(INDEX(QBTotEff,MATCH($F16,QBTeams,0)),0)+IFERROR(INDEX(QBTotEff,MATCH($E16,QBTeams,0)),0))} -> 0 | AD16: =IF($B16="","",SUMIFS(AdjTot,AdjGameID,$B16,AdjActive,1)) -> 0 | AE16: =IF(OR($AA16="",$AB16=""),"",ROUND($AA16+$AB16+$AC16+$AD16,2)) -> 0 | AG16: =IF(AND($AF16="",$AE16=""),"",IF($AF16<>"",$AF16,$AE16)) -> 0 | AH16: {=IF($B16="","",IFERROR(INDEX(MktTotal,MATCH($B16,MktGameID,0)),""))} | AI16: =IF(OR($AG16="",$AH16=""),"",ROUND($AG16-$AH16,2)) | AJ16: =IF($AI16="","",ABS($AI16)) | AK16: =IF($AI16="","",IF($AI16>0.05,"OVER",IF($AI16<-0.05,"UNDER","—"))) | AL16: {=IF($B16="","",IF((IF(AND(IFERROR(INDEX(RatGP,MATCH($E16,RatTeams,0)),0)>=MinGamesTrust,IFERROR(INDEX(RatGP,MATCH($F16,RatTeams,0)),0)>=MinGamesTrust),1,0)+IF($AP16="READY",1,0)+IF($AO16="",1,0)+IF(IFERROR(INDEX(MktStale,MATCH($B16,MktGameID,0)),"")<>"STALE",1,0)+IF(ABS(IF($AD16="",0,$AD16))<=AdjCap,1,0))>=5,"High",IF((IF(AND(IFERROR(INDEX(RatGP,MATCH($E16,RatTeams,0)),0)>=MinGamesTrust,IFERROR(INDEX(RatGP,MATCH($F16,RatTeams,0)),0)>=MinGamesTrust),1,0)+IF($AP16="READY",1,0)+IF($AO16="",1,0)+IF(IFERROR(INDEX(MktStale,MATCH($B16,MktGameID,0)),"")<>"STALE",1,0)+IF(ABS(IF($AD16="",0,$AD16))<=AdjCap,1,0))>=4,"Medium","Low")))} -> Medium | AM16: =IF(OR($B16="",$AI16=""),"",IF(LEFT($AP16,7)="BLOCKED","",IF(AND($AJ16>=BetTot,$AL16<>"Low"),IF(AND(EnableBetLabels="Y",$AL16="High",$AP16="READY"),"BET ","STRONG INVESTIGATE ")&$AK16,IF($AJ16>=InvTot,"INVESTIGATE "&$AK16,IF(AND($AJ16>=LeanTot,$AL16<>"Low"),"LEAN "&$AK16,""))))) | AN16: =IF($AG16="","","BET OVER at ≤ "&TEXT($AG16-BetTot,"0.0")&" | BET UNDER at ≥ "&TEXT($AG16+BetTot,"0.0")) -> BET OVER at ≤ -3.0 | BET UNDER at ≥ 3.0 | AO16: {=IF($B16="","",IF(OR(IFERROR(INDEX(QBFlag,MATCH($F16,QBTeams,0)),1)=1,IFERROR(INDEX(QBFlag,MATCH($E16,QBTeams,0)),1)=1),"QB UNCERTAIN",""))} | AP16: {=IF($B16="","",IFERROR(INDEX(DQStatus,MATCH($B16,DQGameID,0)),"BLOCKED — DQ ROW NOT FOUND"))} -> READY | AQ16: {=IF($B16="","",IF(LEFT($AP16,7)="BLOCKED",IF($AP16="BLOCKED","BLOCKED — see DATA QUALITY",$AP16),IF(AND($U16="",$AH16=""),"PENDING BOTH",IF($U16="","PENDING SPREAD",IF($AH16="","PENDING TOTAL",IF(IFERROR(INDEX(MktStale,MATCH($B16,MktGameID,0)),"")="STALE","STALE LINE",IF($AO16<>"",$AO16,IF(OR(NOT(ISNUMBER($J16)),NOT(ISNUMBER($K16))),"DATA INCOMPLETE","READY"))))))))} -> PENDING BOTH | AR16: =IF(OR($R16<>"",$AF16<>""),"OVERRIDE","") | AS16: {=IF(OR($B16="",$C16<>CurrentWeek),"",ROUND(25*MIN(1,IF($W16="",0,$W16)/5)+20*IF($AP16="READY",1,0)+20*IF($AO16="",1,0)+15*IF(IFERROR(INDEX(MktStale,MATCH($B16,MktGameID,0)),"x")="OK",1,0)+10*MAX(0,1-ABS(IF($P16="",0,$P16))/AdjCap)+10*IF(AND($Z16<>"",$AM16<>""),1,0),0))} -> 50 | AT16: =IF($AS16="","",RANK($AS16,$AS$5:$AS$304,0)) -> 1
... A304: 300 | B304: {=IFERROR(INDEX(SchedZone,MATCH($A304,SchedSeq,0),MAP!$B$6),"")} | C304: {=IF($B304="","",INDEX(SchedZone,MATCH($A304,SchedSeq,0),MAP!$B$4))} | D304: {=IF($B304="","",INDEX(SchedZone,MATCH($A304,SchedSeq,0),MAP!$B$7))} | E304: {=IF($B304="","",IF(COUNTIF(Teams,INDEX(SchedZone,MATCH($A304,SchedSeq,0),MAP!$B$10))>0,INDEX(SchedZone,MATCH($A304,SchedSeq,0),MAP!$B$10),IFERROR(INDEX(LISTS!$D$2:$D$12,MATCH(INDEX(SchedZone,MATCH($A304,SchedSeq,0),MAP!$B$10),LISTS!$C$2:$C$12,0)),"⚠ "&INDEX(SchedZone,MATCH($A304,SchedSeq,0),MAP!$B$10))))} | F304: {=IF($B304="","",IF(COUNTIF(Teams,INDEX(SchedZone,MATCH($A304,SchedSeq,0),MAP!$B$12))>0,INDEX(SchedZone,MATCH($A304,SchedSeq,0),MAP!$B$12),IFERROR(INDEX(LISTS!$D$2:$D$12,MATCH(INDEX(SchedZone,MATCH($A304,SchedSeq,0),MAP!$B$12),LISTS!$C$2:$C$12,0)),"⚠ "&INDEX(SchedZone,MATCH($A304,SchedSeq,0),MAP!$B$12))))} | G304: {=IF($B304="","",IF(INDEX(SchedZone,MATCH($A304,SchedSeq,0),MAP!$B$14)="Neutral","Y",""))} | H304: {=IF($B304="","",INDEX(SchedZone,MATCH($A304,SchedSeq,0),MAP!$B$17))} | I304: =IF(OR($B304="",$C304<>CurrentWeek),"",COUNTIF($C$5:$C304,CurrentWeek)) | J304: {=IF($B304="","",IFERROR(INDEX(RatEff,MATCH($E304,RatTeams,0)),"⚠ TEAM NOT FOUND"))} | K304: {=IF($B304="","",IFERROR(INDEX(RatEff,MATCH($F304,RatTeams,0)),"⚠ TEAM NOT FOUND"))} | L304: =IF(OR($B304="",NOT(ISNUMBER($J304)),NOT(ISNUMBER($K304))),"",$K304-$J304) | M304: {=IF($B304="","",IF($G304="Y",NeutralHFA,IFERROR(INDEX(HFAexcVal,MATCH($F304,HFAexcTeam,0)),HFA_Base)))} | N304: {=IF($B304="","",IFERROR(INDEX(QBSpreadEff,MATCH($F304,QBTeams,0)),0)-IFERROR(INDEX(QBSpreadEff,MATCH($E304,QBTeams,0)),0))} | O304: {=IF($B304="","",IFERROR(MEDIAN(-RestCapPts,RestCapPts,RestPerDay*(INDEX(SchedZone,MATCH($A304,SchedSeq,0),MAP!$B$16)-INDEX(SchedZone,MATCH($A304,SchedSeq,0),MAP!$B$15))),0))} | P304: =IF($B304="","",SUMIFS(AdjSpread,AdjGameID,$B304,AdjTeam,$F304,AdjActive,1)-SUMIFS(AdjSpread,AdjGameID,$B304,AdjTeam,$E304,AdjActive,1)) | Q304: =IF($L304="","",ROUND($L304+$M304+$N304+$O304+$P304,2)) | S304: =IF(AND($R304="",$Q304=""),"",IF($R304<>"",$R304,$Q304)) | T304: =IF($S304="","",IF(ABS($S304)<0.05,"PK",IF($S304>0,$F304&" "&TEXT(-$S304,"+0.0;-0.0"),$E304&" "&TEXT($S304,"+0.0;-0.0")))) | U304: {=IF($B304="","",IFERROR(INDEX(MktHomeSpread,MATCH($B304,MktGameID,0)),""))} | V304: =IF(OR($S304="",$U304=""),"",ROUND($S304+$U304,2)) | W304: =IF($V304="","",ABS($V304)) | X304: =IF($V304="","",IF($V304>0,$F304&" "&TEXT($U304,"+0.0;-0.0;""PK"""),$E304&" "&TEXT(-$U304,"+0.0;-0.0;""PK"""))) | Y304: {=IF($B304="","",IF((IF(AND(IFERROR(INDEX(RatGP,MATCH($E304,RatTeams,0)),0)>=MinGamesTrust,IFERROR(INDEX(RatGP,MATCH($F304,RatTeams,0)),0)>=MinGamesTrust),1,0)+IF($AP304="READY",1,0)+IF(AND(IFERROR(INDEX(RatMode,MATCH($E304,RatTeams,0)),"")="ENHANCED",IFERROR(INDEX(RatMode,MATCH($F304,RatTeams,0)),"")="ENHANCED"),1,0)+IF($AO304="",1,0)+IF(IFERROR(INDEX(MktStale,MATCH($B304,MktGameID,0)),"")<>"STALE",1,0))>=5,"High",IF((IF(AND(IFERROR(INDEX(RatGP,MATCH($E304,RatTeams,0)),0)>=MinGamesTrust,IFERROR(INDEX(RatGP,MATCH($F304,RatTeams,0)),0)>=MinGamesTrust),1,0)+IF($AP304="READY",1,0)+IF(AND(IFERROR(INDEX(RatMode,MATCH($E304,RatTeams,0)),"")="ENHANCED",IFERROR(INDEX(RatMode,MATCH($F304,RatTeams,0)),"")="ENHANCED"),1,0)+IF($AO304="",1,0)+IF(IFERROR(INDEX(MktStale,MATCH($B304,MktGameID,0)),"")<>"STALE",1,0))>=4,"Medium","Low")))} | Z304: =IF(OR($B304="",$V304=""),"",IF(LEFT($AP304,7)="BLOCKED","",IF(AND($W304>=BetATS,$Y304<>"Low"),IF(AND(EnableBetLabels="Y",$Y304="High",$AP304="READY",ABS(IF($P304="",0,$P304))<=AdjCap),"BET","STRONG INVESTIGATE"),IF($W304>=InvATS,"INVESTIGATE",IF(AND($W304>=LeanATS,$Y304<>"Low"),"LEAN",""))))) | AA304: {=IF($B304="","",IFERROR(ROUND(((1-TotRegress)*0.5*(INDEX(CalcOffPl,MATCH($E304,CalcTeams,0))+INDEX(CalcDefPl,MATCH($F304,CalcTeams,0)))+TotRegress*LeaguePlays)*(INDEX(CalcOffAdj,MATCH($E304,CalcTeams,0))+INDEX(CalcDefAdj,MATCH($F304,CalcTeams,0))-LeaguePPP)+DstPts,2),""))} | AB304: {=IF($B304="","",IFERROR(ROUND(((1-TotRegress)*0.5*(INDEX(CalcOffPl,MATCH($F304,CalcTeams,0))+INDEX(CalcDefPl,MATCH($E304,CalcTeams,0)))+TotRegress*LeaguePlays)*(INDEX(CalcOffAdj,MATCH($F304,CalcTeams,0))+INDEX(CalcDefAdj,MATCH($E304,CalcTeams,0))-LeaguePPP)+DstPts,2),""))} | AC304: {=IF($B304="","",IFERROR(INDEX(QBTotEff,MATCH($F304,QBTeams,0)),0)+IFERROR(INDEX(QBTotEff,MATCH($E304,QBTeams,0)),0))} | AD304: =IF($B304="","",SUMIFS(AdjTot,AdjGameID,$B304,AdjActive,1)) | AE304: =IF(OR($AA304="",$AB304=""),"",ROUND($AA304+$AB304+$AC304+$AD304,2)) | AG304: =IF(AND($AF304="",$AE304=""),"",IF($AF304<>"",$AF304,$AE304)) | AH304: {=IF($B304="","",IFERROR(INDEX(MktTotal,MATCH($B304,MktGameID,0)),""))} | AI304: =IF(OR($AG304="",$AH304=""),"",ROUND($AG304-$AH304,2)) | AJ304: =IF($AI304="","",ABS($AI304)) | AK304: =IF($AI304="","",IF($AI304>0.05,"OVER",IF($AI304<-0.05,"UNDER","—"))) | AL304: {=IF($B304="","",IF((IF(AND(IFERROR(INDEX(RatGP,MATCH($E304,RatTeams,0)),0)>=MinGamesTrust,IFERROR(INDEX(RatGP,MATCH($F304,RatTeams,0)),0)>=MinGamesTrust),1,0)+IF($AP304="READY",1,0)+IF($AO304="",1,0)+IF(IFERROR(INDEX(MktStale,MATCH($B304,MktGameID,0)),"")<>"STALE",1,0)+IF(ABS(IF($AD304="",0,$AD304))<=AdjCap,1,0))>=5,"High",IF((IF(AND(IFERROR(INDEX(RatGP,MATCH($E304,RatTeams,0)),0)>=MinGamesTrust,IFERROR(INDEX(RatGP,MATCH($F304,RatTeams,0)),0)>=MinGamesTrust),1,0)+IF($AP304="READY",1,0)+IF($AO304="",1,0)+IF(IFERROR(INDEX(MktStale,MATCH($B304,MktGameID,0)),"")<>"STALE",1,0)+IF(ABS(IF($AD304="",0,$AD304))<=AdjCap,1,0))>=4,"Medium","Low")))} | AM304: =IF(OR($B304="",$AI304=""),"",IF(LEFT($AP304,7)="BLOCKED","",IF(AND($AJ304>=BetTot,$AL304<>"Low"),IF(AND(EnableBetLabels="Y",$AL304="High",$AP304="READY"),"BET ","STRONG INVESTIGATE ")&$AK304,IF($AJ304>=InvTot,"INVESTIGATE "&$AK304,IF(AND($AJ304>=LeanTot,$AL304<>"Low"),"LEAN "&$AK304,""))))) | AN304: =IF($AG304="","","BET OVER at ≤ "&TEXT($AG304-BetTot,"0.0")&" | BET UNDER at ≥ "&TEXT($AG304+BetTot,"0.0")) | AO304: {=IF($B304="","",IF(OR(IFERROR(INDEX(QBFlag,MATCH($F304,QBTeams,0)),1)=1,IFERROR(INDEX(QBFlag,MATCH($E304,QBTeams,0)),1)=1),"QB UNCERTAIN",""))} | AP304: {=IF($B304="","",IFERROR(INDEX(DQStatus,MATCH($B304,DQGameID,0)),"BLOCKED — DQ ROW NOT FOUND"))} | AQ304: {=IF($B304="","",IF(LEFT($AP304,7)="BLOCKED",IF($AP304="BLOCKED","BLOCKED — see DATA QUALITY",$AP304),IF(AND($U304="",$AH304=""),"PENDING BOTH",IF($U304="","PENDING SPREAD",IF($AH304="","PENDING TOTAL",IF(IFERROR(INDEX(MktStale,MATCH($B304,MktGameID,0)),"")="STALE","STALE LINE",IF($AO304<>"",$AO304,IF(OR(NOT(ISNUMBER($J304)),NOT(ISNUMBER($K304))),"DATA INCOMPLETE","READY"))))))))} | AR304: =IF(OR($R304<>"",$AF304<>""),"OVERRIDE","") | AS304: {=IF(OR($B304="",$C304<>CurrentWeek),"",ROUND(25*MIN(1,IF($W304="",0,$W304)/5)+20*IF($AP304="READY",1,0)+20*IF($AO304="",1,0)+15*IF(IFERROR(INDEX(MktStale,MATCH($B304,MktGameID,0)),"x")="OK",1,0)+10*MAX(0,1-ABS(IF($P304="",0,$P304))/AdjCap)+10*IF(AND($Z304<>"",$AM304<>""),1,0),0))} | AT304: =IF($AS304="","",RANK($AS304,$AS$5:$AS$304,0))

Sheet MARKET LINES
A1: MARKET LINES — Novig is your primary entry; OddsLogic columns are reference-only
A2: Entry pattern (same as your WNBA sheet): pick the FAVORITE from the dropdown, enter the spread as a POSITIVE number, enter the total. The sheet converts signs internally and the Input Check column flags anything inconsistent. Enter the line date each time — staleness is measured against SETTINGS As-of date. SAMPLE ROWS: week-18 2025 rows are prefilled from nflverse HISTORICAL reference lines (source semantics unverified) purely to demonstrate the pipeline — replace with Novig lines for live use.
A4: Seq | B4: GameID | C4: Week | D4: Date | E4: Away | F4: Home | G4: Favorite (dropdown) | H4: Spread (+) | I4: Total | J4: Open spread | K4: Open total | L4: OddsLogic spread (ref) | M4: OddsLogic total (ref) | N4: Source | O4: Line date | P4: Notes | Q4: Market home spread (auto) | R4: Input check | S4: Stale?
A5: 1 | B5: {=IFERROR(INDEX(SchedZone,MATCH($A5,SchedSeq,0),MAP!$B$6),"")} -> 2026_01_NE_SEA | C5: {=IF($B5="","",INDEX(SchedZone,MATCH($A5,SchedSeq,0),MAP!$B$4))} -> 1 | D5: {=IF($B5="","",INDEX(SchedZone,MATCH($A5,SchedSeq,0),MAP!$B$7))} -> 46274 | E5: {=IF($B5="","",IF(COUNTIF(Teams,INDEX(SchedZone,MATCH($A5,SchedSeq,0),MAP!$B$10))>0,INDEX(SchedZone,MATCH($A5,SchedSeq,0),MAP!$B$10),IFERROR(INDEX(LISTS!$D$2:$D$12,MATCH(INDEX(SchedZone,MATCH($A5,SchedSeq,0),MAP!$B$10),LISTS!$C$2:$C$12,0)),"⚠ "&INDEX(SchedZone,MATCH($A5,SchedSeq,0),MAP!$B$10))))} -> NE | F5: {=IF($B5="","",IF(COUNTIF(Teams,INDEX(SchedZone,MATCH($A5,SchedSeq,0),MAP!$B$12))>0,INDEX(SchedZone,MATCH($A5,SchedSeq,0),MAP!$B$12),IFERROR(INDEX(LISTS!$D$2:$D$12,MATCH(INDEX(SchedZone,MATCH($A5,SchedSeq,0),MAP!$B$12),LISTS!$C$2:$C$12,0)),"⚠ "&INDEX(SchedZone,MATCH($A5,SchedSeq,0),MAP!$B$12))))} -> SEA | Q5: =IF(OR($B5="",$G5="",$H5=""),"",IF($G5="Pick",0,IF($G5=$F5,-$H5,IF($G5=$E5,$H5,"")))) | R5: =IF($B5="","",IF(AND($G5="",$H5="",$I5=""),"",IF(AND($G5="",$H5<>""),"⚠ ADD FAVORITE",IF(AND($G5<>"",$G5<>"Pick",$G5<>$E5,$G5<>$F5),"⚠ FAVORITE NOT IN GAME",IF(AND($G5<>"",$H5=""),"⚠ SPREAD MISSING",IF(AND($H5<>"",NOT(ISNUMBER($H5))),"⚠ SPREAD NOT A NUMBER",IF(AND(ISNUMBER($H5),$H5<0),"⚠ ENTER SPREAD AS POSITIVE","OK"))))))) | S5: =IF(OR($B5="",$O5=""),"",IF(AsOfDate-$O5>StaleDays,"STALE","OK"))
A6: 2 | B6: {=IFERROR(INDEX(SchedZone,MATCH($A6,SchedSeq,0),MAP!$B$6),"")} -> 2026_01_SF_LA | C6: {=IF($B6="","",INDEX(SchedZone,MATCH($A6,SchedSeq,0),MAP!$B$4))} -> 1 | D6: {=IF($B6="","",INDEX(SchedZone,MATCH($A6,SchedSeq,0),MAP!$B$7))} -> 46275 | E6: {=IF($B6="","",IF(COUNTIF(Teams,INDEX(SchedZone,MATCH($A6,SchedSeq,0),MAP!$B$10))>0,INDEX(SchedZone,MATCH($A6,SchedSeq,0),MAP!$B$10),IFERROR(INDEX(LISTS!$D$2:$D$12,MATCH(INDEX(SchedZone,MATCH($A6,SchedSeq,0),MAP!$B$10),LISTS!$C$2:$C$12,0)),"⚠ "&INDEX(SchedZone,MATCH($A6,SchedSeq,0),MAP!$B$10))))} -> SF | F6: {=IF($B6="","",IF(COUNTIF(Teams,INDEX(SchedZone,MATCH($A6,SchedSeq,0),MAP!$B$12))>0,INDEX(SchedZone,MATCH($A6,SchedSeq,0),MAP!$B$12),IFERROR(INDEX(LISTS!$D$2:$D$12,MATCH(INDEX(SchedZone,MATCH($A6,SchedSeq,0),MAP!$B$12),LISTS!$C$2:$C$12,0)),"⚠ "&INDEX(SchedZone,MATCH($A6,SchedSeq,0),MAP!$B$12))))} -> LA | Q6: =IF(OR($B6="",$G6="",$H6=""),"",IF($G6="Pick",0,IF($G6=$F6,-$H6,IF($G6=$E6,$H6,"")))) | R6: =IF($B6="","",IF(AND($G6="",$H6="",$I6=""),"",IF(AND($G6="",$H6<>""),"⚠ ADD FAVORITE",IF(AND($G6<>"",$G6<>"Pick",$G6<>$E6,$G6<>$F6),"⚠ FAVORITE NOT IN GAME",IF(AND($G6<>"",$H6=""),"⚠ SPREAD MISSING",IF(AND($H6<>"",NOT(ISNUMBER($H6))),"⚠ SPREAD NOT A NUMBER",IF(AND(ISNUMBER($H6),$H6<0),"⚠ ENTER SPREAD AS POSITIVE","OK"))))))) | S6: =IF(OR($B6="",$O6=""),"",IF(AsOfDate-$O6>StaleDays,"STALE","OK"))
A7: 3 | B7: {=IFERROR(INDEX(SchedZone,MATCH($A7,SchedSeq,0),MAP!$B$6),"")} -> 2026_01_CHI_CAR | C7: {=IF($B7="","",INDEX(SchedZone,MATCH($A7,SchedSeq,0),MAP!$B$4))} -> 1 | D7: {=IF($B7="","",INDEX(SchedZone,MATCH($A7,SchedSeq,0),MAP!$B$7))} -> 46278 | E7: {=IF($B7="","",IF(COUNTIF(Teams,INDEX(SchedZone,MATCH($A7,SchedSeq,0),MAP!$B$10))>0,INDEX(SchedZone,MATCH($A7,SchedSeq,0),MAP!$B$10),IFERROR(INDEX(LISTS!$D$2:$D$12,MATCH(INDEX(SchedZone,MATCH($A7,SchedSeq,0),MAP!$B$10),LISTS!$C$2:$C$12,0)),"⚠ "&INDEX(SchedZone,MATCH($A7,SchedSeq,0),MAP!$B$10))))} -> CHI | F7: {=IF($B7="","",IF(COUNTIF(Teams,INDEX(SchedZone,MATCH($A7,SchedSeq,0),MAP!$B$12))>0,INDEX(SchedZone,MATCH($A7,SchedSeq,0),MAP!$B$12),IFERROR(INDEX(LISTS!$D$2:$D$12,MATCH(INDEX(SchedZone,MATCH($A7,SchedSeq,0),MAP!$B$12),LISTS!$C$2:$C$12,0)),"⚠ "&INDEX(SchedZone,MATCH($A7,SchedSeq,0),MAP!$B$12))))} -> CAR | Q7: =IF(OR($B7="",$G7="",$H7=""),"",IF($G7="Pick",0,IF($G7=$F7,-$H7,IF($G7=$E7,$H7,"")))) | R7: =IF($B7="","",IF(AND($G7="",$H7="",$I7=""),"",IF(AND($G7="",$H7<>""),"⚠ ADD FAVORITE",IF(AND($G7<>"",$G7<>"Pick",$G7<>$E7,$G7<>$F7),"⚠ FAVORITE NOT IN GAME",IF(AND($G7<>"",$H7=""),"⚠ SPREAD MISSING",IF(AND($H7<>"",NOT(ISNUMBER($H7))),"⚠ SPREAD NOT A NUMBER",IF(AND(ISNUMBER($H7),$H7<0),"⚠ ENTER SPREAD AS POSITIVE","OK"))))))) | S7: =IF(OR($B7="",$O7=""),"",IF(AsOfDate-$O7>StaleDays,"STALE","OK"))
A8: 4 | B8: {=IFERROR(INDEX(SchedZone,MATCH($A8,SchedSeq,0),MAP!$B$6),"")} -> 2026_01_TB_CIN | C8: {=IF($B8="","",INDEX(SchedZone,MATCH($A8,SchedSeq,0),MAP!$B$4))} -> 1 | D8: {=IF($B8="","",INDEX(SchedZone,MATCH($A8,SchedSeq,0),MAP!$B$7))} -> 46278 | E8: {=IF($B8="","",IF(COUNTIF(Teams,INDEX(SchedZone,MATCH($A8,SchedSeq,0),MAP!$B$10))>0,INDEX(SchedZone,MATCH($A8,SchedSeq,0),MAP!$B$10),IFERROR(INDEX(LISTS!$D$2:$D$12,MATCH(INDEX(SchedZone,MATCH($A8,SchedSeq,0),MAP!$B$10),LISTS!$C$2:$C$12,0)),"⚠ "&INDEX(SchedZone,MATCH($A8,SchedSeq,0),MAP!$B$10))))} -> TB | F8: {=IF($B8="","",IF(COUNTIF(Teams,INDEX(SchedZone,MATCH($A8,SchedSeq,0),MAP!$B$12))>0,INDEX(SchedZone,MATCH($A8,SchedSeq,0),MAP!$B$12),IFERROR(INDEX(LISTS!$D$2:$D$12,MATCH(INDEX(SchedZone,MATCH($A8,SchedSeq,0),MAP!$B$12),LISTS!$C$2:$C$12,0)),"⚠ "&INDEX(SchedZone,MATCH($A8,SchedSeq,0),MAP!$B$12))))} -> CIN | Q8: =IF(OR($B8="",$G8="",$H8=""),"",IF($G8="Pick",0,IF($G8=$F8,-$H8,IF($G8=$E8,$H8,"")))) | R8: =IF($B8="","",IF(AND($G8="",$H8="",$I8=""),"",IF(AND($G8="",$H8<>""),"⚠ ADD FAVORITE",IF(AND($G8<>"",$G8<>"Pick",$G8<>$E8,$G8<>$F8),"⚠ FAVORITE NOT IN GAME",IF(AND($G8<>"",$H8=""),"⚠ SPREAD MISSING",IF(AND($H8<>"",NOT(ISNUMBER($H8))),"⚠ SPREAD NOT A NUMBER",IF(AND(ISNUMBER($H8),$H8<0),"⚠ ENTER SPREAD AS POSITIVE","OK"))))))) | S8: =IF(OR($B8="",$O8=""),"",IF(AsOfDate-$O8>StaleDays,"STALE","OK"))
A9: 5 | B9: {=IFERROR(INDEX(SchedZone,MATCH($A9,SchedSeq,0),MAP!$B$6),"")} -> 2026_01_NO_DET | C9: {=IF($B9="","",INDEX(SchedZone,MATCH($A9,SchedSeq,0),MAP!$B$4))} -> 1 | D9: {=IF($B9="","",INDEX(SchedZone,MATCH($A9,SchedSeq,0),MAP!$B$7))} -> 46278 | E9: {=IF($B9="","",IF(COUNTIF(Teams,INDEX(SchedZone,MATCH($A9,SchedSeq,0),MAP!$B$10))>0,INDEX(SchedZone,MATCH($A9,SchedSeq,0),MAP!$B$10),IFERROR(INDEX(LISTS!$D$2:$D$12,MATCH(INDEX(SchedZone,MATCH($A9,SchedSeq,0),MAP!$B$10),LISTS!$C$2:$C$12,0)),"⚠ "&INDEX(SchedZone,MATCH($A9,SchedSeq,0),MAP!$B$10))))} -> NO | F9: {=IF($B9="","",IF(COUNTIF(Teams,INDEX(SchedZone,MATCH($A9,SchedSeq,0),MAP!$B$12))>0,INDEX(SchedZone,MATCH($A9,SchedSeq,0),MAP!$B$12),IFERROR(INDEX(LISTS!$D$2:$D$12,MATCH(INDEX(SchedZone,MATCH($A9,SchedSeq,0),MAP!$B$12),LISTS!$C$2:$C$12,0)),"⚠ "&INDEX(SchedZone,MATCH($A9,SchedSeq,0),MAP!$B$12))))} -> DET | Q9: =IF(OR($B9="",$G9="",$H9=""),"",IF($G9="Pick",0,IF($G9=$F9,-$H9,IF($G9=$E9,$H9,"")))) | R9: =IF($B9="","",IF(AND($G9="",$H9="",$I9=""),"",IF(AND($G9="",$H9<>""),"⚠ ADD FAVORITE",IF(AND($G9<>"",$G9<>"Pick",$G9<>$E9,$G9<>$F9),"⚠ FAVORITE NOT IN GAME",IF(AND($G9<>"",$H9=""),"⚠ SPREAD MISSING",IF(AND($H9<>"",NOT(ISNUMBER($H9))),"⚠ SPREAD NOT A NUMBER",IF(AND(ISNUMBER($H9),$H9<0),"⚠ ENTER SPREAD AS POSITIVE","OK"))))))) | S9: =IF(OR($B9="",$O9=""),"",IF(AsOfDate-$O9>StaleDays,"STALE","OK"))
A10: 6 | B10: {=IFERROR(INDEX(SchedZone,MATCH($A10,SchedSeq,0),MAP!$B$6),"")} -> 2026_01_BUF_HOU | C10: {=IF($B10="","",INDEX(SchedZone,MATCH($A10,SchedSeq,0),MAP!$B$4))} -> 1 | D10: {=IF($B10="","",INDEX(SchedZone,MATCH($A10,SchedSeq,0),MAP!$B$7))} -> 46278 | E10: {=IF($B10="","",IF(COUNTIF(Teams,INDEX(SchedZone,MATCH($A10,SchedSeq,0),MAP!$B$10))>0,INDEX(SchedZone,MATCH($A10,SchedSeq,0),MAP!$B$10),IFERROR(INDEX(LISTS!$D$2:$D$12,MATCH(INDEX(SchedZone,MATCH($A10,SchedSeq,0),MAP!$B$10),LISTS!$C$2:$C$12,0)),"⚠ "&INDEX(SchedZone,MATCH($A10,SchedSeq,0),MAP!$B$10))))} -> BUF | F10: {=IF($B10="","",IF(COUNTIF(Teams,INDEX(SchedZone,MATCH($A10,SchedSeq,0),MAP!$B$12))>0,INDEX(SchedZone,MATCH($A10,SchedSeq,0),MAP!$B$12),IFERROR(INDEX(LISTS!$D$2:$D$12,MATCH(INDEX(SchedZone,MATCH($A10,SchedSeq,0),MAP!$B$12),LISTS!$C$2:$C$12,0)),"⚠ "&INDEX(SchedZone,MATCH($A10,SchedSeq,0),MAP!$B$12))))} -> HOU | Q10: =IF(OR($B10="",$G10="",$H10=""),"",IF($G10="Pick",0,IF($G10=$F10,-$H10,IF($G10=$E10,$H10,"")))) | R10: =IF($B10="","",IF(AND($G10="",$H10="",$I10=""),"",IF(AND($G10="",$H10<>""),"⚠ ADD FAVORITE",IF(AND($G10<>"",$G10<>"Pick",$G10<>$E10,$G10<>$F10),"⚠ FAVORITE NOT IN GAME",IF(AND($G10<>"",$H10=""),"⚠ SPREAD MISSING",IF(AND($H10<>"",NOT(ISNUMBER($H10))),"⚠ SPREAD NOT A NUMBER",IF(AND(ISNUMBER($H10),$H10<0),"⚠ ENTER SPREAD AS POSITIVE","OK"))))))) | S10: =IF(OR($B10="",$O10=""),"",IF(AsOfDate-$O10>StaleDays,"STALE","OK"))
A11: 7 | B11: {=IFERROR(INDEX(SchedZone,MATCH($A11,SchedSeq,0),MAP!$B$6),"")} -> 2026_01_BAL_IND | C11: {=IF($B11="","",INDEX(SchedZone,MATCH($A11,SchedSeq,0),MAP!$B$4))} -> 1 | D11: {=IF($B11="","",INDEX(SchedZone,MATCH($A11,SchedSeq,0),MAP!$B$7))} -> 46278 | E11: {=IF($B11="","",IF(COUNTIF(Teams,INDEX(SchedZone,MATCH($A11,SchedSeq,0),MAP!$B$10))>0,INDEX(SchedZone,MATCH($A11,SchedSeq,0),MAP!$B$10),IFERROR(INDEX(LISTS!$D$2:$D$12,MATCH(INDEX(SchedZone,MATCH($A11,SchedSeq,0),MAP!$B$10),LISTS!$C$2:$C$12,0)),"⚠ "&INDEX(SchedZone,MATCH($A11,SchedSeq,0),MAP!$B$10))))} -> BAL | F11: {=IF($B11="","",IF(COUNTIF(Teams,INDEX(SchedZone,MATCH($A11,SchedSeq,0),MAP!$B$12))>0,INDEX(SchedZone,MATCH($A11,SchedSeq,0),MAP!$B$12),IFERROR(INDEX(LISTS!$D$2:$D$12,MATCH(INDEX(SchedZone,MATCH($A11,SchedSeq,0),MAP!$B$12),LISTS!$C$2:$C$12,0)),"⚠ "&INDEX(SchedZone,MATCH($A11,SchedSeq,0),MAP!$B$12))))} -> IND | Q11: =IF(OR($B11="",$G11="",$H11=""),"",IF($G11="Pick",0,IF($G11=$F11,-$H11,IF($G11=$E11,$H11,"")))) | R11: =IF($B11="","",IF(AND($G11="",$H11="",$I11=""),"",IF(AND($G11="",$H11<>""),"⚠ ADD FAVORITE",IF(AND($G11<>"",$G11<>"Pick",$G11<>$E11,$G11<>$F11),"⚠ FAVORITE NOT IN GAME",IF(AND($G11<>"",$H11=""),"⚠ SPREAD MISSING",IF(AND($H11<>"",NOT(ISNUMBER($H11))),"⚠ SPREAD NOT A NUMBER",IF(AND(ISNUMBER($H11),$H11<0),"⚠ ENTER SPREAD AS POSITIVE","OK"))))))) | S11: =IF(OR($B11="",$O11=""),"",IF(AsOfDate-$O11>StaleDays,"STALE","OK"))
A12: 8 | B12: {=IFERROR(INDEX(SchedZone,MATCH($A12,SchedSeq,0),MAP!$B$6),"")} -> 2026_01_CLE_JAX | C12: {=IF($B12="","",INDEX(SchedZone,MATCH($A12,SchedSeq,0),MAP!$B$4))} -> 1 | D12: {=IF($B12="","",INDEX(SchedZone,MATCH($A12,SchedSeq,0),MAP!$B$7))} -> 46278 | E12: {=IF($B12="","",IF(COUNTIF(Teams,INDEX(SchedZone,MATCH($A12,SchedSeq,0),MAP!$B$10))>0,INDEX(SchedZone,MATCH($A12,SchedSeq,0),MAP!$B$10),IFERROR(INDEX(LISTS!$D$2:$D$12,MATCH(INDEX(SchedZone,MATCH($A12,SchedSeq,0),MAP!$B$10),LISTS!$C$2:$C$12,0)),"⚠ "&INDEX(SchedZone,MATCH($A12,SchedSeq,0),MAP!$B$10))))} -> CLE | F12: {=IF($B12="","",IF(COUNTIF(Teams,INDEX(SchedZone,MATCH($A12,SchedSeq,0),MAP!$B$12))>0,INDEX(SchedZone,MATCH($A12,SchedSeq,0),MAP!$B$12),IFERROR(INDEX(LISTS!$D$2:$D$12,MATCH(INDEX(SchedZone,MATCH($A12,SchedSeq,0),MAP!$B$12),LISTS!$C$2:$C$12,0)),"⚠ "&INDEX(SchedZone,MATCH($A12,SchedSeq,0),MAP!$B$12))))} -> JAX | Q12: =IF(OR($B12="",$G12="",$H12=""),"",IF($G12="Pick",0,IF($G12=$F12,-$H12,IF($G12=$E12,$H12,"")))) | R12: =IF($B12="","",IF(AND($G12="",$H12="",$I12=""),"",IF(AND($G12="",$H12<>""),"⚠ ADD FAVORITE",IF(AND($G12<>"",$G12<>"Pick",$G12<>$E12,$G12<>$F12),"⚠ FAVORITE NOT IN GAME",IF(AND($G12<>"",$H12=""),"⚠ SPREAD MISSING",IF(AND($H12<>"",NOT(ISNUMBER($H12))),"⚠ SPREAD NOT A NUMBER",IF(AND(ISNUMBER($H12),$H12<0),"⚠ ENTER SPREAD AS POSITIVE","OK"))))))) | S12: =IF(OR($B12="",$O12=""),"",IF(AsOfDate-$O12>StaleDays,"STALE","OK"))
A13: 9 | B13: {=IFERROR(INDEX(SchedZone,MATCH($A13,SchedSeq,0),MAP!$B$6),"")} -> 2026_01_ATL_PIT | C13: {=IF($B13="","",INDEX(SchedZone,MATCH($A13,SchedSeq,0),MAP!$B$4))} -> 1 | D13: {=IF($B13="","",INDEX(SchedZone,MATCH($A13,SchedSeq,0),MAP!$B$7))} -> 46278 | E13: {=IF($B13="","",IF(COUNTIF(Teams,INDEX(SchedZone,MATCH($A13,SchedSeq,0),MAP!$B$10))>0,INDEX(SchedZone,MATCH($A13,SchedSeq,0),MAP!$B$10),IFERROR(INDEX(LISTS!$D$2:$D$12,MATCH(INDEX(SchedZone,MATCH($A13,SchedSeq,0),MAP!$B$10),LISTS!$C$2:$C$12,0)),"⚠ "&INDEX(SchedZone,MATCH($A13,SchedSeq,0),MAP!$B$10))))} -> ATL | F13: {=IF($B13="","",IF(COUNTIF(Teams,INDEX(SchedZone,MATCH($A13,SchedSeq,0),MAP!$B$12))>0,INDEX(SchedZone,MATCH($A13,SchedSeq,0),MAP!$B$12),IFERROR(INDEX(LISTS!$D$2:$D$12,MATCH(INDEX(SchedZone,MATCH($A13,SchedSeq,0),MAP!$B$12),LISTS!$C$2:$C$12,0)),"⚠ "&INDEX(SchedZone,MATCH($A13,SchedSeq,0),MAP!$B$12))))} -> PIT | Q13: =IF(OR($B13="",$G13="",$H13=""),"",IF($G13="Pick",0,IF($G13=$F13,-$H13,IF($G13=$E13,$H13,"")))) | R13: =IF($B13="","",IF(AND($G13="",$H13="",$I13=""),"",IF(AND($G13="",$H13<>""),"⚠ ADD FAVORITE",IF(AND($G13<>"",$G13<>"Pick",$G13<>$E13,$G13<>$F13),"⚠ FAVORITE NOT IN GAME",IF(AND($G13<>"",$H13=""),"⚠ SPREAD MISSING",IF(AND($H13<>"",NOT(ISNUMBER($H13))),"⚠ SPREAD NOT A NUMBER",IF(AND(ISNUMBER($H13),$H13<0),"⚠ ENTER SPREAD AS POSITIVE","OK"))))))) | S13: =IF(OR($B13="",$O13=""),"",IF(AsOfDate-$O13>StaleDays,"STALE","OK"))
A14: 10 | B14: {=IFERROR(INDEX(SchedZone,MATCH($A14,SchedSeq,0),MAP!$B$6),"")} -> 2026_01_NYJ_TEN | C14: {=IF($B14="","",INDEX(SchedZone,MATCH($A14,SchedSeq,0),MAP!$B$4))} -> 1 | D14: {=IF($B14="","",INDEX(SchedZone,MATCH($A14,SchedSeq,0),MAP!$B$7))} -> 46278 | E14: {=IF($B14="","",IF(COUNTIF(Teams,INDEX(SchedZone,MATCH($A14,SchedSeq,0),MAP!$B$10))>0,INDEX(SchedZone,MATCH($A14,SchedSeq,0),MAP!$B$10),IFERROR(INDEX(LISTS!$D$2:$D$12,MATCH(INDEX(SchedZone,MATCH($A14,SchedSeq,0),MAP!$B$10),LISTS!$C$2:$C$12,0)),"⚠ "&INDEX(SchedZone,MATCH($A14,SchedSeq,0),MAP!$B$10))))} -> NYJ | F14: {=IF($B14="","",IF(COUNTIF(Teams,INDEX(SchedZone,MATCH($A14,SchedSeq,0),MAP!$B$12))>0,INDEX(SchedZone,MATCH($A14,SchedSeq,0),MAP!$B$12),IFERROR(INDEX(LISTS!$D$2:$D$12,MATCH(INDEX(SchedZone,MATCH($A14,SchedSeq,0),MAP!$B$12),LISTS!$C$2:$C$12,0)),"⚠ "&INDEX(SchedZone,MATCH($A14,SchedSeq,0),MAP!$B$12))))} -> TEN | Q14: =IF(OR($B14="",$G14="",$H14=""),"",IF($G14="Pick",0,IF($G14=$F14,-$H14,IF($G14=$E14,$H14,"")))) | R14: =IF($B14="","",IF(AND($G14="",$H14="",$I14=""),"",IF(AND($G14="",$H14<>""),"⚠ ADD FAVORITE",IF(AND($G14<>"",$G14<>"Pick",$G14<>$E14,$G14<>$F14),"⚠ FAVORITE NOT IN GAME",IF(AND($G14<>"",$H14=""),"⚠ SPREAD MISSING",IF(AND($H14<>"",NOT(ISNUMBER($H14))),"⚠ SPREAD NOT A NUMBER",IF(AND(ISNUMBER($H14),$H14<0),"⚠ ENTER SPREAD AS POSITIVE","OK"))))))) | S14: =IF(OR($B14="",$O14=""),"",IF(AsOfDate-$O14>StaleDays,"STALE","OK"))
A15: 11 | B15: {=IFERROR(INDEX(SchedZone,MATCH($A15,SchedSeq,0),MAP!$B$6),"")} -> 2026_01_ARI_LAC | C15: {=IF($B15="","",INDEX(SchedZone,MATCH($A15,SchedSeq,0),MAP!$B$4))} -> 1 | D15: {=IF($B15="","",INDEX(SchedZone,MATCH($A15,SchedSeq,0),MAP!$B$7))} -> 46278 | E15: {=IF($B15="","",IF(COUNTIF(Teams,INDEX(SchedZone,MATCH($A15,SchedSeq,0),MAP!$B$10))>0,INDEX(SchedZone,MATCH($A15,SchedSeq,0),MAP!$B$10),IFERROR(INDEX(LISTS!$D$2:$D$12,MATCH(INDEX(SchedZone,MATCH($A15,SchedSeq,0),MAP!$B$10),LISTS!$C$2:$C$12,0)),"⚠ "&INDEX(SchedZone,MATCH($A15,SchedSeq,0),MAP!$B$10))))} -> ARI | F15: {=IF($B15="","",IF(COUNTIF(Teams,INDEX(SchedZone,MATCH($A15,SchedSeq,0),MAP!$B$12))>0,INDEX(SchedZone,MATCH($A15,SchedSeq,0),MAP!$B$12),IFERROR(INDEX(LISTS!$D$2:$D$12,MATCH(INDEX(SchedZone,MATCH($A15,SchedSeq,0),MAP!$B$12),LISTS!$C$2:$C$12,0)),"⚠ "&INDEX(SchedZone,MATCH($A15,SchedSeq,0),MAP!$B$12))))} -> LAC | Q15: =IF(OR($B15="",$G15="",$H15=""),"",IF($G15="Pick",0,IF($G15=$F15,-$H15,IF($G15=$E15,$H15,"")))) | R15: =IF($B15="","",IF(AND($G15="",$H15="",$I15=""),"",IF(AND($G15="",$H15<>""),"⚠ ADD FAVORITE",IF(AND($G15<>"",$G15<>"Pick",$G15<>$E15,$G15<>$F15),"⚠ FAVORITE NOT IN GAME",IF(AND($G15<>"",$H15=""),"⚠ SPREAD MISSING",IF(AND($H15<>"",NOT(ISNUMBER($H15))),"⚠ SPREAD NOT A NUMBER",IF(AND(ISNUMBER($H15),$H15<0),"⚠ ENTER SPREAD AS POSITIVE","OK"))))))) | S15: =IF(OR($B15="",$O15=""),"",IF(AsOfDate-$O15>StaleDays,"STALE","OK"))
A16: 12 | B16: {=IFERROR(INDEX(SchedZone,MATCH($A16,SchedSeq,0),MAP!$B$6),"")} -> 2026_01_MIA_LV | C16: {=IF($B16="","",INDEX(SchedZone,MATCH($A16,SchedSeq,0),MAP!$B$4))} -> 1 | D16: {=IF($B16="","",INDEX(SchedZone,MATCH($A16,SchedSeq,0),MAP!$B$7))} -> 46278 | E16: {=IF($B16="","",IF(COUNTIF(Teams,INDEX(SchedZone,MATCH($A16,SchedSeq,0),MAP!$B$10))>0,INDEX(SchedZone,MATCH($A16,SchedSeq,0),MAP!$B$10),IFERROR(INDEX(LISTS!$D$2:$D$12,MATCH(INDEX(SchedZone,MATCH($A16,SchedSeq,0),MAP!$B$10),LISTS!$C$2:$C$12,0)),"⚠ "&INDEX(SchedZone,MATCH($A16,SchedSeq,0),MAP!$B$10))))} -> MIA | F16: {=IF($B16="","",IF(COUNTIF(Teams,INDEX(SchedZone,MATCH($A16,SchedSeq,0),MAP!$B$12))>0,INDEX(SchedZone,MATCH($A16,SchedSeq,0),MAP!$B$12),IFERROR(INDEX(LISTS!$D$2:$D$12,MATCH(INDEX(SchedZone,MATCH($A16,SchedSeq,0),MAP!$B$12),LISTS!$C$2:$C$12,0)),"⚠ "&INDEX(SchedZone,MATCH($A16,SchedSeq,0),MAP!$B$12))))} -> LV | Q16: =IF(OR($B16="",$G16="",$H16=""),"",IF($G16="Pick",0,IF($G16=$F16,-$H16,IF($G16=$E16,$H16,"")))) | R16: =IF($B16="","",IF(AND($G16="",$H16="",$I16=""),"",IF(AND($G16="",$H16<>""),"⚠ ADD FAVORITE",IF(AND($G16<>"",$G16<>"Pick",$G16<>$E16,$G16<>$F16),"⚠ FAVORITE NOT IN GAME",IF(AND($G16<>"",$H16=""),"⚠ SPREAD MISSING",IF(AND($H16<>"",NOT(ISNUMBER($H16))),"⚠ SPREAD NOT A NUMBER",IF(AND(ISNUMBER($H16),$H16<0),"⚠ ENTER SPREAD AS POSITIVE","OK"))))))) | S16: =IF(OR($B16="",$O16=""),"",IF(AsOfDate-$O16>StaleDays,"STALE","OK"))
... A260: 256 | B260: {=IFERROR(INDEX(SchedZone,MATCH($A260,SchedSeq,0),MAP!$B$6),"")} -> 2026_17_HOU_GB | C260: {=IF($B260="","",INDEX(SchedZone,MATCH($A260,SchedSeq,0),MAP!$B$4))} -> 17 | D260: {=IF($B260="","",INDEX(SchedZone,MATCH($A260,SchedSeq,0),MAP!$B$7))} -> 46391 | E260: {=IF($B260="","",IF(COUNTIF(Teams,INDEX(SchedZone,MATCH($A260,SchedSeq,0),MAP!$B$10))>0,INDEX(SchedZone,MATCH($A260,SchedSeq,0),MAP!$B$10),IFERROR(INDEX(LISTS!$D$2:$D$12,MATCH(INDEX(SchedZone,MATCH($A260,SchedSeq,0),MAP!$B$10),LISTS!$C$2:$C$12,0)),"⚠ "&INDEX(SchedZone,MATCH($A260,SchedSeq,0),MAP!$B$10))))} -> HOU | F260: {=IF($B260="","",IF(COUNTIF(Teams,INDEX(SchedZone,MATCH($A260,SchedSeq,0),MAP!$B$12))>0,INDEX(SchedZone,MATCH($A260,SchedSeq,0),MAP!$B$12),IFERROR(INDEX(LISTS!$D$2:$D$12,MATCH(INDEX(SchedZone,MATCH($A260,SchedSeq,0),MAP!$B$12),LISTS!$C$2:$C$12,0)),"⚠ "&INDEX(SchedZone,MATCH($A260,SchedSeq,0),MAP!$B$12))))} -> GB | Q260: =IF(OR($B260="",$G260="",$H260=""),"",IF($G260="Pick",0,IF($G260=$F260,-$H260,IF($G260=$E260,$H260,"")))) | R260: =IF($B260="","",IF(AND($G260="",$H260="",$I260=""),"",IF(AND($G260="",$H260<>""),"⚠ ADD FAVORITE",IF(AND($G260<>"",$G260<>"Pick",$G260<>$E260,$G260<>$F260),"⚠ FAVORITE NOT IN GAME",IF(AND($G260<>"",$H260=""),"⚠ SPREAD MISSING",IF(AND($H260<>"",NOT(ISNUMBER($H260))),"⚠ SPREAD NOT A NUMBER",IF(AND(ISNUMBER($H260),$H260<0),"⚠ ENTER SPREAD AS POSITIVE","OK"))))))) | S260: =IF(OR($B260="",$O260=""),"",IF(AsOfDate-$O260>StaleDays,"STALE","OK"))
A261: 257 | B261: {=IFERROR(INDEX(SchedZone,MATCH($A261,SchedSeq,0),MAP!$B$6),"")} -> 2026_18_SF_ARI | C261: {=IF($B261="","",INDEX(SchedZone,MATCH($A261,SchedSeq,0),MAP!$B$4))} -> 18 | D261: {=IF($B261="","",INDEX(SchedZone,MATCH($A261,SchedSeq,0),MAP!$B$7))} -> 46397 | E261: {=IF($B261="","",IF(COUNTIF(Teams,INDEX(SchedZone,MATCH($A261,SchedSeq,0),MAP!$B$10))>0,INDEX(SchedZone,MATCH($A261,SchedSeq,0),MAP!$B$10),IFERROR(INDEX(LISTS!$D$2:$D$12,MATCH(INDEX(SchedZone,MATCH($A261,SchedSeq,0),MAP!$B$10),LISTS!$C$2:$C$12,0)),"⚠ "&INDEX(SchedZone,MATCH($A261,SchedSeq,0),MAP!$B$10))))} -> SF | F261: {=IF($B261="","",IF(COUNTIF(Teams,INDEX(SchedZone,MATCH($A261,SchedSeq,0),MAP!$B$12))>0,INDEX(SchedZone,MATCH($A261,SchedSeq,0),MAP!$B$12),IFERROR(INDEX(LISTS!$D$2:$D$12,MATCH(INDEX(SchedZone,MATCH($A261,SchedSeq,0),MAP!$B$12),LISTS!$C$2:$C$12,0)),"⚠ "&INDEX(SchedZone,MATCH($A261,SchedSeq,0),MAP!$B$12))))} -> ARI | G261: ATL | H261: 4.5 | I261: 43.5 | N261: NFLVERSE-HIST (sample) | O261: 2026-01-01 | P261: SAMPLE — historical reference line, replace with Novig | Q261: =IF(OR($B261="",$G261="",$H261=""),"",IF($G261="Pick",0,IF($G261=$F261,-$H261,IF($G261=$E261,$H261,"")))) | R261: =IF($B261="","",IF(AND($G261="",$H261="",$I261=""),"",IF(AND($G261="",$H261<>""),"⚠ ADD FAVORITE",IF(AND($G261<>"",$G261<>"Pick",$G261<>$E261,$G261<>$F261),"⚠ FAVORITE NOT IN GAME",IF(AND($G261<>"",$H261=""),"⚠ SPREAD MISSING",IF(AND($H261<>"",NOT(ISNUMBER($H261))),"⚠ SPREAD NOT A NUMBER",IF(AND(ISNUMBER($H261),$H261<0),"⚠ ENTER SPREAD AS POSITIVE","OK"))))))) -> ⚠ FAVORITE NOT IN GAME | S261: =IF(OR($B261="",$O261=""),"",IF(AsOfDate-$O261>StaleDays,"STALE","OK")) -> STALE
A262: 258 | B262: {=IFERROR(INDEX(SchedZone,MATCH($A262,SchedSeq,0),MAP!$B$6),"")} -> 2026_18_PIT_BAL | C262: {=IF($B262="","",INDEX(SchedZone,MATCH($A262,SchedSeq,0),MAP!$B$4))} -> 18 | D262: {=IF($B262="","",INDEX(SchedZone,MATCH($A262,SchedSeq,0),MAP!$B$7))} -> 46397 | E262: {=IF($B262="","",IF(COUNTIF(Teams,INDEX(SchedZone,MATCH($A262,SchedSeq,0),MAP!$B$10))>0,INDEX(SchedZone,MATCH($A262,SchedSeq,0),MAP!$B$10),IFERROR(INDEX(LISTS!$D$2:$D$12,MATCH(INDEX(SchedZone,MATCH($A262,SchedSeq,0),MAP!$B$10),LISTS!$C$2:$C$12,0)),"⚠ "&INDEX(SchedZone,MATCH($A262,SchedSeq,0),MAP!$B$10))))} -> PIT | F262: {=IF($B262="","",IF(COUNTIF(Teams,INDEX(SchedZone,MATCH($A262,SchedSeq,0),MAP!$B$12))>0,INDEX(SchedZone,MATCH($A262,SchedSeq,0),MAP!$B$12),IFERROR(INDEX(LISTS!$D$2:$D$12,MATCH(INDEX(SchedZone,MATCH($A262,SchedSeq,0),MAP!$B$12),LISTS!$C$2:$C$12,0)),"⚠ "&INDEX(SchedZone,MATCH($A262,SchedSeq,0),MAP!$B$12))))} -> BAL | G262: BUF | H262: 12.5 | I262: 39.5 | N262: NFLVERSE-HIST (sample) | O262: 2026-01-01 | P262: SAMPLE — historical reference line, replace with Novig | Q262: =IF(OR($B262="",$G262="",$H262=""),"",IF($G262="Pick",0,IF($G262=$F262,-$H262,IF($G262=$E262,$H262,"")))) | R262: =IF($B262="","",IF(AND($G262="",$H262="",$I262=""),"",IF(AND($G262="",$H262<>""),"⚠ ADD FAVORITE",IF(AND($G262<>"",$G262<>"Pick",$G262<>$E262,$G262<>$F262),"⚠ FAVORITE NOT IN GAME",IF(AND($G262<>"",$H262=""),"⚠ SPREAD MISSING",IF(AND($H262<>"",NOT(ISNUMBER($H262))),"⚠ SPREAD NOT A NUMBER",IF(AND(ISNUMBER($H262),$H262<0),"⚠ ENTER SPREAD AS POSITIVE","OK"))))))) -> ⚠ FAVORITE NOT IN GAME | S262: =IF(OR($B262="",$O262=""),"",IF(AsOfDate-$O262>StaleDays,"STALE","OK")) -> STALE
A263: 259 | B263: {=IFERROR(INDEX(SchedZone,MATCH($A263,SchedSeq,0),MAP!$B$6),"")} -> 2026_18_NYJ_BUF | C263: {=IF($B263="","",INDEX(SchedZone,MATCH($A263,SchedSeq,0),MAP!$B$4))} -> 18 | D263: {=IF($B263="","",INDEX(SchedZone,MATCH($A263,SchedSeq,0),MAP!$B$7))} -> 46397 | E263: {=IF($B263="","",IF(COUNTIF(Teams,INDEX(SchedZone,MATCH($A263,SchedSeq,0),MAP!$B$10))>0,INDEX(SchedZone,MATCH($A263,SchedSeq,0),MAP!$B$10),IFERROR(INDEX(LISTS!$D$2:$D$12,MATCH(INDEX(SchedZone,MATCH($A263,SchedSeq,0),MAP!$B$10),LISTS!$C$2:$C$12,0)),"⚠ "&INDEX(SchedZone,MATCH($A263,SchedSeq,0),MAP!$B$10))))} -> NYJ | F263: {=IF($B263="","",IF(COUNTIF(Teams,INDEX(SchedZone,MATCH($A263,SchedSeq,0),MAP!$B$12))>0,INDEX(SchedZone,MATCH($A263,SchedSeq,0),MAP!$B$12),IFERROR(INDEX(LISTS!$D$2:$D$12,MATCH(INDEX(SchedZone,MATCH($A263,SchedSeq,0),MAP!$B$12),LISTS!$C$2:$C$12,0)),"⚠ "&INDEX(SchedZone,MATCH($A263,SchedSeq,0),MAP!$B$12))))} -> BUF | G263: CHI | H263: 3.5 | I263: 51.5 | N263: NFLVERSE-HIST (sample) | O263: 2026-01-01 | P263: SAMPLE — historical reference line, replace with Novig | Q263: =IF(OR($B263="",$G263="",$H263=""),"",IF($G263="Pick",0,IF($G263=$F263,-$H263,IF($G263=$E263,$H263,"")))) | R263: =IF($B263="","",IF(AND($G263="",$H263="",$I263=""),"",IF(AND($G263="",$H263<>""),"⚠ ADD FAVORITE",IF(AND($G263<>"",$G263<>"Pick",$G263<>$E263,$G263<>$F263),"⚠ FAVORITE NOT IN GAME",IF(AND($G263<>"",$H263=""),"⚠ SPREAD MISSING",IF(AND($H263<>"",NOT(ISNUMBER($H263))),"⚠ SPREAD NOT A NUMBER",IF(AND(ISNUMBER($H263),$H263<0),"⚠ ENTER SPREAD AS POSITIVE","OK"))))))) -> ⚠ FAVORITE NOT IN GAME | S263: =IF(OR($B263="",$O263=""),"",IF(AsOfDate-$O263>StaleDays,"STALE","OK")) -> STALE
A264: 260 | B264: {=IFERROR(INDEX(SchedZone,MATCH($A264,SchedSeq,0),MAP!$B$6),"")} -> 2026_18_ATL_CAR | C264: {=IF($B264="","",INDEX(SchedZone,MATCH($A264,SchedSeq,0),MAP!$B$4))} -> 18 | D264: {=IF($B264="","",INDEX(SchedZone,MATCH($A264,SchedSeq,0),MAP!$B$7))} -> 46397 | E264: {=IF($B264="","",IF(COUNTIF(Teams,INDEX(SchedZone,MATCH($A264,SchedSeq,0),MAP!$B$10))>0,INDEX(SchedZone,MATCH($A264,SchedSeq,0),MAP!$B$10),IFERROR(INDEX(LISTS!$D$2:$D$12,MATCH(INDEX(SchedZone,MATCH($A264,SchedSeq,0),MAP!$B$10),LISTS!$C$2:$C$12,0)),"⚠ "&INDEX(SchedZone,MATCH($A264,SchedSeq,0),MAP!$B$10))))} -> ATL | F264: {=IF($B264="","",IF(COUNTIF(Teams,INDEX(SchedZone,MATCH($A264,SchedSeq,0),MAP!$B$12))>0,INDEX(SchedZone,MATCH($A264,SchedSeq,0),MAP!$B$12),IFERROR(INDEX(LISTS!$D$2:$D$12,MATCH(INDEX(SchedZone,MATCH($A264,SchedSeq,0),MAP!$B$12),LISTS!$C$2:$C$12,0)),"⚠ "&INDEX(SchedZone,MATCH($A264,SchedSeq,0),MAP!$B$12))))} -> CAR | G264: CIN | H264: 9.5 | I264: 47.5 | N264: NFLVERSE-HIST (sample) | O264: 2026-01-01 | P264: SAMPLE — historical reference line, replace with Novig | Q264: =IF(OR($B264="",$G264="",$H264=""),"",IF($G264="Pick",0,IF($G264=$F264,-$H264,IF($G264=$E264,$H264,"")))) | R264: =IF($B264="","",IF(AND($G264="",$H264="",$I264=""),"",IF(AND($G264="",$H264<>""),"⚠ ADD FAVORITE",IF(AND($G264<>"",$G264<>"Pick",$G264<>$E264,$G264<>$F264),"⚠ FAVORITE NOT IN GAME",IF(AND($G264<>"",$H264=""),"⚠ SPREAD MISSING",IF(AND($H264<>"",NOT(ISNUMBER($H264))),"⚠ SPREAD NOT A NUMBER",IF(AND(ISNUMBER($H264),$H264<0),"⚠ ENTER SPREAD AS POSITIVE","OK"))))))) -> ⚠ FAVORITE NOT IN GAME | S264: =IF(OR($B264="",$O264=""),"",IF(AsOfDate-$O264>StaleDays,"STALE","OK")) -> STALE
A265: 261 | B265: {=IFERROR(INDEX(SchedZone,MATCH($A265,SchedSeq,0),MAP!$B$6),"")} -> 2026_18_CLE_CIN | C265: {=IF($B265="","",INDEX(SchedZone,MATCH($A265,SchedSeq,0),MAP!$B$4))} -> 18 | D265: {=IF($B265="","",INDEX(SchedZone,MATCH($A265,SchedSeq,0),MAP!$B$7))} -> 46397 | E265: {=IF($B265="","",IF(COUNTIF(Teams,INDEX(SchedZone,MATCH($A265,SchedSeq,0),MAP!$B$10))>0,INDEX(SchedZone,MATCH($A265,SchedSeq,0),MAP!$B$10),IFERROR(INDEX(LISTS!$D$2:$D$12,MATCH(INDEX(SchedZone,MATCH($A265,SchedSeq,0),MAP!$B$10),LISTS!$C$2:$C$12,0)),"⚠ "&INDEX(SchedZone,MATCH($A265,SchedSeq,0),MAP!$B$10))))} -> CLE | F265: {=IF($B265="","",IF(COUNTIF(Teams,INDEX(SchedZone,MATCH($A265,SchedSeq,0),MAP!$B$12))>0,INDEX(SchedZone,MATCH($A265,SchedSeq,0),MAP!$B$12),IFERROR(INDEX(LISTS!$D$2:$D$12,MATCH(INDEX(SchedZone,MATCH($A265,SchedSeq,0),MAP!$B$12),LISTS!$C$2:$C$12,0)),"⚠ "&INDEX(SchedZone,MATCH($A265,SchedSeq,0),MAP!$B$12))))} -> CIN | G265: DEN | H265: 14.5 | I265: 37.5 | N265: NFLVERSE-HIST (sample) | O265: 2026-01-01 | P265: SAMPLE — historical reference line, replace with Novig | Q265: =IF(OR($B265="",$G265="",$H265=""),"",IF($G265="Pick",0,IF($G265=$F265,-$H265,IF($G265=$E265,$H265,"")))) | R265: =IF($B265="","",IF(AND($G265="",$H265="",$I265=""),"",IF(AND($G265="",$H265<>""),"⚠ ADD FAVORITE",IF(AND($G265<>"",$G265<>"Pick",$G265<>$E265,$G265<>$F265),"⚠ FAVORITE NOT IN GAME",IF(AND($G265<>"",$H265=""),"⚠ SPREAD MISSING",IF(AND($H265<>"",NOT(ISNUMBER($H265))),"⚠ SPREAD NOT A NUMBER",IF(AND(ISNUMBER($H265),$H265<0),"⚠ ENTER SPREAD AS POSITIVE","OK"))))))) -> ⚠ FAVORITE NOT IN GAME | S265: =IF(OR($B265="",$O265=""),"",IF(AsOfDate-$O265>StaleDays,"STALE","OK")) -> STALE
A266: 262 | B266: {=IFERROR(INDEX(SchedZone,MATCH($A266,SchedSeq,0),MAP!$B$6),"")} -> 2026_18_LAC_DEN | C266: {=IF($B266="","",INDEX(SchedZone,MATCH($A266,SchedSeq,0),MAP!$B$4))} -> 18 | D266: {=IF($B266="","",INDEX(SchedZone,MATCH($A266,SchedSeq,0),MAP!$B$7))} -> 46397 | E266: {=IF($B266="","",IF(COUNTIF(Teams,INDEX(SchedZone,MATCH($A266,SchedSeq,0),MAP!$B$10))>0,INDEX(SchedZone,MATCH($A266,SchedSeq,0),MAP!$B$10),IFERROR(INDEX(LISTS!$D$2:$D$12,MATCH(INDEX(SchedZone,MATCH($A266,SchedSeq,0),MAP!$B$10),LISTS!$C$2:$C$12,0)),"⚠ "&INDEX(SchedZone,MATCH($A266,SchedSeq,0),MAP!$B$10))))} -> LAC | F266: {=IF($B266="","",IF(COUNTIF(Teams,INDEX(SchedZone,MATCH($A266,SchedSeq,0),MAP!$B$12))>0,INDEX(SchedZone,MATCH($A266,SchedSeq,0),MAP!$B$12),IFERROR(INDEX(LISTS!$D$2:$D$12,MATCH(INDEX(SchedZone,MATCH($A266,SchedSeq,0),MAP!$B$12),LISTS!$C$2:$C$12,0)),"⚠ "&INDEX(SchedZone,MATCH($A266,SchedSeq,0),MAP!$B$12))))} -> DEN | G266: HOU | H266: 9.5 | I266: 37.5 | N266: NFLVERSE-HIST (sample) | O266: 2026-01-01 | P266: SAMPLE — historical reference line, replace with Novig | Q266: =IF(OR($B266="",$G266="",$H266=""),"",IF($G266="Pick",0,IF($G266=$F266,-$H266,IF($G266=$E266,$H266,"")))) | R266: =IF($B266="","",IF(AND($G266="",$H266="",$I266=""),"",IF(AND($G266="",$H266<>""),"⚠ ADD FAVORITE",IF(AND($G266<>"",$G266<>"Pick",$G266<>$E266,$G266<>$F266),"⚠ FAVORITE NOT IN GAME",IF(AND($G266<>"",$H266=""),"⚠ SPREAD MISSING",IF(AND($H266<>"",NOT(ISNUMBER($H266))),"⚠ SPREAD NOT A NUMBER",IF(AND(ISNUMBER($H266),$H266<0),"⚠ ENTER SPREAD AS POSITIVE","OK"))))))) -> ⚠ FAVORITE NOT IN GAME | S266: =IF(OR($B266="",$O266=""),"",IF(AsOfDate-$O266>StaleDays,"STALE","OK")) -> STALE
A267: 263 | B267: {=IFERROR(INDEX(SchedZone,MATCH($A267,SchedSeq,0),MAP!$B$6),"")} -> 2026_18_DET_GB | C267: {=IF($B267="","",INDEX(SchedZone,MATCH($A267,SchedSeq,0),MAP!$B$4))} -> 18 | D267: {=IF($B267="","",INDEX(SchedZone,MATCH($A267,SchedSeq,0),MAP!$B$7))} -> 46397 | E267: {=IF($B267="","",IF(COUNTIF(Teams,INDEX(SchedZone,MATCH($A267,SchedSeq,0),MAP!$B$10))>0,INDEX(SchedZone,MATCH($A267,SchedSeq,0),MAP!$B$10),IFERROR(INDEX(LISTS!$D$2:$D$12,MATCH(INDEX(SchedZone,MATCH($A267,SchedSeq,0),MAP!$B$10),LISTS!$C$2:$C$12,0)),"⚠ "&INDEX(SchedZone,MATCH($A267,SchedSeq,0),MAP!$B$10))))} -> DET | F267: {=IF($B267="","",IF(COUNTIF(Teams,INDEX(SchedZone,MATCH($A267,SchedSeq,0),MAP!$B$12))>0,INDEX(SchedZone,MATCH($A267,SchedSeq,0),MAP!$B$12),IFERROR(INDEX(LISTS!$D$2:$D$12,MATCH(INDEX(SchedZone,MATCH($A267,SchedSeq,0),MAP!$B$12),LISTS!$C$2:$C$12,0)),"⚠ "&INDEX(SchedZone,MATCH($A267,SchedSeq,0),MAP!$B$12))))} -> GB | G267: JAX | H267: 12.5 | I267: 46.5 | N267: NFLVERSE-HIST (sample) | O267: 2026-01-01 | P267: SAMPLE — historical reference line, replace with Novig | Q267: =IF(OR($B267="",$G267="",$H267=""),"",IF($G267="Pick",0,IF($G267=$F267,-$H267,IF($G267=$E267,$H267,"")))) | R267: =IF($B267="","",IF(AND($G267="",$H267="",$I267=""),"",IF(AND($G267="",$H267<>""),"⚠ ADD FAVORITE",IF(AND($G267<>"",$G267<>"Pick",$G267<>$E267,$G267<>$F267),"⚠ FAVORITE NOT IN GAME",IF(AND($G267<>"",$H267=""),"⚠ SPREAD MISSING",IF(AND($H267<>"",NOT(ISNUMBER($H267))),"⚠ SPREAD NOT A NUMBER",IF(AND(ISNUMBER($H267),$H267<0),"⚠ ENTER SPREAD AS POSITIVE","OK"))))))) -> ⚠ FAVORITE NOT IN GAME | S267: =IF(OR($B267="",$O267=""),"",IF(AsOfDate-$O267>StaleDays,"STALE","OK")) -> STALE
A268: 264 | B268: {=IFERROR(INDEX(SchedZone,MATCH($A268,SchedSeq,0),MAP!$B$6),"")} -> 2026_18_TEN_HOU | C268: {=IF($B268="","",INDEX(SchedZone,MATCH($A268,SchedSeq,0),MAP!$B$4))} -> 18 | D268: {=IF($B268="","",INDEX(SchedZone,MATCH($A268,SchedSeq,0),MAP!$B$7))} -> 46397 | E268: {=IF($B268="","",IF(COUNTIF(Teams,INDEX(SchedZone,MATCH($A268,SchedSeq,0),MAP!$B$10))>0,INDEX(SchedZone,MATCH($A268,SchedSeq,0),MAP!$B$10),IFERROR(INDEX(LISTS!$D$2:$D$12,MATCH(INDEX(SchedZone,MATCH($A268,SchedSeq,0),MAP!$B$10),LISTS!$C$2:$C$12,0)),"⚠ "&INDEX(SchedZone,MATCH($A268,SchedSeq,0),MAP!$B$10))))} -> TEN | F268: {=IF($B268="","",IF(COUNTIF(Teams,INDEX(SchedZone,MATCH($A268,SchedSeq,0),MAP!$B$12))>0,INDEX(SchedZone,MATCH($A268,SchedSeq,0),MAP!$B$12),IFERROR(INDEX(LISTS!$D$2:$D$12,MATCH(INDEX(SchedZone,MATCH($A268,SchedSeq,0),MAP!$B$12),LISTS!$C$2:$C$12,0)),"⚠ "&INDEX(SchedZone,MATCH($A268,SchedSeq,0),MAP!$B$12))))} -> HOU | G268: LA | H268: 14.5 | I268: 49.5 | N268: NFLVERSE-HIST (sample) | O268: 2026-01-01 | P268: SAMPLE — historical reference line, replace with Novig | Q268: =IF(OR($B268="",$G268="",$H268=""),"",IF($G268="Pick",0,IF($G268=$F268,-$H268,IF($G268=$E268,$H268,"")))) | R268: =IF($B268="","",IF(AND($G268="",$H268="",$I268=""),"",IF(AND($G268="",$H268<>""),"⚠ ADD FAVORITE",IF(AND($G268<>"",$G268<>"Pick",$G268<>$E268,$G268<>$F268),"⚠ FAVORITE NOT IN GAME",IF(AND($G268<>"",$H268=""),"⚠ SPREAD MISSING",IF(AND($H268<>"",NOT(ISNUMBER($H268))),"⚠ SPREAD NOT A NUMBER",IF(AND(ISNUMBER($H268),$H268<0),"⚠ ENTER SPREAD AS POSITIVE","OK"))))))) -> ⚠ FAVORITE NOT IN GAME | S268: =IF(OR($B268="",$O268=""),"",IF(AsOfDate-$O268>StaleDays,"STALE","OK")) -> STALE
A269: 265 | B269: {=IFERROR(INDEX(SchedZone,MATCH($A269,SchedSeq,0),MAP!$B$6),"")} -> 2026_18_JAX_IND | C269: {=IF($B269="","",INDEX(SchedZone,MATCH($A269,SchedSeq,0),MAP!$B$4))} -> 18 | D269: {=IF($B269="","",INDEX(SchedZone,MATCH($A269,SchedSeq,0),MAP!$B$7))} -> 46397 | E269: {=IF($B269="","",IF(COUNTIF(Teams,INDEX(SchedZone,MATCH($A269,SchedSeq,0),MAP!$B$10))>0,INDEX(SchedZone,MATCH($A269,SchedSeq,0),MAP!$B$10),IFERROR(INDEX(LISTS!$D$2:$D$12,MATCH(INDEX(SchedZone,MATCH($A269,SchedSeq,0),MAP!$B$10),LISTS!$C$2:$C$12,0)),"⚠ "&INDEX(SchedZone,MATCH($A269,SchedSeq,0),MAP!$B$10))))} -> JAX | F269: {=IF($B269="","",IF(COUNTIF(Teams,INDEX(SchedZone,MATCH($A269,SchedSeq,0),MAP!$B$12))>0,INDEX(SchedZone,MATCH($A269,SchedSeq,0),MAP!$B$12),IFERROR(INDEX(LISTS!$D$2:$D$12,MATCH(INDEX(SchedZone,MATCH($A269,SchedSeq,0),MAP!$B$12),LISTS!$C$2:$C$12,0)),"⚠ "&INDEX(SchedZone,MATCH($A269,SchedSeq,0),MAP!$B$12))))} -> IND | G269: KC | H269: 3.5 | I269: 36.5 | N269: NFLVERSE-HIST (sample) | O269: 2026-01-01 | P269: SAMPLE — historical reference line, replace with Novig | Q269: =IF(OR($B269="",$G269="",$H269=""),"",IF($G269="Pick",0,IF($G269=$F269,-$H269,IF($G269=$E269,$H269,"")))) | R269: =IF($B269="","",IF(AND($G269="",$H269="",$I269=""),"",IF(AND($G269="",$H269<>""),"⚠ ADD FAVORITE",IF(AND($G269<>"",$G269<>"Pick",$G269<>$E269,$G269<>$F269),"⚠ FAVORITE NOT IN GAME",IF(AND($G269<>"",$H269=""),"⚠ SPREAD MISSING",IF(AND($H269<>"",NOT(ISNUMBER($H269))),"⚠ SPREAD NOT A NUMBER",IF(AND(ISNUMBER($H269),$H269<0),"⚠ ENTER SPREAD AS POSITIVE","OK"))))))) -> ⚠ FAVORITE NOT IN GAME | S269: =IF(OR($B269="",$O269=""),"",IF(AsOfDate-$O269>StaleDays,"STALE","OK")) -> STALE
A270: 266 | B270: {=IFERROR(INDEX(SchedZone,MATCH($A270,SchedSeq,0),MAP!$B$6),"")} -> 2026_18_LV_KC | C270: {=IF($B270="","",INDEX(SchedZone,MATCH($A270,SchedSeq,0),MAP!$B$4))} -> 18 | D270: {=IF($B270="","",INDEX(SchedZone,MATCH($A270,SchedSeq,0),MAP!$B$7))} -> 46397 | E270: {=IF($B270="","",IF(COUNTIF(Teams,INDEX(SchedZone,MATCH($A270,SchedSeq,0),MAP!$B$10))>0,INDEX(SchedZone,MATCH($A270,SchedSeq,0),MAP!$B$10),IFERROR(INDEX(LISTS!$D$2:$D$12,MATCH(INDEX(SchedZone,MATCH($A270,SchedSeq,0),MAP!$B$10),LISTS!$C$2:$C$12,0)),"⚠ "&INDEX(SchedZone,MATCH($A270,SchedSeq,0),MAP!$B$10))))} -> LV | F270: {=IF($B270="","",IF(COUNTIF(Teams,INDEX(SchedZone,MATCH($A270,SchedSeq,0),MAP!$B$12))>0,INDEX(SchedZone,MATCH($A270,SchedSeq,0),MAP!$B$12),IFERROR(INDEX(LISTS!$D$2:$D$12,MATCH(INDEX(SchedZone,MATCH($A270,SchedSeq,0),MAP!$B$12),LISTS!$C$2:$C$12,0)),"⚠ "&INDEX(SchedZone,MATCH($A270,SchedSeq,0),MAP!$B$12))))} -> KC | G270: MIN | H270: 12.5 | I270: 37.5 | N270: NFLVERSE-HIST (sample) | O270: 2026-01-01 | P270: SAMPLE — historical reference line, replace with Novig | Q270: =IF(OR($B270="",$G270="",$H270=""),"",IF($G270="Pick",0,IF($G270=$F270,-$H270,IF($G270=$E270,$H270,"")))) | R270: =IF($B270="","",IF(AND($G270="",$H270="",$I270=""),"",IF(AND($G270="",$H270<>""),"⚠ ADD FAVORITE",IF(AND($G270<>"",$G270<>"Pick",$G270<>$E270,$G270<>$F270),"⚠ FAVORITE NOT IN GAME",IF(AND($G270<>"",$H270=""),"⚠ SPREAD MISSING",IF(AND($H270<>"",NOT(ISNUMBER($H270))),"⚠ SPREAD NOT A NUMBER",IF(AND(ISNUMBER($H270),$H270<0),"⚠ ENTER SPREAD AS POSITIVE","OK"))))))) -> ⚠ FAVORITE NOT IN GAME | S270: =IF(OR($B270="",$O270=""),"",IF(AsOfDate-$O270>StaleDays,"STALE","OK")) -> STALE
A271: 267 | B271: {=IFERROR(INDEX(SchedZone,MATCH($A271,SchedSeq,0),MAP!$B$6),"")} -> 2026_18_SEA_LA | C271: {=IF($B271="","",INDEX(SchedZone,MATCH($A271,SchedSeq,0),MAP!$B$4))} -> 18 | D271: {=IF($B271="","",INDEX(SchedZone,MATCH($A271,SchedSeq,0),MAP!$B$7))} -> 46397 | E271: {=IF($B271="","",IF(COUNTIF(Teams,INDEX(SchedZone,MATCH($A271,SchedSeq,0),MAP!$B$10))>0,INDEX(SchedZone,MATCH($A271,SchedSeq,0),MAP!$B$10),IFERROR(INDEX(LISTS!$D$2:$D$12,MATCH(INDEX(SchedZone,MATCH($A271,SchedSeq,0),MAP!$B$10),LISTS!$C$2:$C$12,0)),"⚠ "&INDEX(SchedZone,MATCH($A271,SchedSeq,0),MAP!$B$10))))} -> SEA | F271: {=IF($B271="","",IF(COUNTIF(Teams,INDEX(SchedZone,MATCH($A271,SchedSeq,0),MAP!$B$12))>0,INDEX(SchedZone,MATCH($A271,SchedSeq,0),MAP!$B$12),IFERROR(INDEX(LISTS!$D$2:$D$12,MATCH(INDEX(SchedZone,MATCH($A271,SchedSeq,0),MAP!$B$12),LISTS!$C$2:$C$12,0)),"⚠ "&INDEX(SchedZone,MATCH($A271,SchedSeq,0),MAP!$B$12))))} -> LA | G271: NE | H271: 14 | I271: 44.5 | N271: NFLVERSE-HIST (sample) | O271: 2026-01-01 | P271: SAMPLE — historical reference line, replace with Novig | Q271: =IF(OR($B271="",$G271="",$H271=""),"",IF($G271="Pick",0,IF($G271=$F271,-$H271,IF($G271=$E271,$H271,"")))) | R271: =IF($B271="","",IF(AND($G271="",$H271="",$I271=""),"",IF(AND($G271="",$H271<>""),"⚠ ADD FAVORITE",IF(AND($G271<>"",$G271<>"Pick",$G271<>$E271,$G271<>$F271),"⚠ FAVORITE NOT IN GAME",IF(AND($G271<>"",$H271=""),"⚠ SPREAD MISSING",IF(AND($H271<>"",NOT(ISNUMBER($H271))),"⚠ SPREAD NOT A NUMBER",IF(AND(ISNUMBER($H271),$H271<0),"⚠ ENTER SPREAD AS POSITIVE","OK"))))))) -> ⚠ FAVORITE NOT IN GAME | S271: =IF(OR($B271="",$O271=""),"",IF(AsOfDate-$O271>StaleDays,"STALE","OK")) -> STALE
A272: 268 | B272: {=IFERROR(INDEX(SchedZone,MATCH($A272,SchedSeq,0),MAP!$B$6),"")} -> 2026_18_CHI_MIN | C272: {=IF($B272="","",INDEX(SchedZone,MATCH($A272,SchedSeq,0),MAP!$B$4))} -> 18 | D272: {=IF($B272="","",INDEX(SchedZone,MATCH($A272,SchedSeq,0),MAP!$B$7))} -> 46397 | E272: {=IF($B272="","",IF(COUNTIF(Teams,INDEX(SchedZone,MATCH($A272,SchedSeq,0),MAP!$B$10))>0,INDEX(SchedZone,MATCH($A272,SchedSeq,0),MAP!$B$10),IFERROR(INDEX(LISTS!$D$2:$D$12,MATCH(INDEX(SchedZone,MATCH($A272,SchedSeq,0),MAP!$B$10),LISTS!$C$2:$C$12,0)),"⚠ "&INDEX(SchedZone,MATCH($A272,SchedSeq,0),MAP!$B$10))))} -> CHI | F272: {=IF($B272="","",IF(COUNTIF(Teams,INDEX(SchedZone,MATCH($A272,SchedSeq,0),MAP!$B$12))>0,INDEX(SchedZone,MATCH($A272,SchedSeq,0),MAP!$B$12),IFERROR(INDEX(LISTS!$D$2:$D$12,MATCH(INDEX(SchedZone,MATCH($A272,SchedSeq,0),MAP!$B$12),LISTS!$C$2:$C$12,0)),"⚠ "&INDEX(SchedZone,MATCH($A272,SchedSeq,0),MAP!$B$12))))} -> MIN | G272: DAL | H272: 3 | I272: 50.5 | N272: NFLVERSE-HIST (sample) | O272: 2026-01-01 | P272: SAMPLE — historical reference line, replace with Novig | Q272: =IF(OR($B272="",$G272="",$H272=""),"",IF($G272="Pick",0,IF($G272=$F272,-$H272,IF($G272=$E272,$H272,"")))) | R272: =IF($B272="","",IF(AND($G272="",$H272="",$I272=""),"",IF(AND($G272="",$H272<>""),"⚠ ADD FAVORITE",IF(AND($G272<>"",$G272<>"Pick",$G272<>$E272,$G272<>$F272),"⚠ FAVORITE NOT IN GAME",IF(AND($G272<>"",$H272=""),"⚠ SPREAD MISSING",IF(AND($H272<>"",NOT(ISNUMBER($H272))),"⚠ SPREAD NOT A NUMBER",IF(AND(ISNUMBER($H272),$H272<0),"⚠ ENTER SPREAD AS POSITIVE","OK"))))))) -> ⚠ FAVORITE NOT IN GAME | S272: =IF(OR($B272="",$O272=""),"",IF(AsOfDate-$O272>StaleDays,"STALE","OK")) -> STALE
... A276: 272 | B276: {=IFERROR(INDEX(SchedZone,MATCH($A276,SchedSeq,0),MAP!$B$6),"")} -> 2026_18_DAL_WAS | C276: {=IF($B276="","",INDEX(SchedZone,MATCH($A276,SchedSeq,0),MAP!$B$4))} -> 18 | D276: {=IF($B276="","",INDEX(SchedZone,MATCH($A276,SchedSeq,0),MAP!$B$7))} -> 46397 | E276: {=IF($B276="","",IF(COUNTIF(Teams,INDEX(SchedZone,MATCH($A276,SchedSeq,0),MAP!$B$10))>0,INDEX(SchedZone,MATCH($A276,SchedSeq,0),MAP!$B$10),IFERROR(INDEX(LISTS!$D$2:$D$12,MATCH(INDEX(SchedZone,MATCH($A276,SchedSeq,0),MAP!$B$10),LISTS!$C$2:$C$12,0)),"⚠ "&INDEX(SchedZone,MATCH($A276,SchedSeq,0),MAP!$B$10))))} -> DAL | F276: {=IF($B276="","",IF(COUNTIF(Teams,INDEX(SchedZone,MATCH($A276,SchedSeq,0),MAP!$B$12))>0,INDEX(SchedZone,MATCH($A276,SchedSeq,0),MAP!$B$12),IFERROR(INDEX(LISTS!$D$2:$D$12,MATCH(INDEX(SchedZone,MATCH($A276,SchedSeq,0),MAP!$B$12),LISTS!$C$2:$C$12,0)),"⚠ "&INDEX(SchedZone,MATCH($A276,SchedSeq,0),MAP!$B$12))))} -> WAS | G276: TB | H276: 3 | I276: 43.5 | N276: NFLVERSE-HIST (sample) | O276: 2026-01-01 | P276: SAMPLE — historical reference line, replace with Novig | Q276: =IF(OR($B276="",$G276="",$H276=""),"",IF($G276="Pick",0,IF($G276=$F276,-$H276,IF($G276=$E276,$H276,"")))) | R276: =IF($B276="","",IF(AND($G276="",$H276="",$I276=""),"",IF(AND($G276="",$H276<>""),"⚠ ADD FAVORITE",IF(AND($G276<>"",$G276<>"Pick",$G276<>$E276,$G276<>$F276),"⚠ FAVORITE NOT IN GAME",IF(AND($G276<>"",$H276=""),"⚠ SPREAD MISSING",IF(AND($H276<>"",NOT(ISNUMBER($H276))),"⚠ SPREAD NOT A NUMBER",IF(AND(ISNUMBER($H276),$H276<0),"⚠ ENTER SPREAD AS POSITIVE","OK"))))))) -> ⚠ FAVORITE NOT IN GAME | S276: =IF(OR($B276="",$O276=""),"",IF(AsOfDate-$O276>StaleDays,"STALE","OK")) -> STALE
A277: 273 | B277: {=IFERROR(INDEX(SchedZone,MATCH($A277,SchedSeq,0),MAP!$B$6),"")} | C277: {=IF($B277="","",INDEX(SchedZone,MATCH($A277,SchedSeq,0),MAP!$B$4))} | D277: {=IF($B277="","",INDEX(SchedZone,MATCH($A277,SchedSeq,0),MAP!$B$7))} | E277: {=IF($B277="","",IF(COUNTIF(Teams,INDEX(SchedZone,MATCH($A277,SchedSeq,0),MAP!$B$10))>0,INDEX(SchedZone,MATCH($A277,SchedSeq,0),MAP!$B$10),IFERROR(INDEX(LISTS!$D$2:$D$12,MATCH(INDEX(SchedZone,MATCH($A277,SchedSeq,0),MAP!$B$10),LISTS!$C$2:$C$12,0)),"⚠ "&INDEX(SchedZone,MATCH($A277,SchedSeq,0),MAP!$B$10))))} | F277: {=IF($B277="","",IF(COUNTIF(Teams,INDEX(SchedZone,MATCH($A277,SchedSeq,0),MAP!$B$12))>0,INDEX(SchedZone,MATCH($A277,SchedSeq,0),MAP!$B$12),IFERROR(INDEX(LISTS!$D$2:$D$12,MATCH(INDEX(SchedZone,MATCH($A277,SchedSeq,0),MAP!$B$12),LISTS!$C$2:$C$12,0)),"⚠ "&INDEX(SchedZone,MATCH($A277,SchedSeq,0),MAP!$B$12))))} | Q277: =IF(OR($B277="",$G277="",$H277=""),"",IF($G277="Pick",0,IF($G277=$F277,-$H277,IF($G277=$E277,$H277,"")))) | R277: =IF($B277="","",IF(AND($G277="",$H277="",$I277=""),"",IF(AND($G277="",$H277<>""),"⚠ ADD FAVORITE",IF(AND($G277<>"",$G277<>"Pick",$G277<>$E277,$G277<>$F277),"⚠ FAVORITE NOT IN GAME",IF(AND($G277<>"",$H277=""),"⚠ SPREAD MISSING",IF(AND($H277<>"",NOT(ISNUMBER($H277))),"⚠ SPREAD NOT A NUMBER",IF(AND(ISNUMBER($H277),$H277<0),"⚠ ENTER SPREAD AS POSITIVE","OK"))))))) | S277: =IF(OR($B277="",$O277=""),"",IF(AsOfDate-$O277>StaleDays,"STALE","OK"))
A278: 274 | B278: {=IFERROR(INDEX(SchedZone,MATCH($A278,SchedSeq,0),MAP!$B$6),"")} | C278: {=IF($B278="","",INDEX(SchedZone,MATCH($A278,SchedSeq,0),MAP!$B$4))} | D278: {=IF($B278="","",INDEX(SchedZone,MATCH($A278,SchedSeq,0),MAP!$B$7))} | E278: {=IF($B278="","",IF(COUNTIF(Teams,INDEX(SchedZone,MATCH($A278,SchedSeq,0),MAP!$B$10))>0,INDEX(SchedZone,MATCH($A278,SchedSeq,0),MAP!$B$10),IFERROR(INDEX(LISTS!$D$2:$D$12,MATCH(INDEX(SchedZone,MATCH($A278,SchedSeq,0),MAP!$B$10),LISTS!$C$2:$C$12,0)),"⚠ "&INDEX(SchedZone,MATCH($A278,SchedSeq,0),MAP!$B$10))))} | F278: {=IF($B278="","",IF(COUNTIF(Teams,INDEX(SchedZone,MATCH($A278,SchedSeq,0),MAP!$B$12))>0,INDEX(SchedZone,MATCH($A278,SchedSeq,0),MAP!$B$12),IFERROR(INDEX(LISTS!$D$2:$D$12,MATCH(INDEX(SchedZone,MATCH($A278,SchedSeq,0),MAP!$B$12),LISTS!$C$2:$C$12,0)),"⚠ "&INDEX(SchedZone,MATCH($A278,SchedSeq,0),MAP!$B$12))))} | Q278: =IF(OR($B278="",$G278="",$H278=""),"",IF($G278="Pick",0,IF($G278=$F278,-$H278,IF($G278=$E278,$H278,"")))) | R278: =IF($B278="","",IF(AND($G278="",$H278="",$I278=""),"",IF(AND($G278="",$H278<>""),"⚠ ADD FAVORITE",IF(AND($G278<>"",$G278<>"Pick",$G278<>$E278,$G278<>$F278),"⚠ FAVORITE NOT IN GAME",IF(AND($G278<>"",$H278=""),"⚠ SPREAD MISSING",IF(AND($H278<>"",NOT(ISNUMBER($H278))),"⚠ SPREAD NOT A NUMBER",IF(AND(ISNUMBER($H278),$H278<0),"⚠ ENTER SPREAD AS POSITIVE","OK"))))))) | S278: =IF(OR($B278="",$O278=""),"",IF(AsOfDate-$O278>StaleDays,"STALE","OK"))
A279: 275 | B279: {=IFERROR(INDEX(SchedZone,MATCH($A279,SchedSeq,0),MAP!$B$6),"")} | C279: {=IF($B279="","",INDEX(SchedZone,MATCH($A279,SchedSeq,0),MAP!$B$4))} | D279: {=IF($B279="","",INDEX(SchedZone,MATCH($A279,SchedSeq,0),MAP!$B$7))} | E279: {=IF($B279="","",IF(COUNTIF(Teams,INDEX(SchedZone,MATCH($A279,SchedSeq,0),MAP!$B$10))>0,INDEX(SchedZone,MATCH($A279,SchedSeq,0),MAP!$B$10),IFERROR(INDEX(LISTS!$D$2:$D$12,MATCH(INDEX(SchedZone,MATCH($A279,SchedSeq,0),MAP!$B$10),LISTS!$C$2:$C$12,0)),"⚠ "&INDEX(SchedZone,MATCH($A279,SchedSeq,0),MAP!$B$10))))} | F279: {=IF($B279="","",IF(COUNTIF(Teams,INDEX(SchedZone,MATCH($A279,SchedSeq,0),MAP!$B$12))>0,INDEX(SchedZone,MATCH($A279,SchedSeq,0),MAP!$B$12),IFERROR(INDEX(LISTS!$D$2:$D$12,MATCH(INDEX(SchedZone,MATCH($A279,SchedSeq,0),MAP!$B$12),LISTS!$C$2:$C$12,0)),"⚠ "&INDEX(SchedZone,MATCH($A279,SchedSeq,0),MAP!$B$12))))} | Q279: =IF(OR($B279="",$G279="",$H279=""),"",IF($G279="Pick",0,IF($G279=$F279,-$H279,IF($G279=$E279,$H279,"")))) | R279: =IF($B279="","",IF(AND($G279="",$H279="",$I279=""),"",IF(AND($G279="",$H279<>""),"⚠ ADD FAVORITE",IF(AND($G279<>"",$G279<>"Pick",$G279<>$E279,$G279<>$F279),"⚠ FAVORITE NOT IN GAME",IF(AND($G279<>"",$H279=""),"⚠ SPREAD MISSING",IF(AND($H279<>"",NOT(ISNUMBER($H279))),"⚠ SPREAD NOT A NUMBER",IF(AND(ISNUMBER($H279),$H279<0),"⚠ ENTER SPREAD AS POSITIVE","OK"))))))) | S279: =IF(OR($B279="",$O279=""),"",IF(AsOfDate-$O279>StaleDays,"STALE","OK"))
A280: 276 | B280: {=IFERROR(INDEX(SchedZone,MATCH($A280,SchedSeq,0),MAP!$B$6),"")} | C280: {=IF($B280="","",INDEX(SchedZone,MATCH($A280,SchedSeq,0),MAP!$B$4))} | D280: {=IF($B280="","",INDEX(SchedZone,MATCH($A280,SchedSeq,0),MAP!$B$7))} | E280: {=IF($B280="","",IF(COUNTIF(Teams,INDEX(SchedZone,MATCH($A280,SchedSeq,0),MAP!$B$10))>0,INDEX(SchedZone,MATCH($A280,SchedSeq,0),MAP!$B$10),IFERROR(INDEX(LISTS!$D$2:$D$12,MATCH(INDEX(SchedZone,MATCH($A280,SchedSeq,0),MAP!$B$10),LISTS!$C$2:$C$12,0)),"⚠ "&INDEX(SchedZone,MATCH($A280,SchedSeq,0),MAP!$B$10))))} | F280: {=IF($B280="","",IF(COUNTIF(Teams,INDEX(SchedZone,MATCH($A280,SchedSeq,0),MAP!$B$12))>0,INDEX(SchedZone,MATCH($A280,SchedSeq,0),MAP!$B$12),IFERROR(INDEX(LISTS!$D$2:$D$12,MATCH(INDEX(SchedZone,MATCH($A280,SchedSeq,0),MAP!$B$12),LISTS!$C$2:$C$12,0)),"⚠ "&INDEX(SchedZone,MATCH($A280,SchedSeq,0),MAP!$B$12))))} | Q280: =IF(OR($B280="",$G280="",$H280=""),"",IF($G280="Pick",0,IF($G280=$F280,-$H280,IF($G280=$E280,$H280,"")))) | R280: =IF($B280="","",IF(AND($G280="",$H280="",$I280=""),"",IF(AND($G280="",$H280<>""),"⚠ ADD FAVORITE",IF(AND($G280<>"",$G280<>"Pick",$G280<>$E280,$G280<>$F280),"⚠ FAVORITE NOT IN GAME",IF(AND($G280<>"",$H280=""),"⚠ SPREAD MISSING",IF(AND($H280<>"",NOT(ISNUMBER($H280))),"⚠ SPREAD NOT A NUMBER",IF(AND(ISNUMBER($H280),$H280<0),"⚠ ENTER SPREAD AS POSITIVE","OK"))))))) | S280: =IF(OR($B280="",$O280=""),"",IF(AsOfDate-$O280>StaleDays,"STALE","OK"))
A281: 277 | B281: {=IFERROR(INDEX(SchedZone,MATCH($A281,SchedSeq,0),MAP!$B$6),"")} | C281: {=IF($B281="","",INDEX(SchedZone,MATCH($A281,SchedSeq,0),MAP!$B$4))} | D281: {=IF($B281="","",INDEX(SchedZone,MATCH($A281,SchedSeq,0),MAP!$B$7))} | E281: {=IF($B281="","",IF(COUNTIF(Teams,INDEX(SchedZone,MATCH($A281,SchedSeq,0),MAP!$B$10))>0,INDEX(SchedZone,MATCH($A281,SchedSeq,0),MAP!$B$10),IFERROR(INDEX(LISTS!$D$2:$D$12,MATCH(INDEX(SchedZone,MATCH($A281,SchedSeq,0),MAP!$B$10),LISTS!$C$2:$C$12,0)),"⚠ "&INDEX(SchedZone,MATCH($A281,SchedSeq,0),MAP!$B$10))))} | F281: {=IF($B281="","",IF(COUNTIF(Teams,INDEX(SchedZone,MATCH($A281,SchedSeq,0),MAP!$B$12))>0,INDEX(SchedZone,MATCH($A281,SchedSeq,0),MAP!$B$12),IFERROR(INDEX(LISTS!$D$2:$D$12,MATCH(INDEX(SchedZone,MATCH($A281,SchedSeq,0),MAP!$B$12),LISTS!$C$2:$C$12,0)),"⚠ "&INDEX(SchedZone,MATCH($A281,SchedSeq,0),MAP!$B$12))))} | Q281: =IF(OR($B281="",$G281="",$H281=""),"",IF($G281="Pick",0,IF($G281=$F281,-$H281,IF($G281=$E281,$H281,"")))) | R281: =IF($B281="","",IF(AND($G281="",$H281="",$I281=""),"",IF(AND($G281="",$H281<>""),"⚠ ADD FAVORITE",IF(AND($G281<>"",$G281<>"Pick",$G281<>$E281,$G281<>$F281),"⚠ FAVORITE NOT IN GAME",IF(AND($G281<>"",$H281=""),"⚠ SPREAD MISSING",IF(AND($H281<>"",NOT(ISNUMBER($H281))),"⚠ SPREAD NOT A NUMBER",IF(AND(ISNUMBER($H281),$H281<0),"⚠ ENTER SPREAD AS POSITIVE","OK"))))))) | S281: =IF(OR($B281="",$O281=""),"",IF(AsOfDate-$O281>StaleDays,"STALE","OK"))
A282: 278 | B282: {=IFERROR(INDEX(SchedZone,MATCH($A282,SchedSeq,0),MAP!$B$6),"")} | C282: {=IF($B282="","",INDEX(SchedZone,MATCH($A282,SchedSeq,0),MAP!$B$4))} | D282: {=IF($B282="","",INDEX(SchedZone,MATCH($A282,SchedSeq,0),MAP!$B$7))} | E282: {=IF($B282="","",IF(COUNTIF(Teams,INDEX(SchedZone,MATCH($A282,SchedSeq,0),MAP!$B$10))>0,INDEX(SchedZone,MATCH($A282,SchedSeq,0),MAP!$B$10),IFERROR(INDEX(LISTS!$D$2:$D$12,MATCH(INDEX(SchedZone,MATCH($A282,SchedSeq,0),MAP!$B$10),LISTS!$C$2:$C$12,0)),"⚠ "&INDEX(SchedZone,MATCH($A282,SchedSeq,0),MAP!$B$10))))} | F282: {=IF($B282="","",IF(COUNTIF(Teams,INDEX(SchedZone,MATCH($A282,SchedSeq,0),MAP!$B$12))>0,INDEX(SchedZone,MATCH($A282,SchedSeq,0),MAP!$B$12),IFERROR(INDEX(LISTS!$D$2:$D$12,MATCH(INDEX(SchedZone,MATCH($A282,SchedSeq,0),MAP!$B$12),LISTS!$C$2:$C$12,0)),"⚠ "&INDEX(SchedZone,MATCH($A282,SchedSeq,0),MAP!$B$12))))} | Q282: =IF(OR($B282="",$G282="",$H282=""),"",IF($G282="Pick",0,IF($G282=$F282,-$H282,IF($G282=$E282,$H282,"")))) | R282: =IF($B282="","",IF(AND($G282="",$H282="",$I282=""),"",IF(AND($G282="",$H282<>""),"⚠ ADD FAVORITE",IF(AND($G282<>"",$G282<>"Pick",$G282<>$E282,$G282<>$F282),"⚠ FAVORITE NOT IN GAME",IF(AND($G282<>"",$H282=""),"⚠ SPREAD MISSING",IF(AND($H282<>"",NOT(ISNUMBER($H282))),"⚠ SPREAD NOT A NUMBER",IF(AND(ISNUMBER($H282),$H282<0),"⚠ ENTER SPREAD AS POSITIVE","OK"))))))) | S282: =IF(OR($B282="",$O282=""),"",IF(AsOfDate-$O282>StaleDays,"STALE","OK"))
A283: 279 | B283: {=IFERROR(INDEX(SchedZone,MATCH($A283,SchedSeq,0),MAP!$B$6),"")} | C283: {=IF($B283="","",INDEX(SchedZone,MATCH($A283,SchedSeq,0),MAP!$B$4))} | D283: {=IF($B283="","",INDEX(SchedZone,MATCH($A283,SchedSeq,0),MAP!$B$7))} | E283: {=IF($B283="","",IF(COUNTIF(Teams,INDEX(SchedZone,MATCH($A283,SchedSeq,0),MAP!$B$10))>0,INDEX(SchedZone,MATCH($A283,SchedSeq,0),MAP!$B$10),IFERROR(INDEX(LISTS!$D$2:$D$12,MATCH(INDEX(SchedZone,MATCH($A283,SchedSeq,0),MAP!$B$10),LISTS!$C$2:$C$12,0)),"⚠ "&INDEX(SchedZone,MATCH($A283,SchedSeq,0),MAP!$B$10))))} | F283: {=IF($B283="","",IF(COUNTIF(Teams,INDEX(SchedZone,MATCH($A283,SchedSeq,0),MAP!$B$12))>0,INDEX(SchedZone,MATCH($A283,SchedSeq,0),MAP!$B$12),IFERROR(INDEX(LISTS!$D$2:$D$12,MATCH(INDEX(SchedZone,MATCH($A283,SchedSeq,0),MAP!$B$12),LISTS!$C$2:$C$12,0)),"⚠ "&INDEX(SchedZone,MATCH($A283,SchedSeq,0),MAP!$B$12))))} | Q283: =IF(OR($B283="",$G283="",$H283=""),"",IF($G283="Pick",0,IF($G283=$F283,-$H283,IF($G283=$E283,$H283,"")))) | R283: =IF($B283="","",IF(AND($G283="",$H283="",$I283=""),"",IF(AND($G283="",$H283<>""),"⚠ ADD FAVORITE",IF(AND($G283<>"",$G283<>"Pick",$G283<>$E283,$G283<>$F283),"⚠ FAVORITE NOT IN GAME",IF(AND($G283<>"",$H283=""),"⚠ SPREAD MISSING",IF(AND($H283<>"",NOT(ISNUMBER($H283))),"⚠ SPREAD NOT A NUMBER",IF(AND(ISNUMBER($H283),$H283<0),"⚠ ENTER SPREAD AS POSITIVE","OK"))))))) | S283: =IF(OR($B283="",$O283=""),"",IF(AsOfDate-$O283>StaleDays,"STALE","OK"))
A284: 280 | B284: {=IFERROR(INDEX(SchedZone,MATCH($A284,SchedSeq,0),MAP!$B$6),"")} | C284: {=IF($B284="","",INDEX(SchedZone,MATCH($A284,SchedSeq,0),MAP!$B$4))} | D284: {=IF($B284="","",INDEX(SchedZone,MATCH($A284,SchedSeq,0),MAP!$B$7))} | E284: {=IF($B284="","",IF(COUNTIF(Teams,INDEX(SchedZone,MATCH($A284,SchedSeq,0),MAP!$B$10))>0,INDEX(SchedZone,MATCH($A284,SchedSeq,0),MAP!$B$10),IFERROR(INDEX(LISTS!$D$2:$D$12,MATCH(INDEX(SchedZone,MATCH($A284,SchedSeq,0),MAP!$B$10),LISTS!$C$2:$C$12,0)),"⚠ "&INDEX(SchedZone,MATCH($A284,SchedSeq,0),MAP!$B$10))))} | F284: {=IF($B284="","",IF(COUNTIF(Teams,INDEX(SchedZone,MATCH($A284,SchedSeq,0),MAP!$B$12))>0,INDEX(SchedZone,MATCH($A284,SchedSeq,0),MAP!$B$12),IFERROR(INDEX(LISTS!$D$2:$D$12,MATCH(INDEX(SchedZone,MATCH($A284,SchedSeq,0),MAP!$B$12),LISTS!$C$2:$C$12,0)),"⚠ "&INDEX(SchedZone,MATCH($A284,SchedSeq,0),MAP!$B$12))))} | Q284: =IF(OR($B284="",$G284="",$H284=""),"",IF($G284="Pick",0,IF($G284=$F284,-$H284,IF($G284=$E284,$H284,"")))) | R284: =IF($B284="","",IF(AND($G284="",$H284="",$I284=""),"",IF(AND($G284="",$H284<>""),"⚠ ADD FAVORITE",IF(AND($G284<>"",$G284<>"Pick",$G284<>$E284,$G284<>$F284),"⚠ FAVORITE NOT IN GAME",IF(AND($G284<>"",$H284=""),"⚠ SPREAD MISSING",IF(AND($H284<>"",NOT(ISNUMBER($H284))),"⚠ SPREAD NOT A NUMBER",IF(AND(ISNUMBER($H284),$H284<0),"⚠ ENTER SPREAD AS POSITIVE","OK"))))))) | S284: =IF(OR($B284="",$O284=""),"",IF(AsOfDate-$O284>StaleDays,"STALE","OK"))
A285: 281 | B285: {=IFERROR(INDEX(SchedZone,MATCH($A285,SchedSeq,0),MAP!$B$6),"")} | C285: {=IF($B285="","",INDEX(SchedZone,MATCH($A285,SchedSeq,0),MAP!$B$4))} | D285: {=IF($B285="","",INDEX(SchedZone,MATCH($A285,SchedSeq,0),MAP!$B$7))} | E285: {=IF($B285="","",IF(COUNTIF(Teams,INDEX(SchedZone,MATCH($A285,SchedSeq,0),MAP!$B$10))>0,INDEX(SchedZone,MATCH($A285,SchedSeq,0),MAP!$B$10),IFERROR(INDEX(LISTS!$D$2:$D$12,MATCH(INDEX(SchedZone,MATCH($A285,SchedSeq,0),MAP!$B$10),LISTS!$C$2:$C$12,0)),"⚠ "&INDEX(SchedZone,MATCH($A285,SchedSeq,0),MAP!$B$10))))} | F285: {=IF($B285="","",IF(COUNTIF(Teams,INDEX(SchedZone,MATCH($A285,SchedSeq,0),MAP!$B$12))>0,INDEX(SchedZone,MATCH($A285,SchedSeq,0),MAP!$B$12),IFERROR(INDEX(LISTS!$D$2:$D$12,MATCH(INDEX(SchedZone,MATCH($A285,SchedSeq,0),MAP!$B$12),LISTS!$C$2:$C$12,0)),"⚠ "&INDEX(SchedZone,MATCH($A285,SchedSeq,0),MAP!$B$12))))} | Q285: =IF(OR($B285="",$G285="",$H285=""),"",IF($G285="Pick",0,IF($G285=$F285,-$H285,IF($G285=$E285,$H285,"")))) | R285: =IF($B285="","",IF(AND($G285="",$H285="",$I285=""),"",IF(AND($G285="",$H285<>""),"⚠ ADD FAVORITE",IF(AND($G285<>"",$G285<>"Pick",$G285<>$E285,$G285<>$F285),"⚠ FAVORITE NOT IN GAME",IF(AND($G285<>"",$H285=""),"⚠ SPREAD MISSING",IF(AND($H285<>"",NOT(ISNUMBER($H285))),"⚠ SPREAD NOT A NUMBER",IF(AND(ISNUMBER($H285),$H285<0),"⚠ ENTER SPREAD AS POSITIVE","OK"))))))) | S285: =IF(OR($B285="",$O285=""),"",IF(AsOfDate-$O285>StaleDays,"STALE","OK"))
A286: 282 | B286: {=IFERROR(INDEX(SchedZone,MATCH($A286,SchedSeq,0),MAP!$B$6),"")} | C286: {=IF($B286="","",INDEX(SchedZone,MATCH($A286,SchedSeq,0),MAP!$B$4))} | D286: {=IF($B286="","",INDEX(SchedZone,MATCH($A286,SchedSeq,0),MAP!$B$7))} | E286: {=IF($B286="","",IF(COUNTIF(Teams,INDEX(SchedZone,MATCH($A286,SchedSeq,0),MAP!$B$10))>0,INDEX(SchedZone,MATCH($A286,SchedSeq,0),MAP!$B$10),IFERROR(INDEX(LISTS!$D$2:$D$12,MATCH(INDEX(SchedZone,MATCH($A286,SchedSeq,0),MAP!$B$10),LISTS!$C$2:$C$12,0)),"⚠ "&INDEX(SchedZone,MATCH($A286,SchedSeq,0),MAP!$B$10))))} | F286: {=IF($B286="","",IF(COUNTIF(Teams,INDEX(SchedZone,MATCH($A286,SchedSeq,0),MAP!$B$12))>0,INDEX(SchedZone,MATCH($A286,SchedSeq,0),MAP!$B$12),IFERROR(INDEX(LISTS!$D$2:$D$12,MATCH(INDEX(SchedZone,MATCH($A286,SchedSeq,0),MAP!$B$12),LISTS!$C$2:$C$12,0)),"⚠ "&INDEX(SchedZone,MATCH($A286,SchedSeq,0),MAP!$B$12))))} | Q286: =IF(OR($B286="",$G286="",$H286=""),"",IF($G286="Pick",0,IF($G286=$F286,-$H286,IF($G286=$E286,$H286,"")))) | R286: =IF($B286="","",IF(AND($G286="",$H286="",$I286=""),"",IF(AND($G286="",$H286<>""),"⚠ ADD FAVORITE",IF(AND($G286<>"",$G286<>"Pick",$G286<>$E286,$G286<>$F286),"⚠ FAVORITE NOT IN GAME",IF(AND($G286<>"",$H286=""),"⚠ SPREAD MISSING",IF(AND($H286<>"",NOT(ISNUMBER($H286))),"⚠ SPREAD NOT A NUMBER",IF(AND(ISNUMBER($H286),$H286<0),"⚠ ENTER SPREAD AS POSITIVE","OK"))))))) | S286: =IF(OR($B286="",$O286=""),"",IF(AsOfDate-$O286>StaleDays,"STALE","OK"))
A287: 283 | B287: {=IFERROR(INDEX(SchedZone,MATCH($A287,SchedSeq,0),MAP!$B$6),"")} | C287: {=IF($B287="","",INDEX(SchedZone,MATCH($A287,SchedSeq,0),MAP!$B$4))} | D287: {=IF($B287="","",INDEX(SchedZone,MATCH($A287,SchedSeq,0),MAP!$B$7))} | E287: {=IF($B287="","",IF(COUNTIF(Teams,INDEX(SchedZone,MATCH($A287,SchedSeq,0),MAP!$B$10))>0,INDEX(SchedZone,MATCH($A287,SchedSeq,0),MAP!$B$10),IFERROR(INDEX(LISTS!$D$2:$D$12,MATCH(INDEX(SchedZone,MATCH($A287,SchedSeq,0),MAP!$B$10),LISTS!$C$2:$C$12,0)),"⚠ "&INDEX(SchedZone,MATCH($A287,SchedSeq,0),MAP!$B$10))))} | F287: {=IF($B287="","",IF(COUNTIF(Teams,INDEX(SchedZone,MATCH($A287,SchedSeq,0),MAP!$B$12))>0,INDEX(SchedZone,MATCH($A287,SchedSeq,0),MAP!$B$12),IFERROR(INDEX(LISTS!$D$2:$D$12,MATCH(INDEX(SchedZone,MATCH($A287,SchedSeq,0),MAP!$B$12),LISTS!$C$2:$C$12,0)),"⚠ "&INDEX(SchedZone,MATCH($A287,SchedSeq,0),MAP!$B$12))))} | Q287: =IF(OR($B287="",$G287="",$H287=""),"",IF($G287="Pick",0,IF($G287=$F287,-$H287,IF($G287=$E287,$H287,"")))) | R287: =IF($B287="","",IF(AND($G287="",$H287="",$I287=""),"",IF(AND($G287="",$H287<>""),"⚠ ADD FAVORITE",IF(AND($G287<>"",$G287<>"Pick",$G287<>$E287,$G287<>$F287),"⚠ FAVORITE NOT IN GAME",IF(AND($G287<>"",$H287=""),"⚠ SPREAD MISSING",IF(AND($H287<>"",NOT(ISNUMBER($H287))),"⚠ SPREAD NOT A NUMBER",IF(AND(ISNUMBER($H287),$H287<0),"⚠ ENTER SPREAD AS POSITIVE","OK"))))))) | S287: =IF(OR($B287="",$O287=""),"",IF(AsOfDate-$O287>StaleDays,"STALE","OK"))
A288: 284 | B288: {=IFERROR(INDEX(SchedZone,MATCH($A288,SchedSeq,0),MAP!$B$6),"")} | C288: {=IF($B288="","",INDEX(SchedZone,MATCH($A288,SchedSeq,0),MAP!$B$4))} | D288: {=IF($B288="","",INDEX(SchedZone,MATCH($A288,SchedSeq,0),MAP!$B$7))} | E288: {=IF($B288="","",IF(COUNTIF(Teams,INDEX(SchedZone,MATCH($A288,SchedSeq,0),MAP!$B$10))>0,INDEX(SchedZone,MATCH($A288,SchedSeq,0),MAP!$B$10),IFERROR(INDEX(LISTS!$D$2:$D$12,MATCH(INDEX(SchedZone,MATCH($A288,SchedSeq,0),MAP!$B$10),LISTS!$C$2:$C$12,0)),"⚠ "&INDEX(SchedZone,MATCH($A288,SchedSeq,0),MAP!$B$10))))} | F288: {=IF($B288="","",IF(COUNTIF(Teams,INDEX(SchedZone,MATCH($A288,SchedSeq,0),MAP!$B$12))>0,INDEX(SchedZone,MATCH($A288,SchedSeq,0),MAP!$B$12),IFERROR(INDEX(LISTS!$D$2:$D$12,MATCH(INDEX(SchedZone,MATCH($A288,SchedSeq,0),MAP!$B$12),LISTS!$C$2:$C$12,0)),"⚠ "&INDEX(SchedZone,MATCH($A288,SchedSeq,0),MAP!$B$12))))} | Q288: =IF(OR($B288="",$G288="",$H288=""),"",IF($G288="Pick",0,IF($G288=$F288,-$H288,IF($G288=$E288,$H288,"")))) | R288: =IF($B288="","",IF(AND($G288="",$H288="",$I288=""),"",IF(AND($G288="",$H288<>""),"⚠ ADD FAVORITE",IF(AND($G288<>"",$G288<>"Pick",$G288<>$E288,$G288<>$F288),"⚠ FAVORITE NOT IN GAME",IF(AND($G288<>"",$H288=""),"⚠ SPREAD MISSING",IF(AND($H288<>"",NOT(ISNUMBER($H288))),"⚠ SPREAD NOT A NUMBER",IF(AND(ISNUMBER($H288),$H288<0),"⚠ ENTER SPREAD AS POSITIVE","OK"))))))) | S288: =IF(OR($B288="",$O288=""),"",IF(AsOfDate-$O288>StaleDays,"STALE","OK"))
... A304: 300 | B304: {=IFERROR(INDEX(SchedZone,MATCH($A304,SchedSeq,0),MAP!$B$6),"")} | C304: {=IF($B304="","",INDEX(SchedZone,MATCH($A304,SchedSeq,0),MAP!$B$4))} | D304: {=IF($B304="","",INDEX(SchedZone,MATCH($A304,SchedSeq,0),MAP!$B$7))} | E304: {=IF($B304="","",IF(COUNTIF(Teams,INDEX(SchedZone,MATCH($A304,SchedSeq,0),MAP!$B$10))>0,INDEX(SchedZone,MATCH($A304,SchedSeq,0),MAP!$B$10),IFERROR(INDEX(LISTS!$D$2:$D$12,MATCH(INDEX(SchedZone,MATCH($A304,SchedSeq,0),MAP!$B$10),LISTS!$C$2:$C$12,0)),"⚠ "&INDEX(SchedZone,MATCH($A304,SchedSeq,0),MAP!$B$10))))} | F304: {=IF($B304="","",IF(COUNTIF(Teams,INDEX(SchedZone,MATCH($A304,SchedSeq,0),MAP!$B$12))>0,INDEX(SchedZone,MATCH($A304,SchedSeq,0),MAP!$B$12),IFERROR(INDEX(LISTS!$D$2:$D$12,MATCH(INDEX(SchedZone,MATCH($A304,SchedSeq,0),MAP!$B$12),LISTS!$C$2:$C$12,0)),"⚠ "&INDEX(SchedZone,MATCH($A304,SchedSeq,0),MAP!$B$12))))} | Q304: =IF(OR($B304="",$G304="",$H304=""),"",IF($G304="Pick",0,IF($G304=$F304,-$H304,IF($G304=$E304,$H304,"")))) | R304: =IF($B304="","",IF(AND($G304="",$H304="",$I304=""),"",IF(AND($G304="",$H304<>""),"⚠ ADD FAVORITE",IF(AND($G304<>"",$G304<>"Pick",$G304<>$E304,$G304<>$F304),"⚠ FAVORITE NOT IN GAME",IF(AND($G304<>"",$H304=""),"⚠ SPREAD MISSING",IF(AND($H304<>"",NOT(ISNUMBER($H304))),"⚠ SPREAD NOT A NUMBER",IF(AND(ISNUMBER($H304),$H304<0),"⚠ ENTER SPREAD AS POSITIVE","OK"))))))) | S304: =IF(OR($B304="",$O304=""),"",IF(AsOfDate-$O304>StaleDays,"STALE","OK"))

Sheet ADJUSTMENTS
A1: MANUAL ADJUSTMENTS — every subjective point, documented and reversible
A2: One row per adjustment. Pick the team it FAVORS-or-HURTS (sign of the point value: + helps that team, − hurts). Spread effect applies to that team; totals effect applies to the game total. Adjustments only count when Active = Y and the game week is at/before the expiration week. The ENGINE nets home-minus-away automatically. Weather: no reliable pre-game weather exists in the source files — enter weather as a category here (roof type is shown in the ENGINE as a prompt).
A4: GameID (paste from ENGINE) | B4: Team | C4: Category | D4: Points (+/-) | E4: Spread effect (auto) | F4: Total effect (+/-) | G4: Explanation (required) | H4: Source | I4: Entered by | J4: Date | K4: Expires wk | L4: Active (Y/N) | M4: EffActive (auto) | N4: Check
E5: =IF(OR($A5="",$D5=""),0,$D5) -> 0 | M5: {=IF(OR($A5="",$L5<>"Y"),0,IF($K5="",1,IF(IFERROR(INDEX(SchedZone,MATCH($A5,INDEX(SchedZone,0,MAP!$B$6),0),MAP!$B$4),999)<=$K5,1,0)))} -> 0 | N5: =IF($A5="","",IF($G5="","⚠ EXPLANATION REQUIRED",IF(AND($D5<>"",ABS($D5)>AdjCap),"⚠ LARGE — VERIFY","")))
E6: =IF(OR($A6="",$D6=""),0,$D6) -> 0 | M6: {=IF(OR($A6="",$L6<>"Y"),0,IF($K6="",1,IF(IFERROR(INDEX(SchedZone,MATCH($A6,INDEX(SchedZone,0,MAP!$B$6),0),MAP!$B$4),999)<=$K6,1,0)))} -> 0 | N6: =IF($A6="","",IF($G6="","⚠ EXPLANATION REQUIRED",IF(AND($D6<>"",ABS($D6)>AdjCap),"⚠ LARGE — VERIFY","")))
E7: =IF(OR($A7="",$D7=""),0,$D7) -> 0 | M7: {=IF(OR($A7="",$L7<>"Y"),0,IF($K7="",1,IF(IFERROR(INDEX(SchedZone,MATCH($A7,INDEX(SchedZone,0,MAP!$B$6),0),MAP!$B$4),999)<=$K7,1,0)))} -> 0 | N7: =IF($A7="","",IF($G7="","⚠ EXPLANATION REQUIRED",IF(AND($D7<>"",ABS($D7)>AdjCap),"⚠ LARGE — VERIFY","")))
E8: =IF(OR($A8="",$D8=""),0,$D8) -> 0 | M8: {=IF(OR($A8="",$L8<>"Y"),0,IF($K8="",1,IF(IFERROR(INDEX(SchedZone,MATCH($A8,INDEX(SchedZone,0,MAP!$B$6),0),MAP!$B$4),999)<=$K8,1,0)))} -> 0 | N8: =IF($A8="","",IF($G8="","⚠ EXPLANATION REQUIRED",IF(AND($D8<>"",ABS($D8)>AdjCap),"⚠ LARGE — VERIFY","")))
E9: =IF(OR($A9="",$D9=""),0,$D9) -> 0 | M9: {=IF(OR($A9="",$L9<>"Y"),0,IF($K9="",1,IF(IFERROR(INDEX(SchedZone,MATCH($A9,INDEX(SchedZone,0,MAP!$B$6),0),MAP!$B$4),999)<=$K9,1,0)))} -> 0 | N9: =IF($A9="","",IF($G9="","⚠ EXPLANATION REQUIRED",IF(AND($D9<>"",ABS($D9)>AdjCap),"⚠ LARGE — VERIFY","")))
E10: =IF(OR($A10="",$D10=""),0,$D10) -> 0 | M10: {=IF(OR($A10="",$L10<>"Y"),0,IF($K10="",1,IF(IFERROR(INDEX(SchedZone,MATCH($A10,INDEX(SchedZone,0,MAP!$B$6),0),MAP!$B$4),999)<=$K10,1,0)))} -> 0 | N10: =IF($A10="","",IF($G10="","⚠ EXPLANATION REQUIRED",IF(AND($D10<>"",ABS($D10)>AdjCap),"⚠ LARGE — VERIFY","")))
E11: =IF(OR($A11="",$D11=""),0,$D11) -> 0 | M11: {=IF(OR($A11="",$L11<>"Y"),0,IF($K11="",1,IF(IFERROR(INDEX(SchedZone,MATCH($A11,INDEX(SchedZone,0,MAP!$B$6),0),MAP!$B$4),999)<=$K11,1,0)))} -> 0 | N11: =IF($A11="","",IF($G11="","⚠ EXPLANATION REQUIRED",IF(AND($D11<>"",ABS($D11)>AdjCap),"⚠ LARGE — VERIFY","")))
E12: =IF(OR($A12="",$D12=""),0,$D12) -> 0 | M12: {=IF(OR($A12="",$L12<>"Y"),0,IF($K12="",1,IF(IFERROR(INDEX(SchedZone,MATCH($A12,INDEX(SchedZone,0,MAP!$B$6),0),MAP!$B$4),999)<=$K12,1,0)))} -> 0 | N12: =IF($A12="","",IF($G12="","⚠ EXPLANATION REQUIRED",IF(AND($D12<>"",ABS($D12)>AdjCap),"⚠ LARGE — VERIFY","")))
E13: =IF(OR($A13="",$D13=""),0,$D13) -> 0 | M13: {=IF(OR($A13="",$L13<>"Y"),0,IF($K13="",1,IF(IFERROR(INDEX(SchedZone,MATCH($A13,INDEX(SchedZone,0,MAP!$B$6),0),MAP!$B$4),999)<=$K13,1,0)))} -> 0 | N13: =IF($A13="","",IF($G13="","⚠ EXPLANATION REQUIRED",IF(AND($D13<>"",ABS($D13)>AdjCap),"⚠ LARGE — VERIFY","")))
E14: =IF(OR($A14="",$D14=""),0,$D14) -> 0 | M14: {=IF(OR($A14="",$L14<>"Y"),0,IF($K14="",1,IF(IFERROR(INDEX(SchedZone,MATCH($A14,INDEX(SchedZone,0,MAP!$B$6),0),MAP!$B$4),999)<=$K14,1,0)))} -> 0 | N14: =IF($A14="","",IF($G14="","⚠ EXPLANATION REQUIRED",IF(AND($D14<>"",ABS($D14)>AdjCap),"⚠ LARGE — VERIFY","")))
E15: =IF(OR($A15="",$D15=""),0,$D15) -> 0 | M15: {=IF(OR($A15="",$L15<>"Y"),0,IF($K15="",1,IF(IFERROR(INDEX(SchedZone,MATCH($A15,INDEX(SchedZone,0,MAP!$B$6),0),MAP!$B$4),999)<=$K15,1,0)))} -> 0 | N15: =IF($A15="","",IF($G15="","⚠ EXPLANATION REQUIRED",IF(AND($D15<>"",ABS($D15)>AdjCap),"⚠ LARGE — VERIFY","")))
E16: =IF(OR($A16="",$D16=""),0,$D16) -> 0 | M16: {=IF(OR($A16="",$L16<>"Y"),0,IF($K16="",1,IF(IFERROR(INDEX(SchedZone,MATCH($A16,INDEX(SchedZone,0,MAP!$B$6),0),MAP!$B$4),999)<=$K16,1,0)))} -> 0 | N16: =IF($A16="","",IF($G16="","⚠ EXPLANATION REQUIRED",IF(AND($D16<>"",ABS($D16)>AdjCap),"⚠ LARGE — VERIFY","")))
... E104: =IF(OR($A104="",$D104=""),0,$D104) -> 0 | M104: {=IF(OR($A104="",$L104<>"Y"),0,IF($K104="",1,IF(IFERROR(INDEX(SchedZone,MATCH($A104,INDEX(SchedZone,0,MAP!$B$6),0),MAP!$B$4),999)<=$K104,1,0)))} -> 0 | N104: =IF($A104="","",IF($G104="","⚠ EXPLANATION REQUIRED",IF(AND($D104<>"",ABS($D104)>AdjCap),"⚠ LARGE — VERIFY","")))

Sheet QB VALUES
A1: QB VALUES — baseline-delta architecture
A2: Team ratings are stored WITH the baseline QB; only the active-vs-baseline delta moves projections. v1.1: every row also needs "Reviewed for season" = the current season and a fresh Last-update date. Any team failing either check throws its games into QB UNCERTAIN — this is the guard that stops carried-over 2025 QBs from silently projecting 2026 Week 1.
A4: Team | B4: Baseline QB | C4: Baseline value (pts) | D4: Active QB | E4: Active value (pts) | F4: Delta (pts) | G4: Spread effect | H4: Total effect | I4: Confidence | J4: Source | K4: Last update | L4: Check | M4: Reviewed for season | N4: QBFlag (auto)
A5: ARI | B5: Jacoby Brissett | C5: 1.5 | D5: Jacoby Brissett | E5: 1.5 | F5: =IF(OR($E5="",$C5=""),0,$E5-$C5) -> 0 | G5: =$F5 -> 0 | H5: =ROUND($F5*QBTotFactor,2) -> 0 | I5: Low | J5: ESPN roster preview: Brissett expected; Minshew/Beck behind — TTW scale | K5: 46216 | L5: =IF(ABS($F5)>QBDeltaCap,"⚠ DELTA > CAP — verify",IF($D5="","⚠ ACTIVE QB BLANK",IF($M5<>CurrentSeason,"⚠ NOT REVIEWED FOR "&CurrentSeason,IF(AND($K5<>"",AsOfDate-$K5>QBStaleDays),"⚠ STALE — REVIEW","")))) | M5: 2026 | N5: =IF(OR($D5="",$I5="Low",$M5<>CurrentSeason,AND($K5<>"",AsOfDate-$K5>QBStaleDays)),1,0) -> 1
A6: ATL | B6: Tua Tagovailoa | C6: 3 | D6: Tua Tagovailoa | E6: 3 | F6: =IF(OR($E6="",$C6=""),0,$E6-$C6) -> 0 | G6: =$F6 -> 0 | H6: =ROUND($F6*QBTotFactor,2) -> 0 | I6: Low | J6: Falcons camp: Tua/Penix battle; Tua slight projection — TTW scale | K6: 46216 | L6: =IF(ABS($F6)>QBDeltaCap,"⚠ DELTA > CAP — verify",IF($D6="","⚠ ACTIVE QB BLANK",IF($M6<>CurrentSeason,"⚠ NOT REVIEWED FOR "&CurrentSeason,IF(AND($K6<>"",AsOfDate-$K6>QBStaleDays),"⚠ STALE — REVIEW","")))) | M6: 2026 | N6: =IF(OR($D6="",$I6="Low",$M6<>CurrentSeason,AND($K6<>"",AsOfDate-$K6>QBStaleDays)),1,0) -> 1
A7: BAL | B7: Lamar Jackson | C7: 5.75 | D7: Lamar Jackson | E7: 5.75 | F7: =IF(OR($E7="",$C7=""),0,$E7-$C7) -> 0 | G7: =$F7 -> 0 | H7: =ROUND($F7*QBTotFactor,2) -> 0 | I7: High | J7: ESPN exec/scout 2026 QB survey — TTW scale | K7: 46216 | L7: =IF(ABS($F7)>QBDeltaCap,"⚠ DELTA > CAP — verify",IF($D7="","⚠ ACTIVE QB BLANK",IF($M7<>CurrentSeason,"⚠ NOT REVIEWED FOR "&CurrentSeason,IF(AND($K7<>"",AsOfDate-$K7>QBStaleDays),"⚠ STALE — REVIEW","")))) | M7: 2026 | N7: =IF(OR($D7="",$I7="Low",$M7<>CurrentSeason,AND($K7<>"",AsOfDate-$K7>QBStaleDays)),1,0) -> 0
A8: BUF | B8: Josh Allen | C8: 6.5 | D8: Josh Allen | E8: 6.5 | F8: =IF(OR($E8="",$C8=""),0,$E8-$C8) -> 0 | G8: =$F8 -> 0 | H8: =ROUND($F8*QBTotFactor,2) -> 0 | I8: High | J8: ESPN exec/scout 2026 QB survey (#1) — TTW scale | K8: 46216 | L8: =IF(ABS($F8)>QBDeltaCap,"⚠ DELTA > CAP — verify",IF($D8="","⚠ ACTIVE QB BLANK",IF($M8<>CurrentSeason,"⚠ NOT REVIEWED FOR "&CurrentSeason,IF(AND($K8<>"",AsOfDate-$K8>QBStaleDays),"⚠ STALE — REVIEW","")))) | M8: 2026 | N8: =IF(OR($D8="",$I8="Low",$M8<>CurrentSeason,AND($K8<>"",AsOfDate-$K8>QBStaleDays)),1,0) -> 0
A9: CAR | B9: Bryce Young | C9: 2.25 | D9: Bryce Young | E9: 2.25 | F9: =IF(OR($E9="",$C9=""),0,$E9-$C9) -> 0 | G9: =$F9 -> 0 | H9: =ROUND($F9*QBTotFactor,2) -> 0 | I9: High | J9: PFF/WCG 2026 QB ranking — TTW scale | K9: 46216 | L9: =IF(ABS($F9)>QBDeltaCap,"⚠ DELTA > CAP — verify",IF($D9="","⚠ ACTIVE QB BLANK",IF($M9<>CurrentSeason,"⚠ NOT REVIEWED FOR "&CurrentSeason,IF(AND($K9<>"",AsOfDate-$K9>QBStaleDays),"⚠ STALE — REVIEW","")))) | M9: 2026 | N9: =IF(OR($D9="",$I9="Low",$M9<>CurrentSeason,AND($K9<>"",AsOfDate-$K9>QBStaleDays)),1,0) -> 0
A10: CHI | B10: Caleb Williams | C10: 4.75 | D10: Caleb Williams | E10: 4.75 | F10: =IF(OR($E10="",$C10=""),0,$E10-$C10) -> 0 | G10: =$F10 -> 0 | H10: =ROUND($F10*QBTotFactor,2) -> 0 | I10: High | J10: ESPN exec/scout 2026 QB survey (#10) — TTW scale | K10: 46216 | L10: =IF(ABS($F10)>QBDeltaCap,"⚠ DELTA > CAP — verify",IF($D10="","⚠ ACTIVE QB BLANK",IF($M10<>CurrentSeason,"⚠ NOT REVIEWED FOR "&CurrentSeason,IF(AND($K10<>"",AsOfDate-$K10>QBStaleDays),"⚠ STALE — REVIEW","")))) | M10: 2026 | N10: =IF(OR($D10="",$I10="Low",$M10<>CurrentSeason,AND($K10<>"",AsOfDate-$K10>QBStaleDays)),1,0) -> 0
A11: CIN | B11: Joe Burrow | C11: 5.75 | D11: Joe Burrow | E11: 5.75 | F11: =IF(OR($E11="",$C11=""),0,$E11-$C11) -> 0 | G11: =$F11 -> 0 | H11: =ROUND($F11*QBTotFactor,2) -> 0 | I11: High | J11: ESPN exec/scout 2026 QB survey (top five) — TTW scale | K11: 46216 | L11: =IF(ABS($F11)>QBDeltaCap,"⚠ DELTA > CAP — verify",IF($D11="","⚠ ACTIVE QB BLANK",IF($M11<>CurrentSeason,"⚠ NOT REVIEWED FOR "&CurrentSeason,IF(AND($K11<>"",AsOfDate-$K11>QBStaleDays),"⚠ STALE — REVIEW","")))) | M11: 2026 | N11: =IF(OR($D11="",$I11="Low",$M11<>CurrentSeason,AND($K11<>"",AsOfDate-$K11>QBStaleDays)),1,0) -> 0
A12: CLE | B12: Deshaun Watson | C12: 1 | D12: Deshaun Watson | E12: 1 | F12: =IF(OR($E12="",$C12=""),0,$E12-$C12) -> 0 | G12: =$F12 -> 0 | H12: =ROUND($F12*QBTotFactor,2) -> 0 | I12: Low | J12: Browns camp: Watson/Sanders open; Watson current frontrunner — TTW scale | K12: 46216 | L12: =IF(ABS($F12)>QBDeltaCap,"⚠ DELTA > CAP — verify",IF($D12="","⚠ ACTIVE QB BLANK",IF($M12<>CurrentSeason,"⚠ NOT REVIEWED FOR "&CurrentSeason,IF(AND($K12<>"",AsOfDate-$K12>QBStaleDays),"⚠ STALE — REVIEW","")))) | M12: 2026 | N12: =IF(OR($D12="",$I12="Low",$M12<>CurrentSeason,AND($K12<>"",AsOfDate-$K12>QBStaleDays)),1,0) -> 1
A13: DAL | B13: Dak Prescott | C13: 5 | D13: Dak Prescott | E13: 5 | F13: =IF(OR($E13="",$C13=""),0,$E13-$C13) -> 0 | G13: =$F13 -> 0 | H13: =ROUND($F13*QBTotFactor,2) -> 0 | I13: High | J13: ESPN/PFF 2026 consensus — TTW scale | K13: 46216 | L13: =IF(ABS($F13)>QBDeltaCap,"⚠ DELTA > CAP — verify",IF($D13="","⚠ ACTIVE QB BLANK",IF($M13<>CurrentSeason,"⚠ NOT REVIEWED FOR "&CurrentSeason,IF(AND($K13<>"",AsOfDate-$K13>QBStaleDays),"⚠ STALE — REVIEW","")))) | M13: 2026 | N13: =IF(OR($D13="",$I13="Low",$M13<>CurrentSeason,AND($K13<>"",AsOfDate-$K13>QBStaleDays)),1,0) -> 0
A14: DEN | B14: Bo Nix | C14: 3.75 | D14: Bo Nix | E14: 3.75 | F14: =IF(OR($E14="",$C14=""),0,$E14-$C14) -> 0 | G14: =$F14 -> 0 | H14: =ROUND($F14*QBTotFactor,2) -> 0 | I14: High | J14: PFF/WCG 2026 QB ranking — TTW scale | K14: 46216 | L14: =IF(ABS($F14)>QBDeltaCap,"⚠ DELTA > CAP — verify",IF($D14="","⚠ ACTIVE QB BLANK",IF($M14<>CurrentSeason,"⚠ NOT REVIEWED FOR "&CurrentSeason,IF(AND($K14<>"",AsOfDate-$K14>QBStaleDays),"⚠ STALE — REVIEW","")))) | M14: 2026 | N14: =IF(OR($D14="",$I14="Low",$M14<>CurrentSeason,AND($K14<>"",AsOfDate-$K14>QBStaleDays)),1,0) -> 0
